Workbook
Name cabcolor: [1]OrderForm!$R$15
Name cabcolor: [1]OrderForm!$R$15
Name cabcolor: [2]OrderForm!$Q$15
Name cabprice: [1]OrderForm!$R$16
Name cabprice: [1]OrderForm!$R$16
Name cabprice: [2]OrderForm!$Q$16
Name 物料: #REF!

Sheet Summary Sheet
A1: POWER 38 | L1: Enter information, then, Hide Columns "L" "M" & "N" once finished by selecting the columns and right-clicking, then select "hide columns"
A2: Product | B2: Unit Type | C2: Qty | D2: Unit Price | E2: Total | F2: Total Cabinets | G2: Trim Per Unit | H2: Total Trim | I2: Handles Per Unit | J2: Cabinet Hardware Count | L2: Cabinet Style: | M2: Frameless
A3: =IF(M2="Frameless", "Frameless", "Framed") -> Frameless | B3: 3B2B | C3: 26 | D3: =SUM('Unit Type'!G71:G72) -> 3514.1688 | E3: =C3*D3 -> 91368.389 | F3: ='Unit Type'!C74 -> 442 | G3: ='Unit Type'!C72 -> 27 | H3: =G3*C3 -> 702 | I3: ='Unit Type'!I71 -> 34 | J3: =I3*C3 -> 884 | L3: Cabinet Finish: | M3: Matte White
B4: 3B3BD | C4: 11 | D4: =SUM('Unit Type (2)'!G71:G72) -> 2736.7162 | E4: =C4*D4 -> 30103.878 | F4: ='Unit Type (2)'!C74 -> 154 | G4: ='Unit Type (2)'!C72 -> 19 | H4: =G4*C4 -> 209 | I4: ='Unit Type (2)'!I71 -> 27 | J4: =I4*C4 -> 297 | L4: Box Construction: | M4: Plywood
B5: 3B2B ANSI A | C5: 1 | D5: =SUM('Unit Type (3)'!G71:G72) -> 2578.7314 | E5: =C5*D5 -> 2578.7314 | F5: ='Unit Type (3)'!C74 -> 12 | G5: ='Unit Type (3)'!C72 -> 18 | H5: =G5*C5 -> 18 | I5: ='Unit Type (3)'!I71 -> 27 | J5: =I5*C5 -> 27 | L5: Price Margin: | M5: 0.2
D6: =SUM('Unit Type (4)'!G71:G72) -> 0 | E6: =C6*D6 -> 0 | F6: ='Unit Type (4)'!C74 -> 0 | G6: ='Unit Type (4)'!C72 -> 0 | H6: =G6*C6 -> 0 | I6: ='Unit Type (4)'!I71 -> 0 | J6: =I6*C6 -> 0 | L6: Factor: | M6: =IF('Summary Sheet'!M2:N2="Framed",VLOOKUP(M5,List!B20:C70,2,FALSE),IF('Summary Sheet'!M2:N2="Frameless",VLOOKUP(M5,List!B20:D70,3,FALSE),"Select Cabinet Style")) -> 0.162
D7: =SUM('Unit Type (5)'!G71:G72) -> 0 | E7: =C7*D7 -> 0 | F7: ='Unit Type (5)'!C74 -> 0 | G7: ='Unit Type (5)'!C72 -> 0 | H7: =G7*C7 -> 0 | I7: ='Unit Type (5)'!I71 -> 0 | J7: =I7*C7 -> 0
D8: =SUM('Unit Type (6)'!G71:G72) -> 0 | E8: =C8*D8 -> 0 | F8: ='Unit Type (6)'!C74 -> 0 | G8: ='Unit Type (6)'!C72 -> 0 | H8: =G8*C8 -> 0 | I8: ='Unit Type (6)'!I71 -> 0 | J8: =I8*C8 -> 0 | L8: Handle Price (Per Handle): | M8: 2.75
D9: =SUM('Unit Type (7)'!G71:G72) -> 0 | E9: =C9*D9 -> 0 | F9: ='Unit Type (7)'!C74 -> 0 | G9: ='Unit Type (7)'!C72 -> 0 | H9: =G9*C9 -> 0 | I9: ='Unit Type (7)'!I71 -> 0 | J9: =I9*C9 -> 0 | L9: Build Cost (Per Box): | M9: 20
D10: =SUM('Unit Type (8)'!G71:G72) -> 0 | E10: =C10*D10 -> 0 | F10: ='Unit Type (8)'!C74 -> 0 | G10: ='Unit Type (8)'!C72 -> 0 | H10: =G10*C10 -> 0 | I10: ='Unit Type (8)'!I71 -> 0 | J10: =I10*C10 -> 0 | L10: Shipping Per Unit: | M10: 125
D11: =SUM('Unit Type (9)'!G71:G72) -> 0 | E11: =C11*D11 -> 0 | F11: ='Unit Type (9)'!C74 -> 0 | G11: ='Unit Type (9)'!C72 -> 0 | H11: =G11*C11 -> 0 | I11: ='Unit Type (9)'!I71 -> 0 | J11: =I11*C11 -> 0
D12: =SUM('Unit Type (10)'!G71:G72) -> 0 | E12: =C12*D12 -> 0 | F12: ='Unit Type (10)'!C74 -> 0 | G12: ='Unit Type (10)'!C72 -> 0 | H12: =G12*C12 -> 0 | I12: ='Unit Type (10)'!I71 -> 0 | J12: =I12*C12 -> 0 | L12: Make a copy of this sheet before you begin. OPEN, then SAVE AS your project name. Then fire away! Start by filling out the unit type information, the Summary Sheet will populate as the unit types are completed. You only need to enter the "Unit Type" name and "QTY" on the summary sheet. Leave the "Unit Price", "Total", "Total Cabinets", and "Cabinet Hardware Count" fields alone.
D13: =SUM('Unit Type (11)'!G71:G72) -> 0 | E13: =C13*D13 -> 0 | F13: ='Unit Type (11)'!C74 -> 0 | G13: ='Unit Type (11)'!C72 -> 0 | H13: =G13*C13 -> 0 | I13: ='Unit Type (11)'!I71 -> 0 | J13: =I13*C13 -> 0
D14: =SUM('Unit Type (12)'!G71:G72) -> 0 | E14: =C14*D14 -> 0 | F14: ='Unit Type (12)'!C74 -> 0 | G14: ='Unit Type (12)'!C72 -> 0 | H14: =G14*C14 -> 0 | I14: ='Unit Type (12)'!I71 -> 0 | J14: =I14*C14 -> 0
D15: =SUM('Unit Type (13)'!G71:G72) -> 0 | E15: =C15*D15 -> 0 | F15: ='Unit Type (13)'!C74 -> 0 | G15: ='Unit Type (13)'!C72 -> 0 | H15: =G15*C15 -> 0 | I15: ='Unit Type (13)'!I71 -> 0 | J15: =I15*C15 -> 0
D16: =SUM('Unit Type (14)'!G71:G72) -> 0 | E16: =C16*D16 -> 0 | F16: ='Unit Type (14)'!C74 -> 0 | G16: ='Unit Type (14)'!C72 -> 0 | H16: =G16*C16 -> 0 | I16: ='Unit Type (14)'!I71 -> 0 | J16: =I16*C16 -> 0
D17: =SUM('Unit Type (15)'!G71:G72) -> 0 | E17: =C17*D17 -> 0 | F17: ='Unit Type (15)'!C74 -> 0 | G17: ='Unit Type (15)'!C72 -> 0 | H17: =G17*C17 -> 0 | I17: ='Unit Type (15)'!I71 -> 0 | J17: =I17*C17 -> 0
D18: =SUM('Unit Type (16)'!G71:G72) -> 0 | E18: =C18*D18 -> 0 | F18: ='Unit Type (16)'!C74 -> 0 | G18: ='Unit Type (16)'!C72 -> 0 | H18: =G18*C18 -> 0 | I18: ='Unit Type (16)'!I71 -> 0 | J18: =I18*C18 -> 0
D19: =SUM('Unit Type (17)'!G71:G72) -> 0 | E19: =C19*D19 -> 0 | F19: ='Unit Type (17)'!C74 -> 0 | G19: ='Unit Type (17)'!C72 -> 0 | H19: =G19*C19 -> 0 | I19: ='Unit Type (17)'!I71 -> 0 | J19: =I19*C19 -> 0
D20: =SUM('Unit Type (18)'!G71:G72) -> 0 | E20: =C20*D20 -> 0 | F20: ='Unit Type (18)'!C74 -> 0 | G20: ='Unit Type (18)'!C72 -> 0 | H20: =G20*C20 -> 0 | I20: ='Unit Type (18)'!I71 -> 0 | J20: =I20*C20 -> 0
D21: =SUM('Unit Type (19)'!G71:G72) -> 0 | E21: =C21*D21 -> 0 | F21: ='Unit Type (19)'!C74 -> 0 | G21: ='Unit Type (19)'!C72 -> 0 | H21: =G21*C21 -> 0 | I21: ='Unit Type (19)'!I71 -> 0 | J21: =I21*C21 -> 0
D22: =SUM('Unit Type (20)'!G71:G72) -> 0 | E22: =C22*D22 -> 0 | F22: ='Unit Type (20)'!C74 -> 0 | G22: ='Unit Type (20)'!C72 -> 0 | H22: =G22*C22 -> 0 | I22: ='Unit Type (20)'!I71 -> 0 | J22: =I22*C22 -> 0 | L22: You may hide any extra rows/columns of any extra unit types to make the document more succinct.
D23: =SUM('Unit Type (21)'!G71:G72) -> 0 | E23: =C23*D23 -> 0 | F23: ='Unit Type (21)'!C74 -> 0 | G23: ='Unit Type (21)'!C72 -> 0 | H23: =G23*C23 -> 0 | I23: ='Unit Type (21)'!I71 -> 0 | J23: =I23*C23 -> 0
D24: =SUM('Unit Type (22)'!G71:G72) -> 0 | E24: =C24*D24 -> 0 | F24: ='Unit Type (22)'!C74 -> 0 | G24: ='Unit Type (22)'!C72 -> 0 | H24: =G24*C24 -> 0 | I24: ='Unit Type (22)'!I71 -> 0 | J24: =I24*C24 -> 0
D25: =SUM('Unit Type (23)'!G71:G72) -> 0 | E25: =C25*D25 -> 0 | F25: ='Unit Type (23)'!C74 -> 0 | G25: ='Unit Type (23)'!C72 -> 0 | H25: =G25*C25 -> 0 | I25: ='Unit Type (23)'!I71 -> 0 | J25: =I25*C25 -> 0
D26: =SUM('Unit Type (24)'!G71:G72) -> 0 | E26: =C26*D26 -> 0 | F26: ='Unit Type (24)'!C74 -> 0 | G26: ='Unit Type (24)'!C72 -> 0 | H26: =G26*C26 -> 0 | I26: ='Unit Type (24)'!I71 -> 0 | J26: =I26*C26 -> 0
D27: =SUM('Unit Type (25)'!G71:G72) -> 0 | E27: =C27*D27 -> 0 | F27: ='Unit Type (25)'!C74 -> 0 | G27: ='Unit Type (25)'!C72 -> 0 | H27: =G27*C27 -> 0 | I27: ='Unit Type (25)'!I71 -> 0 | J27: =I27*C27 -> 0
D28: =SUM('Unit Type (26)'!G71:G72) -> 0 | E28: =C28*D28 -> 0 | F28: ='Unit Type (26)'!C74 -> 0 | G28: ='Unit Type (26)'!C72 -> 0 | H28: =G28*C28 -> 0 | I28: ='Unit Type (26)'!I71 -> 0 | J28: =I28*C28 -> 0
D29: =SUM('Unit Type (27)'!G71:G72) -> 0 | E29: =C29*D29 -> 0 | F29: ='Unit Type (27)'!C74 -> 0 | G29: ='Unit Type (27)'!C72 -> 0 | H29: =G29*C29 -> 0 | I29: ='Unit Type (27)'!I71 -> 0 | J29: =I29*C29 -> 0
D30: =SUM('Unit Type (28)'!G71:G72) -> 0 | E30: =C30*D30 -> 0 | F30: ='Unit Type (28)'!C74 -> 0 | G30: ='Unit Type (28)'!C72 -> 0 | H30: =G30*C30 -> 0 | I30: ='Unit Type (28)'!I71 -> 0 | J30: =I30*C30 -> 0
D31: =SUM('Unit Type (29)'!G71:G72) -> 0 | E31: =C31*D31 -> 0 | F31: ='Unit Type (29)'!C74 -> 0 | G31: ='Unit Type (29)'!C72 -> 0 | H31: =G31*C31 -> 0 | I31: ='Unit Type (29)'!I71 -> 0 | J31: =I31*C31 -> 0
D32: =SUM('Unit Type (30)'!G71:G72) -> 0 | E32: =C32*D32 -> 0 | F32: ='Unit Type (30)'!C74 -> 0 | G32: ='Unit Type (30)'!C72 -> 0 | H32: =G32*C32 -> 0 | I32: ='Unit Type (30)'!I71 -> 0 | J32: =I32*C32 -> 0
D33: =SUM('Unit Type (31)'!G71:G72) -> 0 | E33: =C33*D33 -> 0 | F33: ='Unit Type (31)'!C74 -> 0 | G33: ='Unit Type (31)'!C72 -> 0 | H33: =G33*C33 -> 0 | I33: ='Unit Type (31)'!I71 -> 0 | J33: =I33*C33 -> 0
D34: =SUM('Unit Type (32)'!G71:G72) -> 0 | E34: =C34*D34 -> 0 | F34: ='Unit Type (32)'!C74 -> 0 | G34: ='Unit Type (32)'!C72 -> 0 | H34: =G34*C34 -> 0 | I34: ='Unit Type (32)'!I71 -> 0 | J34: =I34*C34 -> 0
D35: =SUM('Unit Type (33)'!G71:G72) -> 0 | E35: =C35*D35 -> 0 | F35: ='Unit Type (33)'!C74 -> 0 | G35: ='Unit Type (33)'!C72 -> 0 | H35: =G35*C35 -> 0 | I35: ='Unit Type (33)'!I71 -> 0 | J35: =I35*C35 -> 0
D36: =SUM('Unit Type (34)'!G71:G72) -> 0 | E36: =C36*D36 -> 0 | F36: ='Unit Type (34)'!C74 -> 0 | G36: ='Unit Type (34)'!C72 -> 0 | H36: =G36*C36 -> 0 | I36: ='Unit Type (34)'!I71 -> 0 | J36: =I36*C36 -> 0
D37: =SUM('Unit Type (35)'!G71:G72) -> 0 | E37: =C37*D37 -> 0 | F37: ='Unit Type (35)'!C74 -> 0 | G37: ='Unit Type (35)'!C72 -> 0 | H37: =G37*C37 -> 0 | I37: ='Unit Type (35)'!I71 -> 0 | J37: =I37*C37 -> 0
D38: =SUM('Unit Type (36)'!G71:G72) -> 0 | E38: =C38*D38 -> 0 | F38: ='Unit Type (36)'!C74 -> 0 | G38: ='Unit Type (36)'!C72 -> 0 | H38: =G38*C38 -> 0 | I38: ='Unit Type (36)'!I71 -> 0 | J38: =I38*C38 -> 0
D39: =SUM('Unit Type (37)'!G71:G72) -> 0 | E39: =C39*D39 -> 0 | F39: ='Unit Type (37)'!C74 -> 0 | G39: ='Unit Type (37)'!C72 -> 0 | H39: =G39*C39 -> 0 | I39: ='Unit Type (37)'!I71 -> 0 | J39: =I39*C39 -> 0
D40: =SUM('Unit Type (38)'!G71:G72) -> 0 | E40: =C40*D40 -> 0 | F40: ='Unit Type (38)'!C74 -> 0 | G40: ='Unit Type (38)'!C72 -> 0 | H40: =G40*C40 -> 0 | I40: ='Unit Type (38)'!I71 -> 0 | J40: =I40*C40 -> 0
D41: =SUM('Unit Type (39)'!G71:G72) -> 0 | E41: =C41*D41 -> 0 | F41: ='Unit Type (39)'!C74 -> 0 | G41: ='Unit Type (39)'!C72 -> 0 | H41: =G41*C41 -> 0 | I41: ='Unit Type (39)'!I71 -> 0 | J41: =I41*C41 -> 0
D42: =SUM('Unit Type (40)'!G71:G72) -> 0 | E42: =C42*D42 -> 0 | F42: ='Unit Type (40)'!C74 -> 0 | G42: ='Unit Type (40)'!C72 -> 0 | H42: =G42*C42 -> 0 | I42: ='Unit Type (40)'!I71 -> 0 | J42: =I42*C42 -> 0
D43: =SUM('Unit Type (41)'!G71:G72) -> 0 | E43: =C43*D43 -> 0 | F43: ='Unit Type (41)'!C74 -> 0 | G43: ='Unit Type (41)'!C72 -> 0 | H43: =G43*C43 -> 0 | I43: ='Unit Type (41)'!I71 -> 0 | J43: =I43*C43 -> 0
D44: =SUM('Unit Type (42)'!G71:G72) -> 0 | E44: =C44*D44 -> 0 | F44: ='Unit Type (42)'!C74 -> 0 | G44: ='Unit Type (42)'!C72 -> 0 | H44: =G44*C44 -> 0 | I44: ='Unit Type (42)'!I71 -> 0 | J44: =I44*C44 -> 0
D45: =SUM('Unit Type (43)'!G71:G72) -> 0 | E45: =C45*D45 -> 0 | F45: ='Unit Type (43)'!C74 -> 0 | G45: ='Unit Type (43)'!C72 -> 0 | H45: =G45*C45 -> 0 | I45: ='Unit Type (43)'!I71 -> 0 | J45: =I45*C45 -> 0
D46: =SUM('Unit Type (44)'!G71:G72) -> 0 | E46: =C46*D46 -> 0 | F46: ='Unit Type (44)'!C74 -> 0 | G46: ='Unit Type (44)'!C72 -> 0 | H46: =G46*C46 -> 0 | I46: ='Unit Type (44)'!I71 -> 0 | J46: =I46*C46 -> 0
D47: =SUM('Unit Type (45)'!G71:G72) -> 0 | E47: =C47*D47 -> 0 | F47: ='Unit Type (45)'!C74 -> 0 | G47: ='Unit Type (45)'!C72 -> 0 | H47: =G47*C47 -> 0 | I47: ='Unit Type (45)'!I71 -> 0 | J47: =I47*C47 -> 0
D48: =SUM('Unit Type (46)'!G71:G72) -> 0 | E48: =C48*D48 -> 0 | F48: ='Unit Type (46)'!C74 -> 0 | G48: ='Unit Type (46)'!C72 -> 0 | H48: =G48*C48 -> 0 | I48: ='Unit Type (46)'!I71 -> 0 | J48: =I48*C48 -> 0
D49: =SUM('Unit Type (47)'!G71:G72) -> 0 | E49: =C49*D49 -> 0 | F49: ='Unit Type (47)'!C74 -> 0 | G49: ='Unit Type (47)'!C72 -> 0 | H49: =G49*C49 -> 0 | I49: ='Unit Type (47)'!I71 -> 0 | J49: =I49*C49 -> 0
D50: =SUM('Unit Type (48)'!G71:G72) -> 0 | E50: =C50*D50 -> 0 | F50: ='Unit Type (48)'!C74 -> 0 | G50: ='Unit Type (48)'!C72 -> 0 | H50: =G50*C50 -> 0 | I50: ='Unit Type (48)'!I71 -> 0 | J50: =I50*C50 -> 0
D51: =SUM('Unit Type (49)'!G71:G72) -> 0 | E51: =C51*D51 -> 0 | F51: ='Unit Type (49)'!C74 -> 0 | G51: ='Unit Type (49)'!C72 -> 0 | H51: =G51*C51 -> 0 | I51: ='Unit Type (49)'!I71 -> 0 | J51: =I51*C51 -> 0
D52: =SUM('Unit Type (50)'!G71:G72) -> 0 | E52: =C52*D52 -> 0 | F52: ='Unit Type (50)'!C74 -> 0 | G52: ='Unit Type (50)'!C72 -> 0 | H52: =G52*C52 -> 0 | I52: ='Unit Type (50)'!I71 -> 0 | J52: =I52*C52 -> 0
C54: =SUM(C3:C41) -> 38 | D54: Cabinets | E54: =SUM(E3:E53) -> 124051 | F54: =SUM(F3:F52) -> 608 | H54: =SUM(H3:H42) -> 929 | J54: =SUM(J3:J53) -> 1208
D55: Handles | E55: =J54*M8 -> 3322
D56: Build cost | E56: =F54*M9 -> 12160 | L56: Total Cabinets + Trim: | M56: =H54+F54 -> 1537
D57: Shipping | E57: =C54*M10 -> 4750
D58: Total | E58: =SUM(E54:E57) -> 144283
B59: (ALTERNATE BELOW)
B60: Cabinet Installation | D60: Total | E60: =F54*79 -> 48032
D61: Grand Total | E61: =E60+E58 -> 192315
B62: 1)General Specifications:
B63: A. Door Material: HDF | D63: E. Drawer runner: SOLID WOOD DOVETAILED
B64: =CONCATENATE("B. Box Material: ", M4, " with maple finish") -> B. Box Material: Plywood with maple finish | D64: E.1. undermount softclose
B65: C. Shelves: Plywood | D65: =CONCATENATE("G. Door style: ",M3) -> G. Door style: Matte White
B66: D. Hinge: DTC soft close

Sheet Framed Catalog List Price
C2: ONYX BLACK | E2: WHITE SHAKER | G2: ESPRESSO SHAKER | I2: SIGNATURE BLUE | K2: Grey Shaker | M2: Uptown White | O2: Modern Slate | Q2: Dark Green Slim Shaker
A3: Description | B3: Cabinet Name | C3: List Price | D3: Inventory Code | E3: List Price | F3: Inventory Code | G3: List Price | H3: Inventory Code | I3: List Price | J3: Inventory Code | K3: List Price | L3: Inventory Code | M3: List Price | N3: Inventory Code | O3: List Price | P3: Inventory Code | Q3: List Price | R3: Inventory Code
A4: Base Cabinets with Drawer, 24" Depth
A5: 9" Base Cabinet: 1 Door & 1 Drawer | B5: B09 | C5: 476 | D5: =CONCATENATE("ONB-",B5) -> ONB-B09 | E5: 433 | F5: =CONCATENATE("WHS-",B5) -> WHS-B09 | G5: 476 | H5: =CONCATENATE("ESS-",B5) -> ESS-B09 | I5: 476 | J5: =CONCATENATE("SIB-",B5) -> SIB-B09 | K5: 433 | L5: =CONCATENATE("GRS-",B5) -> GRS-B09 | M5: 476 | N5: =CONCATENATE("UPB-",B5) -> UPB-B09 | O5: 476 | P5: =CONCATENATE("MSL-",B5) -> MSL-B09 | Q5: 476 | R5: =CONCATENATE("DGS-",B5) -> DGS-B09 | S5: 2
A6: 12" Base Cabinet: 1 Door & 1 Drawer | B6: B12 | C6: 618 | D6: =CONCATENATE("ONB-",B6) -> ONB-B12 | E6: 562 | F6: =CONCATENATE("WHS-",B6) -> WHS-B12 | G6: 618 | H6: =CONCATENATE("ESS-",B6) -> ESS-B12 | I6: 618 | J6: =CONCATENATE("SIB-",B6) -> SIB-B12 | K6: 562 | L6: =CONCATENATE("GRS-",B6) -> GRS-B12 | M6: 618 | N6: =CONCATENATE("UPB-",B6) -> UPB-B12 | O6: 618 | P6: =CONCATENATE("MSL-",B6) -> MSL-B12 | Q6: 618 | R6: =CONCATENATE("DGS-",B6) -> DGS-B12 | S6: 2
A7: 15" Base Cabinet: 1 Door & 1 Drawer | B7: B15 | C7: 677 | D7: =CONCATENATE("ONB-",B7) -> ONB-B15 | E7: 615 | F7: =CONCATENATE("WHS-",B7) -> WHS-B15 | G7: 677 | H7: =CONCATENATE("ESS-",B7) -> ESS-B15 | I7: 677 | J7: =CONCATENATE("SIB-",B7) -> SIB-B15 | K7: 615 | L7: =CONCATENATE("GRS-",B7) -> GRS-B15 | M7: 677 | N7: =CONCATENATE("UPB-",B7) -> UPB-B15 | O7: 677 | P7: =CONCATENATE("MSL-",B7) -> MSL-B15 | Q7: 677 | R7: =CONCATENATE("DGS-",B7) -> DGS-B15 | S7: 2
A8: 18" Base Cabinet: 1 Door & 1 Drawer | B8: B18 | C8: 706 | D8: =CONCATENATE("ONB-",B8) -> ONB-B18 | E8: 642 | F8: =CONCATENATE("WHS-",B8) -> WHS-B18 | G8: 706 | H8: =CONCATENATE("ESS-",B8) -> ESS-B18 | I8: 706 | J8: =CONCATENATE("SIB-",B8) -> SIB-B18 | K8: 642 | L8: =CONCATENATE("GRS-",B8) -> GRS-B18 | M8: 706 | N8: =CONCATENATE("UPB-",B8) -> UPB-B18 | O8: 706 | P8: =CONCATENATE("MSL-",B8) -> MSL-B18 | Q8: 706 | R8: =CONCATENATE("DGS-",B8) -> DGS-B18 | S8: 2
A9: 18" Base Trash Cabinet: 1 Door & 1 Drawer with two 27 qt. Trash Cans | B9: BWBK18-2 | C9: 1311 | D9: =CONCATENATE("ONB-",B9) -> ONB-BWBK18-2 | E9: 1192 | F9: =CONCATENATE("WHS-",B9) -> WHS-BWBK18-2 | G9: 1311 | H9: =CONCATENATE("ESS-",B9) -> ESS-BWBK18-2 | I9: 1311 | J9: =CONCATENATE("SIB-",B9) -> SIB-BWBK18-2 | K9: 1192 | L9: =CONCATENATE("GRS-",B9) -> GRS-BWBK18-2 | M9: 1311 | N9: =CONCATENATE("UPB-",B9) -> UPB-BWBK18-2 | O9: 1311 | P9: =CONCATENATE("MSL-",B9) -> MSL-BWBK18-2 | Q9: 1311 | R9: =CONCATENATE("DGS-",B9) -> DGS-BWBK18-2 | S9: 2
A10: 21" Base Cabinet: 1 Door & 1 Drawer | B10: B21 | C10: 754 | D10: =CONCATENATE("ONB-",B10) -> ONB-B21 | E10: 685 | F10: =CONCATENATE("WHS-",B10) -> WHS-B21 | G10: 754 | H10: =CONCATENATE("ESS-",B10) -> ESS-B21 | I10: 754 | J10: =CONCATENATE("SIB-",B10) -> SIB-B21 | K10: 685 | L10: =CONCATENATE("GRS-",B10) -> GRS-B21 | M10: 754 | N10: =CONCATENATE("UPB-",B10) -> UPB-B21 | O10: 754 | P10: =CONCATENATE("MSL-",B10) -> MSL-B21 | Q10: 754 | R10: =CONCATENATE("DGS-",B10) -> DGS-B21 | S10: 2
A11: 24" Base Cabinet: 2 Doors & 1 Drawer | B11: B24 | C11: 806 | D11: =CONCATENATE("ONB-",B11) -> ONB-B24 | E11: 733 | F11: =CONCATENATE("WHS-",B11) -> WHS-B24 | G11: 806 | H11: =CONCATENATE("ESS-",B11) -> ESS-B24 | I11: 806 | J11: =CONCATENATE("SIB-",B11) -> SIB-B24 | K11: 733 | L11: =CONCATENATE("GRS-",B11) -> GRS-B24 | M11: 806 | N11: =CONCATENATE("UPB-",B11) -> UPB-B24 | O11: 806 | P11: =CONCATENATE("MSL-",B11) -> MSL-B24 | Q11: 806 | R11: =CONCATENATE("DGS-",B11) -> DGS-B24 | S11: 3
A12: 27" Base Cabinet: 2 Doors & 1 Drawer | B12: B27 | C12: 971 | D12: =CONCATENATE("ONB-",B12) -> ONB-B27 | E12: 883 | F12: =CONCATENATE("WHS-",B12) -> WHS-B27 | G12: 971 | H12: =CONCATENATE("ESS-",B12) -> ESS-B27 | I12: 971 | J12: =CONCATENATE("SIB-",B12) -> SIB-B27 | K12: 883 | L12: =CONCATENATE("GRS-",B12) -> GRS-B27 | M12: 971 | N12: =CONCATENATE("UPB-",B12) -> UPB-B27 | O12: 971 | P12: =CONCATENATE("MSL-",B12) -> MSL-B27 | Q12: 971 | R12: =CONCATENATE("DGS-",B12) -> DGS-B27 | S12: 3
A13: 30" Base Cabinet: 2 Doors & 1 Drawer | B13: B30 | C13: 1007 | D13: =CONCATENATE("ONB-",B13) -> ONB-B30 | E13: 915 | F13: =CONCATENATE("WHS-",B13) -> WHS-B30 | G13: 1007 | H13: =CONCATENATE("ESS-",B13) -> ESS-B30 | I13: 1007 | J13: =CONCATENATE("SIB-",B13) -> SIB-B30 | K13: 915 | L13: =CONCATENATE("GRS-",B13) -> GRS-B30 | M13: 1007 | N13: =CONCATENATE("UPB-",B13) -> UPB-B30 | O13: 1007 | P13: =CONCATENATE("MSL-",B13) -> MSL-B30 | Q13: 1007 | R13: =CONCATENATE("DGS-",B13) -> DGS-B30 | S13: 3
A14: 33" Base Cabinet: 2 Doors & 2 Drawers | B14: B33 | C14: 1054 | D14: =CONCATENATE("ONB-",B14) -> ONB-B33 | E14: 958 | F14: =CONCATENATE("WHS-",B14) -> WHS-B33 | G14: 1054 | H14: =CONCATENATE("ESS-",B14) -> ESS-B33 | I14: 1054 | J14: =CONCATENATE("SIB-",B14) -> SIB-B33 | K14: 958 | L14: =CONCATENATE("GRS-",B14) -> GRS-B33 | M14: 1054 | N14: =CONCATENATE("UPB-",B14) -> UPB-B33 | O14: 1054 | P14: =CONCATENATE("MSL-",B14) -> MSL-B33 | Q14: 1054 | R14: =CONCATENATE("DGS-",B14) -> DGS-B33 | S14: 3
A15: 36" Base Cabinet: 2 Doors & 2 Drawers | B15: B36 | C15: 1095 | D15: =CONCATENATE("ONB-",B15) -> ONB-B36 | E15: 995 | F15: =CONCATENATE("WHS-",B15) -> WHS-B36 | G15: 1095 | H15: =CONCATENATE("ESS-",B15) -> ESS-B36 | I15: 1095 | J15: =CONCATENATE("SIB-",B15) -> SIB-B36 | K15: 995 | L15: =CONCATENATE("GRS-",B15) -> GRS-B36 | M15: 1095 | N15: =CONCATENATE("UPB-",B15) -> UPB-B36 | O15: 1095 | P15: =CONCATENATE("MSL-",B15) -> MSL-B36 | Q15: 1095 | R15: =CONCATENATE("DGS-",B15) -> DGS-B36 | S15: 4
A16: 42" Base Cabinet: 2 Doors & 2 Drawers | B16: B42 | C16: 1330 | D16: =CONCATENATE("ONB-",B16) -> ONB-B42 | E16: 1209 | F16: =CONCATENATE("WHS-",B16) -> WHS-B42 | G16: 1330 | H16: =CONCATENATE("ESS-",B16) -> ESS-B42 | I16: 1330 | J16: =CONCATENATE("SIB-",B16) -> SIB-B42 | K16: 1209 | L16: =CONCATENATE("GRS-",B16) -> GRS-B42 | M16: 1330 | N16: =CONCATENATE("UPB-",B16) -> UPB-B42 | O16: 1330 | P16: =CONCATENATE("MSL-",B16) -> MSL-B42 | Q16: 1330 | R16: =CONCATENATE("DGS-",B16) -> DGS-B42 | S16: 4
A17: Base Cabinets with Full Height Door, 24" Depth
A18: 9" Base Cabinet: 1 Full-height Door | B18: B09FHD | C18: 421 | D18: =CONCATENATE("ONB-",B18) -> ONB-B09FHD | E18: 383 | F18: =CONCATENATE("WHS-",B18) -> WHS-B09FHD | G18: 421 | H18: =CONCATENATE("ESS-",B18) -> ESS-B09FHD | I18: 421 | J18: =CONCATENATE("SIB-",B18) -> SIB-B09FHD | K18: 383 | L18: =CONCATENATE("GRS-",B18) -> GRS-B09FHD | M18: 421 | N18: =CONCATENATE("UPB-",B18) -> UPB-B09FHD | O18: 421 | P18: =CONCATENATE("MSL-",B18) -> MSL-B09FHD | Q18: 421 | R18: =CONCATENATE("DGS-",B18) -> DGS-B09FHD | S18: 1
A19: 24" Base Cabinet: 2 Full-height Doors | B19: B24FHD | C19: 751 | D19: =CONCATENATE("ONB-",B19) -> ONB-B24FHD | E19: 683 | F19: =CONCATENATE("WHS-",B19) -> WHS-B24FHD | G19: 751 | H19: =CONCATENATE("ESS-",B19) -> ESS-B24FHD | I19: 751 | J19: =CONCATENATE("SIB-",B19) -> SIB-B24FHD | K19: 683 | L19: =CONCATENATE("GRS-",B19) -> GRS-B24FHD | M19: 751 | N19: =CONCATENATE("UPB-",B19) -> UPB-B24FHD | O19: 751 | P19: =CONCATENATE("MSL-",B19) -> MSL-B24FHD | Q19: 751 | R19: =CONCATENATE("DGS-",B19) -> DGS-B24FHD | S19: 2
A20: 3 Drawer Base Cabinets, 24" Depth
A21: 12" Base Cabinet: 3 Drawers, Drawers are 7", 11" and 11" tall | B21: 3DB12 | C21: 883 | D21: =CONCATENATE("ONB-",B21) -> ONB-3DB12 | E21: 803 | F21: =CONCATENATE("WHS-",B21) -> WHS-3DB12 | G21: 883 | H21: =CONCATENATE("ESS-",B21) -> ESS-3DB12 | I21: 883 | J21: =CONCATENATE("SIB-",B21) -> SIB-3DB12 | K21: 803 | L21: =CONCATENATE("GRS-",B21) -> GRS-3DB12 | M21: 883 | N21: =CONCATENATE("UPB-",B21) -> UPB-3DB12 | O21: 883 | P21: =CONCATENATE("MSL-",B21) -> MSL-3DB12 | Q21: 883 | R21: =CONCATENATE("DGS-",B21) -> DGS-3DB12 | S21: 3
A22: 15" Base Cabinet: 3 Drawers, Drawers are 7", 11" and 11" tall | B22: 3DB15 | C22: 942 | D22: =CONCATENATE("ONB-",B22) -> ONB-3DB15 | E22: 856 | F22: =CONCATENATE("WHS-",B22) -> WHS-3DB15 | G22: 942 | H22: =CONCATENATE("ESS-",B22) -> ESS-3DB15 | I22: 942 | J22: =CONCATENATE("SIB-",B22) -> SIB-3DB15 | K22: 856 | L22: =CONCATENATE("GRS-",B22) -> GRS-3DB15 | M22: 942 | N22: =CONCATENATE("UPB-",B22) -> UPB-3DB15 | O22: 942 | P22: =CONCATENATE("MSL-",B22) -> MSL-3DB15 | Q22: 942 | R22: =CONCATENATE("DGS-",B22) -> DGS-3DB15 | S22: 3
A23: 18" Base Cabinet: 3 Drawers, Drawers are 7", 11" and 11" tall | B23: 3DB18 | C23: 982 | D23: =CONCATENATE("ONB-",B23) -> ONB-3DB18 | E23: 893 | F23: =CONCATENATE("WHS-",B23) -> WHS-3DB18 | G23: 982 | H23: =CONCATENATE("ESS-",B23) -> ESS-3DB18 | I23: 982 | J23: =CONCATENATE("SIB-",B23) -> SIB-3DB18 | K23: 893 | L23: =CONCATENATE("GRS-",B23) -> GRS-3DB18 | M23: 982 | N23: =CONCATENATE("UPB-",B23) -> UPB-3DB18 | O23: 982 | P23: =CONCATENATE("MSL-",B23) -> MSL-3DB18 | Q23: 982 | R23: =CONCATENATE("DGS-",B23) -> DGS-3DB18 | S23: 3
A24: 21" Base Cabinet: 3 Drawers, Drawers are 7", 11" and 11" tall | B24: 3DB21 | C24: 1024 | D24: =CONCATENATE("ONB-",B24) -> ONB-3DB21 | E24: 931 | F24: =CONCATENATE("WHS-",B24) -> WHS-3DB21 | G24: 1024 | H24: =CONCATENATE("ESS-",B24) -> ESS-3DB21 | I24: 1024 | J24: =CONCATENATE("SIB-",B24) -> SIB-3DB21 | K24: 931 | L24: =CONCATENATE("GRS-",B24) -> GRS-3DB21 | M24: 1024 | N24: =CONCATENATE("UPB-",B24) -> UPB-3DB21 | O24: 1024 | P24: =CONCATENATE("MSL-",B24) -> MSL-3DB21 | Q24: 1024 | R24: =CONCATENATE("DGS-",B24) -> DGS-3DB21 | S24: 3
A25: 24" Base Cabinet: 3 Drawers, Drawers are 7", 11" and 11" tall | B25: 3DB24 | C25: 1071 | D25: =CONCATENATE("ONB-",B25) -> ONB-3DB24 | E25: 974 | F25: =CONCATENATE("WHS-",B25) -> WHS-3DB24 | G25: 1071 | H25: =CONCATENATE("ESS-",B25) -> ESS-3DB24 | I25: 1071 | J25: =CONCATENATE("SIB-",B25) -> SIB-3DB24 | K25: 974 | L25: =CONCATENATE("GRS-",B25) -> GRS-3DB24 | M25: 1071 | N25: =CONCATENATE("UPB-",B25) -> UPB-3DB24 | O25: 1071 | P25: =CONCATENATE("MSL-",B25) -> MSL-3DB24 | Q25: 1071 | R25: =CONCATENATE("DGS-",B25) -> DGS-3DB24 | S25: 3
A26: 30" Base Cabinet: 3 Drawers, Drawers are 7", 11" and 11" tall | B26: 3DB30 | C26: 1172 | D26: =CONCATENATE("ONB-",B26) -> ONB-3DB30 | E26: 1065 | F26: =CONCATENATE("WHS-",B26) -> WHS-3DB30 | G26: 1172 | H26: =CONCATENATE("ESS-",B26) -> ESS-3DB30 | I26: 1172 | J26: =CONCATENATE("SIB-",B26) -> SIB-3DB30 | K26: 1065 | L26: =CONCATENATE("GRS-",B26) -> GRS-3DB30 | M26: 1172 | N26: =CONCATENATE("UPB-",B26) -> UPB-3DB30 | O26: 1172 | P26: =CONCATENATE("MSL-",B26) -> MSL-3DB30 | Q26: 1172 | R26: =CONCATENATE("DGS-",B26) -> DGS-3DB30 | S26: 3
A27: 36" Base Cabinet: 3 Drawers, Drawers are 7", 11" and 11" tall | B27: 3DB36 | C27: 1312 | D27: =CONCATENATE("ONB-",B27) -> ONB-3DB36 | E27: 1193 | F27: =CONCATENATE("WHS-",B27) -> WHS-3DB36 | G27: 1312 | H27: =CONCATENATE("ESS-",B27) -> ESS-3DB36 | I27: 1312 | J27: =CONCATENATE("SIB-",B27) -> SIB-3DB36 | K27: 1193 | L27: =CONCATENATE("GRS-",B27) -> GRS-3DB36 | M27: 1312 | N27: =CONCATENATE("UPB-",B27) -> UPB-3DB36 | O27: 1312 | P27: =CONCATENATE("MSL-",B27) -> MSL-3DB36 | Q27: 1312 | R27: =CONCATENATE("DGS-",B27) -> DGS-3DB36 | S27: 3
A28: 2 Drawer Base Cabinets, 24" Depth
A29: 24" Base Cabinet: 2 Drawers, Drawers are 14.5" tall | B29: 2DB24 | C29: 1071 | D29: =CONCATENATE("ONB-",B29) -> ONB-2DB24 | E29: 974 | F29: =CONCATENATE("WHS-",B29) -> WHS-2DB24 | G29: 1071 | H29: =CONCATENATE("ESS-",B29) -> ESS-2DB24 | I29: 1071 | J29: =CONCATENATE("SIB-",B29) -> SIB-2DB24 | K29: 974 | L29: =CONCATENATE("GRS-",B29) -> GRS-2DB24 | M29: 1071 | N29: =CONCATENATE("UPB-",B29) -> UPB-2DB24 | O29: 1071 | P29: =CONCATENATE("MSL-",B29) -> MSL-2DB24 | Q29: 1071 | R29: =CONCATENATE("DGS-",B29) -> DGS-2DB24 | S29: 2
A30: 30" Base Cabinet: 2 Drawers, Drawers are 14.5" tall | B30: 2DB30 | C30: 1172 | D30: =CONCATENATE("ONB-",B30) -> ONB-2DB30 | E30: 1065 | F30: =CONCATENATE("WHS-",B30) -> WHS-2DB30 | G30: 1172 | H30: =CONCATENATE("ESS-",B30) -> ESS-2DB30 | I30: 1172 | J30: =CONCATENATE("SIB-",B30) -> SIB-2DB30 | K30: 1065 | L30: =CONCATENATE("GRS-",B30) -> GRS-2DB30 | M30: 1172 | N30: =CONCATENATE("UPB-",B30) -> UPB-2DB30 | O30: 1172 | P30: =CONCATENATE("MSL-",B30) -> MSL-2DB30 | Q30: 1172 | R30: =CONCATENATE("DGS-",B30) -> DGS-2DB30 | S30: 2
A31: 36" Base Cabinet: 2 Drawers, Drawers are 14.5" tall | B31: 2DB36 | C31: 1312 | D31: =CONCATENATE("ONB-",B31) -> ONB-2DB36 | E31: 1193 | F31: =CONCATENATE("WHS-",B31) -> WHS-2DB36 | G31: 1312 | H31: =CONCATENATE("ESS-",B31) -> ESS-2DB36 | I31: 1312 | J31: =CONCATENATE("SIB-",B31) -> SIB-2DB36 | K31: 1193 | L31: =CONCATENATE("GRS-",B31) -> GRS-2DB36 | M31: 1312 | N31: =CONCATENATE("UPB-",B31) -> UPB-2DB36 | O31: 1312 | P31: =CONCATENATE("MSL-",B31) -> MSL-2DB36 | Q31: 1312 | R31: =CONCATENATE("DGS-",B31) -> DGS-2DB36 | S31: 2
A32: Sink Base Cabinets, 24" Depth
A33: 30" Base Cabinet: 2 Doors & 1 False Drawer | B33: SB30 | C33: 741 | D33: =CONCATENATE("ONB-",B33) -> ONB-SB30 | E33: 674 | F33: =CONCATENATE("WHS-",B33) -> WHS-SB30 | G33: 741 | H33: =CONCATENATE("ESS-",B33) -> ESS-SB30 | I33: 741 | J33: =CONCATENATE("SIB-",B33) -> SIB-SB30 | K33: 674 | L33: =CONCATENATE("GRS-",B33) -> GRS-SB30 | M33: 741 | N33: =CONCATENATE("UPB-",B33) -> UPB-SB30 | O33: 741 | P33: =CONCATENATE("MSL-",B33) -> MSL-SB30 | Q33: 741 | R33: =CONCATENATE("DGS-",B33) -> DGS-SB30 | S33: 2
A34: 33" Base Cabinet: 2 Doors & 1 False Drawer | B34: SB33 | C34: 794 | D34: =CONCATENATE("ONB-",B34) -> ONB-SB33 | E34: 722 | F34: =CONCATENATE("WHS-",B34) -> WHS-SB33 | G34: 794 | H34: =CONCATENATE("ESS-",B34) -> ESS-SB33 | I34: 794 | J34: =CONCATENATE("SIB-",B34) -> SIB-SB33 | K34: 722 | L34: =CONCATENATE("GRS-",B34) -> GRS-SB33 | M34: 794 | N34: =CONCATENATE("UPB-",B34) -> UPB-SB33 | O34: 794 | P34: =CONCATENATE("MSL-",B34) -> MSL-SB33 | Q34: 794 | R34: =CONCATENATE("DGS-",B34) -> DGS-SB33 | S34: 2
A35: 36" Base Cabinet: 2 Doors & 2 False Drawers | B35: SB36 | C35: 812 | D35: =CONCATENATE("ONB-",B35) -> ONB-SB36 | E35: 738 | F35: =CONCATENATE("WHS-",B35) -> WHS-SB36 | G35: 812 | H35: =CONCATENATE("ESS-",B35) -> ESS-SB36 | I35: 812 | J35: =CONCATENATE("SIB-",B35) -> SIB-SB36 | K35: 738 | L35: =CONCATENATE("GRS-",B35) -> GRS-SB36 | M35: 812 | N35: =CONCATENATE("UPB-",B35) -> UPB-SB36 | O35: 812 | P35: =CONCATENATE("MSL-",B35) -> MSL-SB36 | Q35: 812 | R35: =CONCATENATE("DGS-",B35) -> DGS-SB36 | S35: 2
A36: 42" Base Cabinet: 2 Doors & 2 False Drawers | B36: SB42 | C36: 883 | D36: =CONCATENATE("ONB-",B36) -> ONB-SB42 | E36: 803 | F36: =CONCATENATE("WHS-",B36) -> WHS-SB42 | G36: 883 | H36: =CONCATENATE("ESS-",B36) -> ESS-SB42 | I36: 883 | J36: =CONCATENATE("SIB-",B36) -> SIB-SB42 | K36: 803 | L36: =CONCATENATE("GRS-",B36) -> GRS-SB42 | M36: 883 | N36: =CONCATENATE("UPB-",B36) -> UPB-SB42 | O36: 883 | P36: =CONCATENATE("MSL-",B36) -> MSL-SB42 | Q36: 883 | R36: =CONCATENATE("DGS-",B36) -> DGS-SB42 | S36: 2
A37: Farm Sink Base Cabinet, 24" Depth
A38: 36" Base Cabinet: 2 Doors & 33" W x 10" Opening for Sink | B38: FSM36 | C38: 880 | D38: =CONCATENATE("ONB-",B38) -> ONB-FSM36 | E38: 800 | F38: =CONCATENATE("WHS-",B38) -> WHS-FSM36 | G38: 880 | H38: =CONCATENATE("ESS-",B38) -> ESS-FSM36 | I38: 880 | J38: =CONCATENATE("SIB-",B38) -> SIB-FSM36 | K38: 800 | L38: =CONCATENATE("GRS-",B38) -> GRS-FSM36 | M38: 880 | N38: =CONCATENATE("UPB-",B38) -> UPB-FSM36 | O38: 880 | P38: =CONCATENATE("MSL-",B38) -> MSL-FSM36 | Q38: 880 | R38: =CONCATENATE("DGS-",B38) -> DGS-FSM36 | S38: 2
A39: Corner Sink Base Cabinet, 24" Depth
A40: 42" Base Cabinet: 1 24" Door, fits in a 42" x 42" corner space | B40: CSB42 | C40: 982 | D40: =CONCATENATE("ONB-",B40) -> ONB-CSB42 | E40: 893 | F40: =CONCATENATE("WHS-",B40) -> WHS-CSB42 | G40: 982 | H40: =CONCATENATE("ESS-",B40) -> ESS-CSB42 | I40: 982 | J40: =CONCATENATE("SIB-",B40) -> SIB-CSB42 | K40: 893 | L40: =CONCATENATE("GRS-",B40) -> GRS-CSB42 | M40: 982 | N40: =CONCATENATE("UPB-",B40) -> UPB-CSB42 | O40: 982 | P40: =CONCATENATE("MSL-",B40) -> MSL-CSB42 | Q40: 982 | R40: =CONCATENATE("DGS-",B40) -> DGS-CSB42 | S40: 2
A41: Corner Base Cabinets, 24" Depth
A42: 36" Base Cabinet: 2 Doors, Turntable, fits in a 36" x 36" corner space | B42: BLS36-SP | C42: 1165 | D42: =CONCATENATE("ONB-",B42) -> ONB-BLS36-SP | E42: 1059 | F42: =CONCATENATE("WHS-",B42) -> WHS-BLS36-SP | G42: 1165 | H42: =CONCATENATE("ESS-",B42) -> ESS-BLS36-SP | I42: 1165 | J42: =CONCATENATE("SIB-",B42) -> SIB-BLS36-SP | K42: 1059 | L42: =CONCATENATE("GRS-",B42) -> GRS-BLS36-SP | M42: 1165 | N42: =CONCATENATE("UPB-",B42) -> UPB-BLS36-SP | O42: 1165 | P42: =CONCATENATE("MSL-",B42) -> MSL-BLS36-SP | Q42: 1165 | R42: =CONCATENATE("DGS-",B42) -> DGS-BLS36-SP | S42: 1
A43: 42" Base Cabinet: 1 Door & 1 Drawer, Reversible, requires at least 3" pull | B43: BBC42 | C43: 1036 | D43: =CONCATENATE("ONB-",B43) -> ONB-BBC42 | E43: 942 | F43: =CONCATENATE("WHS-",B43) -> WHS-BBC42 | G43: 1036 | H43: =CONCATENATE("ESS-",B43) -> ESS-BBC42 | I43: 1036 | J43: =CONCATENATE("SIB-",B43) -> SIB-BBC42 | K43: 942 | L43: =CONCATENATE("GRS-",B43) -> GRS-BBC42 | M43: 1036 | N43: =CONCATENATE("UPB-",B43) -> UPB-BBC42 | O43: 1036 | P43: =CONCATENATE("MSL-",B43) -> MSL-BBC42 | Q43: 1036 | R43: =CONCATENATE("DGS-",B43) -> DGS-BBC42 | S43: 2
A44: Spice Base Cabinets, 24" Depth
A45: 6" Base Cabinet: 5 Drawers, No soft close, No drawer guides | B45: BWRC6 | C45: 517 | D45: =CONCATENATE("ONB-",B45) -> ONB-BWRC6 | E45: 470 | F45: =CONCATENATE("WHS-",B45) -> WHS-BWRC6 | G45: 517 | H45: =CONCATENATE("ESS-",B45) -> ESS-BWRC6 | I45: 517 | J45: =CONCATENATE("SIB-",B45) -> SIB-BWRC6 | K45: 470 | L45: =CONCATENATE("GRS-",B45) -> GRS-BWRC6 | M45: 517 | N45: =CONCATENATE("UPB-",B45) -> UPB-BWRC6 | O45: 517 | P45: =CONCATENATE("MSL-",B45) -> MSL-BWRC6 | Q45: 517 | R45: =CONCATENATE("DGS-",B45) -> DGS-BWRC6 | S45: 0
A46: 9" Base Cabinet: 1 Door with pullout, Three 4" wide levels | B46: SP09 | C46: 494 | D46: =CONCATENATE("ONB-",B46) -> ONB-SP09 | E46: 449 | F46: =CONCATENATE("WHS-",B46) -> WHS-SP09 | G46: 494 | H46: =CONCATENATE("ESS-",B46) -> ESS-SP09 | I46: 494 | J46: =CONCATENATE("SIB-",B46) -> SIB-SP09 | K46: 449 | L46: =CONCATENATE("GRS-",B46) -> GRS-SP09 | M46: 494 | N46: =CONCATENATE("UPB-",B46) -> UPB-SP09 | O46: 494 | P46: =CONCATENATE("MSL-",B46) -> MSL-SP09 | Q46: 494 | R46: =CONCATENATE("DGS-",B46) -> DGS-SP09 | S46: 1
A47: Base End Cabinets, 24" Depth
A48: 24" Base Cabinet: 2 Doors & 2 False Drawers | B48: BEC24 | C48: 1030 | D48: =CONCATENATE("ONB-",B48) -> ONB-BEC24 | E48: 936 | F48: =CONCATENATE("WHS-",B48) -> WHS-BEC24 | G48: 1030 | H48: =CONCATENATE("ESS-",B48) -> ESS-BEC24 | I48: 1030 | J48: =CONCATENATE("SIB-",B48) -> SIB-BEC24 | K48: 936 | L48: =CONCATENATE("GRS-",B48) -> GRS-BEC24 | M48: 1030 | N48: =CONCATENATE("UPB-",B48) -> UPB-BEC24 | O48: 1030 | P48: =CONCATENATE("MSL-",B48) -> MSL-BEC24 | Q48: 1030 | R48: =CONCATENATE("DGS-",B48) -> DGS-BEC24 | S48: 2
A49: 9" Base Cabinet: 3 Shelves, Specify Left or Right | B49: BES09L/R | C49: 648 | D49: =CONCATENATE("ONB-",B49) -> ONB-BES09L/R | E49: 589 | F49: =CONCATENATE("WHS-",B49) -> WHS-BES09L/R | G49: 648 | H49: =CONCATENATE("ESS-",B49) -> ESS-BES09L/R | I49: 648 | J49: =CONCATENATE("SIB-",B49) -> SIB-BES09L/R | K49: 589 | L49: =CONCATENATE("GRS-",B49) -> GRS-BES09L/R | M49: 648 | N49: =CONCATENATE("UPB-",B49) -> UPB-BES09L/R | O49: 648 | P49: =CONCATENATE("MSL-",B49) -> MSL-BES09L/R | Q49: 648 | R49: =CONCATENATE("DGS-",B49) -> DGS-BES09L/R | S49: 0
A50: Pantry Cabinets, 24" Depth
A51: 18" Pantry Cabinet: 2 Doors, 18" W x 84" H x 24" D | B51: PC188424 | C51: 1472 | D51: =CONCATENATE("ONB-",B51) -> ONB-PC188424 | E51: 1338 | F51: =CONCATENATE("WHS-",B51) -> WHS-PC188424 | G51: 1472 | H51: =CONCATENATE("ESS-",B51) -> ESS-PC188424 | I51: 1472 | J51: =CONCATENATE("SIB-",B51) -> SIB-PC188424 | K51: 1338 | L51: =CONCATENATE("GRS-",B51) -> GRS-PC188424 | M51: 1472 | N51: =CONCATENATE("UPB-",B51) -> UPB-PC188424 | O51: 1472 | P51: =CONCATENATE("MSL-",B51) -> MSL-PC188424 | Q51: 1472 | R51: =CONCATENATE("DGS-",B51) -> DGS-PC188424 | S51: 2
A52: 18" Pantry Cabinet: 2 Doors, 18" W x 90" H x 24" D | B52: PC189024 | C52: 1577 | D52: =CONCATENATE("ONB-",B52) -> ONB-PC189024 | E52: 1434 | F52: =CONCATENATE("WHS-",B52) -> WHS-PC189024 | G52: 1577 | H52: =CONCATENATE("ESS-",B52) -> ESS-PC189024 | I52: 1577 | J52: =CONCATENATE("SIB-",B52) -> SIB-PC189024 | K52: 1434 | L52: =CONCATENATE("GRS-",B52) -> GRS-PC189024 | M52: 1577 | N52: =CONCATENATE("UPB-",B52) -> UPB-PC189024 | O52: 1577 | P52: =CONCATENATE("MSL-",B52) -> MSL-PC189024 | Q52: 1577 | R52: =CONCATENATE("DGS-",B52) -> DGS-PC189024 | S52: 2
A53: 18" Pantry Cabinet: 2 Doors, 18" W x 96" H x 24" D | B53: PC189624 | C53: 1625 | D53: =CONCATENATE("ONB-",B53) -> ONB-PC189624 | E53: 1477 | F53: =CONCATENATE("WHS-",B53) -> WHS-PC189624 | G53: 1625 | H53: =CONCATENATE("ESS-",B53) -> ESS-PC189624 | I53: 1625 | J53: =CONCATENATE("SIB-",B53) -> SIB-PC189624 | K53: 1477 | L53: =CONCATENATE("GRS-",B53) -> GRS-PC189624 | M53: 1625 | N53: =CONCATENATE("UPB-",B53) -> UPB-PC189624 | O53: 1625 | P53: =CONCATENATE("MSL-",B53) -> MSL-PC189624 | Q53: 1625 | R53: =CONCATENATE("DGS-",B53) -> DGS-PC189624 | S53: 2
A54: 24" Pantry Cabinet: 4 Doors, 24" W x 84" H x 24" D | B54: PC248424 | C54: 1707 | D54: =CONCATENATE("ONB-",B54) -> ONB-PC248424 | E54: 1552 | F54: =CONCATENATE("WHS-",B54) -> WHS-PC248424 | G54: 1707 | H54: =CONCATENATE("ESS-",B54) -> ESS-PC248424 | I54: 1707 | J54: =CONCATENATE("SIB-",B54) -> SIB-PC248424 | K54: 1552 | L54: =CONCATENATE("GRS-",B54) -> GRS-PC248424 | M54: 1707 | N54: =CONCATENATE("UPB-",B54) -> UPB-PC248424 | O54: 1707 | P54: =CONCATENATE("MSL-",B54) -> MSL-PC248424 | Q54: 1707 | R54: =CONCATENATE("DGS-",B54) -> DGS-PC248424 | S54: 4
A55: 24" Pantry Cabinet: 4 Doors, 24" W x 90" H x 24" D | B55: PC249024 | C55: 1806 | D55: =CONCATENATE("ONB-",B55) -> ONB-PC249024 | E55: 1642 | F55: =CONCATENATE("WHS-",B55) -> WHS-PC249024 | G55: 1806 | H55: =CONCATENATE("ESS-",B55) -> ESS-PC249024 | I55: 1806 | J55: =CONCATENATE("SIB-",B55) -> SIB-PC249024 | K55: 1642 | L55: =CONCATENATE("GRS-",B55) -> GRS-PC249024 | M55: 1806 | N55: =CONCATENATE("UPB-",B55) -> UPB-PC249024 | O55: 1806 | P55: =CONCATENATE("MSL-",B55) -> MSL-PC249024 | Q55: 1806 | R55: =CONCATENATE("DGS-",B55) -> DGS-PC249024 | S55: 4
A56: 24" Pantry Cabinet: 4 Doors, 24" W x 96" H x 24" D | B56: PC249624 | C56: 1871 | D56: =CONCATENATE("ONB-",B56) -> ONB-PC249624 | E56: 1701 | F56: =CONCATENATE("WHS-",B56) -> WHS-PC249624 | G56: 1871 | H56: =CONCATENATE("ESS-",B56) -> ESS-PC249624 | I56: 1871 | J56: =CONCATENATE("SIB-",B56) -> SIB-PC249624 | K56: 1701 | L56: =CONCATENATE("GRS-",B56) -> GRS-PC249624 | M56: 1871 | N56: =CONCATENATE("UPB-",B56) -> UPB-PC249624 | O56: 1871 | P56: =CONCATENATE("MSL-",B56) -> MSL-PC249624 | Q56: 1871 | R56: =CONCATENATE("DGS-",B56) -> DGS-PC249624 | S56: 4
A57: 30" Pantry Cabinet: 4 Doors, 30" W x 84" H x 24" D | B57: PC308424 | C57: 2119 | D57: =CONCATENATE("ONB-",B57) -> ONB-PC308424 | E57: 1926 | F57: =CONCATENATE("WHS-",B57) -> WHS-PC308424 | G57: 2119 | H57: =CONCATENATE("ESS-",B57) -> ESS-PC308424 | I57: 2119 | J57: =CONCATENATE("SIB-",B57) -> SIB-PC308424 | K57: 1926 | L57: =CONCATENATE("GRS-",B57) -> GRS-PC308424 | M57: 2119 | N57: =CONCATENATE("UPB-",B57) -> UPB-PC308424 | O57: 2119 | P57: =CONCATENATE("MSL-",B57) -> MSL-PC308424 | Q57: 2119 | R57: =CONCATENATE("DGS-",B57) -> DGS-PC308424 | S57: 4
A58: 30" Pantry Cabinet: 4 Doors, 30" W x 90" H x 24" D | B58: PC309024 | C58: 2284 | D58: =CONCATENATE("ONB-",B58) -> ONB-PC309024 | E58: 2076 | F58: =CONCATENATE("WHS-",B58) -> WHS-PC309024 | G58: 2284 | H58: =CONCATENATE("ESS-",B58) -> ESS-PC309024 | I58: 2284 | J58: =CONCATENATE("SIB-",B58) -> SIB-PC309024 | K58: 2076 | L58: =CONCATENATE("GRS-",B58) -> GRS-PC309024 | M58: 2284 | N58: =CONCATENATE("UPB-",B58) -> UPB-PC309024 | O58: 2284 | P58: =CONCATENATE("MSL-",B58) -> MSL-PC309024 | Q58: 2284 | R58: =CONCATENATE("DGS-",B58) -> DGS-PC309024 | S58: 4
A59: 30" Pantry Cabinet: 4 Doors, 30" W x 96" H x 24" D | B59: PC309624 | C59: 2472 | D59: =CONCATENATE("ONB-",B59) -> ONB-PC309624 | E59: 2247 | F59: =CONCATENATE("WHS-",B59) -> WHS-PC309624 | G59: 2472 | H59: =CONCATENATE("ESS-",B59) -> ESS-PC309624 | I59: 2472 | J59: =CONCATENATE("SIB-",B59) -> SIB-PC309624 | K59: 2247 | L59: =CONCATENATE("GRS-",B59) -> GRS-PC309624 | M59: 2472 | N59: =CONCATENATE("UPB-",B59) -> UPB-PC309624 | O59: 2472 | P59: =CONCATENATE("MSL-",B59) -> MSL-PC309624 | Q59: 2472 | R59: =CONCATENATE("DGS-",B59) -> DGS-PC309624 | S59: 4
A60: Oven Cabinets, 24" Depth
A61: 18" Oven Cabinet: 2 Doors & 3 Drawers, 33" W x 84" H x 24" D | B61: OC338424 | C61: 2349 | D61: =CONCATENATE("ONB-",B61) -> ONB-OC338424 | E61: 2135 | F61: =CONCATENATE("WHS-",B61) -> WHS-OC338424 | G61: 2349 | H61: =CONCATENATE("ESS-",B61) -> ESS-OC338424 | I61: 2349 | J61: =CONCATENATE("SIB-",B61) -> SIB-OC338424 | K61: 2135 | L61: =CONCATENATE("GRS-",B61) -> GRS-OC338424 | M61: 2349 | N61: =CONCATENATE("UPB-",B61) -> UPB-OC338424 | O61: 2349 | P61: =CONCATENATE("MSL-",B61) -> MSL-OC338424 | Q61: 2349 | R61: =CONCATENATE("DGS-",B61) -> DGS-OC338424 | S61: 5
A62: 18" Oven Cabinet: 2 Doors & 3 Drawers, 33" W x 84" H x 24" D | B62: OC339024 | C62: 2395 | D62: =CONCATENATE("ONB-",B62) -> ONB-OC339024 | E62: 2177 | F62: =CONCATENATE("WHS-",B62) -> WHS-OC339024 | G62: 2395 | H62: =CONCATENATE("ESS-",B62) -> ESS-OC339024 | I62: 2395 | J62: =CONCATENATE("SIB-",B62) -> SIB-OC339024 | K62: 2177 | L62: =CONCATENATE("GRS-",B62) -> GRS-OC339024 | M62: 2395 | N62: =CONCATENATE("UPB-",B62) -> UPB-OC339024 | O62: 2395 | P62: =CONCATENATE("MSL-",B62) -> MSL-OC339024 | Q62: 2395 | R62: =CONCATENATE("DGS-",B62) -> DGS-OC339024 | S62: 5
A63: 18" Oven Cabinet: 2 Doors & 3 Drawers, 33" W x 84" H x 24" D | B63: OC339624 | C63: 2419 | D63: =CONCATENATE("ONB-",B63) -> ONB-OC339624 | E63: 2199 | F63: =CONCATENATE("WHS-",B63) -> WHS-OC339624 | G63: 2419 | H63: =CONCATENATE("ESS-",B63) -> ESS-OC339624 | I63: 2419 | J63: =CONCATENATE("SIB-",B63) -> SIB-OC339624 | K63: 2199 | L63: =CONCATENATE("GRS-",B63) -> GRS-OC339624 | M63: 2419 | N63: =CONCATENATE("UPB-",B63) -> UPB-OC339624 | O63: 2419 | P63: =CONCATENATE("MSL-",B63) -> MSL-OC339624 | Q63: 2419 | R63: =CONCATENATE("DGS-",B63) -> DGS-OC339624 | S63: 5
A64: Wall Cabinets, 12" Depth
A65: Wall Cabinet: 1 Door, 9" W x 30" H | B65: W0930 | C65: 376 | D65: =CONCATENATE("ONB-",B65) -> ONB-W0930 | E65: 342 | F65: =CONCATENATE("WHS-",B65) -> WHS-W0930 | G65: 376 | H65: =CONCATENATE("ESS-",B65) -> ESS-W0930 | I65: 376 | J65: =CONCATENATE("SIB-",B65) -> SIB-W0930 | K65: 342 | L65: =CONCATENATE("GRS-",B65) -> GRS-W0930 | M65: 376 | N65: =CONCATENATE("UPB-",B65) -> UPB-W0930 | O65: 376 | P65: =CONCATENATE("MSL-",B65) -> MSL-W0930 | Q65: 376 | R65: =CONCATENATE("DGS-",B65) -> DGS-W0930 | S65: 1
A66: Wall Cabinet: 1 Door, 12" W x 30" H | B66: W1230 | C66: 394 | D66: =CONCATENATE("ONB-",B66) -> ONB-W1230 | E66: 358 | F66: =CONCATENATE("WHS-",B66) -> WHS-W1230 | G66: 394 | H66: =CONCATENATE("ESS-",B66) -> ESS-W1230 | I66: 394 | J66: =CONCATENATE("SIB-",B66) -> SIB-W1230 | K66: 358 | L66: =CONCATENATE("GRS-",B66) -> GRS-W1230 | M66: 394 | N66: =CONCATENATE("UPB-",B66) -> UPB-W1230 | O66: 394 | P66: =CONCATENATE("MSL-",B66) -> MSL-W1230 | Q66: 394 | R66: =CONCATENATE("DGS-",B66) -> DGS-W1230 | S66: 1
A67: Wall Cabinet: 1 Door, 15" W x 30" H | B67: W1530 | C67: 424 | D67: =CONCATENATE("ONB-",B67) -> ONB-W1530 | E67: 385 | F67: =CONCATENATE("WHS-",B67) -> WHS-W1530 | G67: 424 | H67: =CONCATENATE("ESS-",B67) -> ESS-W1530 | I67: 424 | J67: =CONCATENATE("SIB-",B67) -> SIB-W1530 | K67: 385 | L67: =CONCATENATE("GRS-",B67) -> GRS-W1530 | M67: 424 | N67: =CONCATENATE("UPB-",B67) -> UPB-W1530 | O67: 424 | P67: =CONCATENATE("MSL-",B67) -> MSL-W1530 | Q67: 424 | R67: =CONCATENATE("DGS-",B67) -> DGS-W1530 | S67: 1
A68: Wall Cabinet: 1 Glass Door, 15" W x 30" H | B68: W1530GD | C68: 451 | D68: =CONCATENATE("ONB-",B68) -> ONB-W1530GD | E68: 410 | F68: =CONCATENATE("WHS-",B68) -> WHS-W1530GD | G68: 451 | H68: =CONCATENATE("ESS-",B68) -> ESS-W1530GD | I68: 451 | J68: =CONCATENATE("SIB-",B68) -> SIB-W1530GD | K68: 410 | L68: =CONCATENATE("GRS-",B68) -> GRS-W1530GD | M68: 451 | N68: =CONCATENATE("UPB-",B68) -> UPB-W1530GD | O68: 451 | P68: =CONCATENATE("MSL-",B68) -> MSL-W1530GD | Q68: 451 | R68: =CONCATENATE("DGS-",B68) -> DGS-W1530GD | S68: 1
A69: Wall Cabinet: 1 Door, 18" W x 30" H | B69: W1830 | C69: 459 | D69: =CONCATENATE("ONB-",B69) -> ONB-W1830 | E69: 417 | F69: =CONCATENATE("WHS-",B69) -> WHS-W1830 | G69: 459 | H69: =CONCATENATE("ESS-",B69) -> ESS-W1830 | I69: 459 | J69: =CONCATENATE("SIB-",B69) -> SIB-W1830 | K69: 417 | L69: =CONCATENATE("GRS-",B69) -> GRS-W1830 | M69: 459 | N69: =CONCATENATE("UPB-",B69) -> UPB-W1830 | O69: 459 | P69: =CONCATENATE("MSL-",B69) -> MSL-W1830 | Q69: 459 | R69: =CONCATENATE("DGS-",B69) -> DGS-W1830 | S69: 1
A70: Wall Cabinet: 1 Glass Door, 18" W x 30" H | B70: W1830GD | C70: 491 | D70: =CONCATENATE("ONB-",B70) -> ONB-W1830GD | E70: 446 | F70: =CONCATENATE("WHS-",B70) -> WHS-W1830GD | G70: 491 | H70: =CONCATENATE("ESS-",B70) -> ESS-W1830GD | I70: 491 | J70: =CONCATENATE("SIB-",B70) -> SIB-W1830GD | K70: 446 | L70: =CONCATENATE("GRS-",B70) -> GRS-W1830GD | M70: 491 | N70: =CONCATENATE("UPB-",B70) -> UPB-W1830GD | O70: 491 | P70: =CONCATENATE("MSL-",B70) -> MSL-W1830GD | Q70: 491 | R70: =CONCATENATE("DGS-",B70) -> DGS-W1830GD | S70: 1
A71: Wall Cabinet: 1 Door, 21" W x 30" H | B71: W2130 | C71: 494 | D71: =CONCATENATE("ONB-",B71) -> ONB-W2130 | E71: 449 | F71: =CONCATENATE("WHS-",B71) -> WHS-W2130 | G71: 494 | H71: =CONCATENATE("ESS-",B71) -> ESS-W2130 | I71: 494 | J71: =CONCATENATE("SIB-",B71) -> SIB-W2130 | K71: 449 | L71: =CONCATENATE("GRS-",B71) -> GRS-W2130 | M71: 494 | N71: =CONCATENATE("UPB-",B71) -> UPB-W2130 | O71: 494 | P71: =CONCATENATE("MSL-",B71) -> MSL-W2130 | Q71: 494 | R71: =CONCATENATE("DGS-",B71) -> DGS-W2130 | S71: 1
A72: Wall Cabinet: 2 Doors, 24" W x 30" H | B72: W2430 | C72: 541 | D72: =CONCATENATE("ONB-",B72) -> ONB-W2430 | E72: 492 | F72: =CONCATENATE("WHS-",B72) -> WHS-W2430 | G72: 541 | H72: =CONCATENATE("ESS-",B72) -> ESS-W2430 | I72: 541 | J72: =CONCATENATE("SIB-",B72) -> SIB-W2430 | K72: 492 | L72: =CONCATENATE("GRS-",B72) -> GRS-W2430 | M72: 541 | N72: =CONCATENATE("UPB-",B72) -> UPB-W2430 | O72: 541 | P72: =CONCATENATE("MSL-",B72) -> MSL-W2430 | Q72: 541 | R72: =CONCATENATE("DGS-",B72) -> DGS-W2430 | S72: 2
A73: Wall Cabinet: 2 Doors, 27" W x 30" H | B73: W2730 | C73: 589 | D73: =CONCATENATE("ONB-",B73) -> ONB-W2730 | E73: 535 | F73: =CONCATENATE("WHS-",B73) -> WHS-W2730 | G73: 589 | H73: =CONCATENATE("ESS-",B73) -> ESS-W2730 | I73: 589 | J73: =CONCATENATE("SIB-",B73) -> SIB-W2730 | K73: 535 | L73: =CONCATENATE("GRS-",B73) -> GRS-W2730 | M73: 589 | N73: =CONCATENATE("UPB-",B73) -> UPB-W2730 | O73: 589 | P73: =CONCATENATE("MSL-",B73) -> MSL-W2730 | Q73: 589 | R73: =CONCATENATE("DGS-",B73) -> DGS-W2730 | S73: 2
A74: Wall Cabinet: 2 Doors, 30" W x 30" H | B74: W3030 | C74: 624 | D74: =CONCATENATE("ONB-",B74) -> ONB-W3030 | E74: 567 | F74: =CONCATENATE("WHS-",B74) -> WHS-W3030 | G74: 624 | H74: =CONCATENATE("ESS-",B74) -> ESS-W3030 | I74: 624 | J74: =CONCATENATE("SIB-",B74) -> SIB-W3030 | K74: 567 | L74: =CONCATENATE("GRS-",B74) -> GRS-W3030 | M74: 624 | N74: =CONCATENATE("UPB-",B74) -> UPB-W3030 | O74: 624 | P74: =CONCATENATE("MSL-",B74) -> MSL-W3030 | Q74: 624 | R74: =CONCATENATE("DGS-",B74) -> DGS-W3030 | S74: 2
A75: Wall Cabinet: 2 Glass Doors, 30" W x 30" H | B75: W3030GD | C75: 668 | D75: =CONCATENATE("ONB-",B75) -> ONB-W3030GD | E75: 607 | F75: =CONCATENATE("WHS-",B75) -> WHS-W3030GD | G75: 668 | H75: =CONCATENATE("ESS-",B75) -> ESS-W3030GD | I75: 668 | J75: =CONCATENATE("SIB-",B75) -> SIB-W3030GD | K75: 607 | L75: =CONCATENATE("GRS-",B75) -> GRS-W3030GD | M75: 668 | N75: =CONCATENATE("UPB-",B75) -> UPB-W3030GD | O75: 668 | P75: =CONCATENATE("MSL-",B75) -> MSL-W3030GD | Q75: 668 | R75: =CONCATENATE("DGS-",B75) -> DGS-W3030GD | S75: 2
A76: Wall Cabinet: 2 Doors, 33" W x 30" H | B76: W3330 | C76: 666 | D76: =CONCATENATE("ONB-",B76) -> ONB-W3330 | E76: 605 | F76: =CONCATENATE("WHS-",B76) -> WHS-W3330 | G76: 666 | H76: =CONCATENATE("ESS-",B76) -> ESS-W3330 | I76: 666 | J76: =CONCATENATE("SIB-",B76) -> SIB-W3330 | K76: 605 | L76: =CONCATENATE("GRS-",B76) -> GRS-W3330 | M76: 666 | N76: =CONCATENATE("UPB-",B76) -> UPB-W3330 | O76: 666 | P76: =CONCATENATE("MSL-",B76) -> MSL-W3330 | Q76: 666 | R76: =CONCATENATE("DGS-",B76) -> DGS-W3330 | S76: 2
... A110: Wall Cabinet: 2 Doors, 24" W x 42" H | B110: W2442 | C110: 683 | D110: =CONCATENATE("ONB-",B110) -> ONB-W2442 | E110: 621 | F110: =CONCATENATE("WHS-",B110) -> WHS-W2442 | G110: 683 | H110: =CONCATENATE("ESS-",B110) -> ESS-W2442 | I110: 683 | J110: =CONCATENATE("SIB-",B110) -> SIB-W2442 | K110: 621 | L110: =CONCATENATE("GRS-",B110) -> GRS-W2442 | M110: 683 | N110: =CONCATENATE("UPB-",B110) -> UPB-W2442 | O110: 683 | P110: =CONCATENATE("MSL-",B110) -> MSL-W2442 | Q110: 683 | R110: =CONCATENATE("DGS-",B110) -> DGS-W2442 | S110: 2
A111: Wall Cabinet: 2 Doors, 27" W x 15" H | B111: W2715 | C111: 567 | D111: =CONCATENATE("ONB-",B111) -> ONB-W2715 | E111: =E108+80 -> 515 | F111: =CONCATENATE("WHS-",B111) -> WHS-W2715 | G111: 567 | H111: =CONCATENATE("ESS-",B111) -> ESS-W2715 | I111: 567 | J111: =CONCATENATE("SIB-",B111) -> SIB-W2715 | K111: =K108+80 -> 515 | L111: =CONCATENATE("GRS-",B111) -> GRS-W2715 | M111: 567 | N111: =CONCATENATE("UPB-",B111) -> UPB-W2715 | O111: 567 | P111: =CONCATENATE("MSL-",B111) -> MSL-W2715 | Q111: 567 | R111: =CONCATENATE("DGS-",B111) -> DGS-W2715 | S111: 2
A112: Wall Cabinet: 2 Glass Doors, 27" W x 15" H | B112: W2715GD | C112: 677 | D112: =CONCATENATE("ONB-",B112) -> ONB-W2715GD | E112: =E111+100 -> 615 | F112: =CONCATENATE("WHS-",B112) -> WHS-W2715GD | G112: 677 | H112: =CONCATENATE("ESS-",B112) -> ESS-W2715GD | I112: 677 | J112: =CONCATENATE("SIB-",B112) -> SIB-W2715GD | K112: =K111+100 -> 615 | L112: =CONCATENATE("GRS-",B112) -> GRS-W2715GD | M112: 677 | N112: =CONCATENATE("UPB-",B112) -> UPB-W2715GD | O112: 677 | P112: =CONCATENATE("MSL-",B112) -> MSL-W2715GD | Q112: 677 | R112: =CONCATENATE("DGS-",B112) -> DGS-W2715GD | S112: 2
A113: Wall Cabinet: 2 Doors, 27" W x 42" H | B113: W2742 | C113: 741 | D113: =CONCATENATE("ONB-",B113) -> ONB-W2742 | E113: 674 | F113: =CONCATENATE("WHS-",B113) -> WHS-W2742 | G113: 741 | H113: =CONCATENATE("ESS-",B113) -> ESS-W2742 | I113: 741 | J113: =CONCATENATE("SIB-",B113) -> SIB-W2742 | K113: 674 | L113: =CONCATENATE("GRS-",B113) -> GRS-W2742 | M113: 741 | N113: =CONCATENATE("UPB-",B113) -> UPB-W2742 | O113: 741 | P113: =CONCATENATE("MSL-",B113) -> MSL-W2742 | Q113: 741 | R113: =CONCATENATE("DGS-",B113) -> DGS-W2742 | S113: 2
A114: Wall Cabinet: 2 Doors, 30" W x 42" H | B114: W3042 | C114: 783 | D114: =CONCATENATE("ONB-",B114) -> ONB-W3042 | E114: 712 | F114: =CONCATENATE("WHS-",B114) -> WHS-W3042 | G114: 783 | H114: =CONCATENATE("ESS-",B114) -> ESS-W3042 | I114: 783 | J114: =CONCATENATE("SIB-",B114) -> SIB-W3042 | K114: 712 | L114: =CONCATENATE("GRS-",B114) -> GRS-W3042 | M114: 783 | N114: =CONCATENATE("UPB-",B114) -> UPB-W3042 | O114: 783 | P114: =CONCATENATE("MSL-",B114) -> MSL-W3042 | Q114: 783 | R114: =CONCATENATE("DGS-",B114) -> DGS-W3042 | S114: 2
A115: Wall Cabinet: 2 Glass Doors, 30" W x 42" H | B115: W3042GD | C115: 837 | D115: =CONCATENATE("ONB-",B115) -> ONB-W3042GD | E115: 761 | F115: =CONCATENATE("WHS-",B115) -> WHS-W3042GD | G115: 837 | H115: =CONCATENATE("ESS-",B115) -> ESS-W3042GD | I115: 837 | J115: =CONCATENATE("SIB-",B115) -> SIB-W3042GD | K115: 761 | L115: =CONCATENATE("GRS-",B115) -> GRS-W3042GD | M115: 837 | N115: =CONCATENATE("UPB-",B115) -> UPB-W3042GD | O115: 837 | P115: =CONCATENATE("MSL-",B115) -> MSL-W3042GD | Q115: 837 | R115: =CONCATENATE("DGS-",B115) -> DGS-W3042GD | S115: 2
A116: Wall Cabinet: 2 Doors, 33" W x 42" H | B116: W3342 | C116: 847 | D116: =CONCATENATE("ONB-",B116) -> ONB-W3342 | E116: 770 | F116: =CONCATENATE("WHS-",B116) -> WHS-W3342 | G116: 847 | H116: =CONCATENATE("ESS-",B116) -> ESS-W3342 | I116: 847 | J116: =CONCATENATE("SIB-",B116) -> SIB-W3342 | K116: 770 | L116: =CONCATENATE("GRS-",B116) -> GRS-W3342 | M116: 847 | N116: =CONCATENATE("UPB-",B116) -> UPB-W3342 | O116: 847 | P116: =CONCATENATE("MSL-",B116) -> MSL-W3342 | Q116: 847 | R116: =CONCATENATE("DGS-",B116) -> DGS-W3342 | S116: 2
A117: Wall Cabinet: 2 Doors, 36" W x 42" H | B117: W3642 | C117: 889 | D117: =CONCATENATE("ONB-",B117) -> ONB-W3642 | E117: 808 | F117: =CONCATENATE("WHS-",B117) -> WHS-W3642 | G117: 889 | H117: =CONCATENATE("ESS-",B117) -> ESS-W3642 | I117: 889 | J117: =CONCATENATE("SIB-",B117) -> SIB-W3642 | K117: 808 | L117: =CONCATENATE("GRS-",B117) -> GRS-W3642 | M117: 889 | N117: =CONCATENATE("UPB-",B117) -> UPB-W3642 | O117: 889 | P117: =CONCATENATE("MSL-",B117) -> MSL-W3642 | Q117: 889 | R117: =CONCATENATE("DGS-",B117) -> DGS-W3642 | S117: 2
A118: Wall Cabinet: 2 Glass Doors, 36" W x 42" H | B118: W3642GD | C118: 950 | D118: =CONCATENATE("ONB-",B118) -> ONB-W3642GD | E118: 864 | F118: =CONCATENATE("WHS-",B118) -> WHS-W3642GD | G118: 950 | H118: =CONCATENATE("ESS-",B118) -> ESS-W3642GD | I118: 950 | J118: =CONCATENATE("SIB-",B118) -> SIB-W3642GD | K118: 864 | L118: =CONCATENATE("GRS-",B118) -> GRS-W3642GD | M118: 950 | N118: =CONCATENATE("UPB-",B118) -> UPB-W3642GD | O118: 950 | P118: =CONCATENATE("MSL-",B118) -> MSL-W3642GD | Q118: 950 | R118: =CONCATENATE("DGS-",B118) -> DGS-W3642GD | S118: 2
A119: Wall Cabinet: 2 Doors, 42" W x 42" H | B119: W4242 | C119: 994 | D119: =CONCATENATE("ONB-",B119) -> ONB-W4242 | E119: 904 | F119: =CONCATENATE("WHS-",B119) -> WHS-W4242 | G119: 994 | H119: =CONCATENATE("ESS-",B119) -> ESS-W4242 | I119: 994 | J119: =CONCATENATE("SIB-",B119) -> SIB-W4242 | K119: 904 | L119: =CONCATENATE("GRS-",B119) -> GRS-W4242 | M119: 994 | N119: =CONCATENATE("UPB-",B119) -> UPB-W4242 | O119: 994 | P119: =CONCATENATE("MSL-",B119) -> MSL-W4242 | Q119: 994 | R119: =CONCATENATE("DGS-",B119) -> DGS-W4242 | S119: 2
A120: Wall Cabinet: 2 Doors, 30" W x 12" H | B120: W3012 | C120: 383 | D120: =CONCATENATE("ONB-",B120) -> ONB-W3012 | E120: 348 | F120: =CONCATENATE("WHS-",B120) -> WHS-W3012 | G120: 383 | H120: =CONCATENATE("ESS-",B120) -> ESS-W3012 | I120: 383 | J120: =CONCATENATE("SIB-",B120) -> SIB-W3012 | K120: 348 | L120: =CONCATENATE("GRS-",B120) -> GRS-W3012 | M120: 383 | N120: =CONCATENATE("UPB-",B120) -> UPB-W3012 | O120: 383 | P120: =CONCATENATE("MSL-",B120) -> MSL-W3012 | Q120: 383 | R120: =CONCATENATE("DGS-",B120) -> DGS-W3012 | S120: 2
A121: Wall Cabinet: 2 Doors, 30" W x 15" H | B121: W3015 | C121: 413 | D121: =CONCATENATE("ONB-",B121) -> ONB-W3015 | E121: 375 | F121: =CONCATENATE("WHS-",B121) -> WHS-W3015 | G121: 413 | H121: =CONCATENATE("ESS-",B121) -> ESS-W3015 | I121: 413 | J121: =CONCATENATE("SIB-",B121) -> SIB-W3015 | K121: 375 | L121: =CONCATENATE("GRS-",B121) -> GRS-W3015 | M121: 413 | N121: =CONCATENATE("UPB-",B121) -> UPB-W3015 | O121: 413 | P121: =CONCATENATE("MSL-",B121) -> MSL-W3015 | Q121: 413 | R121: =CONCATENATE("DGS-",B121) -> DGS-W3015 | S121: 2
A122: Wall Cabinet: 2 Glass Doors, 30" W x 15" H | B122: W3015GD | C122: 523 | D122: =CONCATENATE("ONB-",B122) -> ONB-W3015GD | E122: 475 | F122: =CONCATENATE("WHS-",B122) -> WHS-W3015GD | G122: 523 | H122: =CONCATENATE("ESS-",B122) -> ESS-W3015GD | I122: 523 | J122: =CONCATENATE("SIB-",B122) -> SIB-W3015GD | K122: 475 | L122: =CONCATENATE("GRS-",B122) -> GRS-W3015GD | M122: 523 | N122: =CONCATENATE("UPB-",B122) -> UPB-W3015GD | O122: 523 | P122: =CONCATENATE("MSL-",B122) -> MSL-W3015GD | Q122: 523 | R122: =CONCATENATE("DGS-",B122) -> DGS-W3015GD | S122: 2
A123: Wall Cabinet: 2 Doors, 30" W x 18" H | B123: W3018 | C123: 453 | D123: =CONCATENATE("ONB-",B123) -> ONB-W3018 | E123: 412 | F123: =CONCATENATE("WHS-",B123) -> WHS-W3018 | G123: 453 | H123: =CONCATENATE("ESS-",B123) -> ESS-W3018 | I123: 453 | J123: =CONCATENATE("SIB-",B123) -> SIB-W3018 | K123: 412 | L123: =CONCATENATE("GRS-",B123) -> GRS-W3018 | M123: 453 | N123: =CONCATENATE("UPB-",B123) -> UPB-W3018 | O123: 453 | P123: =CONCATENATE("MSL-",B123) -> MSL-W3018 | Q123: 453 | R123: =CONCATENATE("DGS-",B123) -> DGS-W3018 | S123: 2
A124: Wall Cabinet: 2 Doors, 30" W x 21" H | B124: W3021 | C124: 488 | D124: =CONCATENATE("ONB-",B124) -> ONB-W3021 | E124: 444 | F124: =CONCATENATE("WHS-",B124) -> WHS-W3021 | G124: 488 | H124: =CONCATENATE("ESS-",B124) -> ESS-W3021 | I124: 488 | J124: =CONCATENATE("SIB-",B124) -> SIB-W3021 | K124: 444 | L124: =CONCATENATE("GRS-",B124) -> GRS-W3021 | M124: 488 | N124: =CONCATENATE("UPB-",B124) -> UPB-W3021 | O124: 488 | P124: =CONCATENATE("MSL-",B124) -> MSL-W3021 | Q124: 488 | R124: =CONCATENATE("DGS-",B124) -> DGS-W3021 | S124: 2
... A137: Wall Cabinet: 2 Doors, 36" W x 24" H | B137: W3624 | C137: 718 | D137: =CONCATENATE("ONB-",B137) -> ONB-W3624 | E137: 653 | F137: =CONCATENATE("WHS-",B137) -> WHS-W3624 | G137: 718 | H137: =CONCATENATE("ESS-",B137) -> ESS-W3624 | I137: 718 | J137: =CONCATENATE("SIB-",B137) -> SIB-W3624 | K137: 653 | L137: =CONCATENATE("GRS-",B137) -> GRS-W3624 | M137: 718 | N137: =CONCATENATE("UPB-",B137) -> UPB-W3624 | O137: 718 | P137: =CONCATENATE("MSL-",B137) -> MSL-W3624 | Q137: 718 | R137: =CONCATENATE("DGS-",B137) -> DGS-W3624 | S137: 2
A138: Wall Fridge Cabinets, 24" Depth
A139: Wall Cabinet: 2 Doors, 36" W x 12" H x 24" D | B139: W361224 | C139: 559 | D139: =CONCATENATE("ONB-",B139) -> ONB-W361224 | E139: 508 | F139: =CONCATENATE("WHS-",B139) -> WHS-W361224 | G139: 559 | H139: =CONCATENATE("ESS-",B139) -> ESS-W361224 | I139: 559 | J139: =CONCATENATE("SIB-",B139) -> SIB-W361224 | K139: 508 | L139: =CONCATENATE("GRS-",B139) -> GRS-W361224 | M139: 559 | N139: =CONCATENATE("UPB-",B139) -> UPB-W361224 | O139: 559 | P139: =CONCATENATE("MSL-",B139) -> MSL-W361224 | Q139: 559 | R139: =CONCATENATE("DGS-",B139) -> DGS-W361224 | S139: 2
A140: Wall Cabinet: 2 Doors, 36" W x 15" H x 24" D | B140: W361524 | C140: 620 | D140: =CONCATENATE("ONB-",B140) -> ONB-W361524 | E140: 564 | F140: =CONCATENATE("WHS-",B140) -> WHS-W361524 | G140: 620 | H140: =CONCATENATE("ESS-",B140) -> ESS-W361524 | I140: 620 | J140: =CONCATENATE("SIB-",B140) -> SIB-W361524 | K140: 564 | L140: =CONCATENATE("GRS-",B140) -> GRS-W361524 | M140: 620 | N140: =CONCATENATE("UPB-",B140) -> UPB-W361524 | O140: 620 | P140: =CONCATENATE("MSL-",B140) -> MSL-W361524 | Q140: 620 | R140: =CONCATENATE("DGS-",B140) -> DGS-W361524 | S140: 2
A141: Wall Cabinet: 2 Doors, 36" W x 18" H x 24" D | B141: W361824 | C141: 683 | D141: =CONCATENATE("ONB-",B141) -> ONB-W361824 | E141: 621 | F141: =CONCATENATE("WHS-",B141) -> WHS-W361824 | G141: 683 | H141: =CONCATENATE("ESS-",B141) -> ESS-W361824 | I141: 683 | J141: =CONCATENATE("SIB-",B141) -> SIB-W361824 | K141: 621 | L141: =CONCATENATE("GRS-",B141) -> GRS-W361824 | M141: 683 | N141: =CONCATENATE("UPB-",B141) -> UPB-W361824 | O141: 683 | P141: =CONCATENATE("MSL-",B141) -> MSL-W361824 | Q141: 683 | R141: =CONCATENATE("DGS-",B141) -> DGS-W361824 | S141: 2
A142: Wall Cabinet: 2 Doors, 36" W x 21" H x 24" D | B142: W362124 | C142: 718 | D142: =CONCATENATE("ONB-",B142) -> ONB-W362124 | E142: 653 | F142: =CONCATENATE("WHS-",B142) -> WHS-W362124 | G142: 718 | H142: =CONCATENATE("ESS-",B142) -> ESS-W362124 | I142: 718 | J142: =CONCATENATE("SIB-",B142) -> SIB-W362124 | K142: 653 | L142: =CONCATENATE("GRS-",B142) -> GRS-W362124 | M142: 718 | N142: =CONCATENATE("UPB-",B142) -> UPB-W362124 | O142: 718 | P142: =CONCATENATE("MSL-",B142) -> MSL-W362124 | Q142: 718 | R142: =CONCATENATE("DGS-",B142) -> DGS-W362124 | S142: 2
A143: Wall Cabinet: 2 Doors, 36" W x 24" H x 24" D | B143: W362424 | C143: 754 | D143: =CONCATENATE("ONB-",B143) -> ONB-W362424 | E143: 685 | F143: =CONCATENATE("WHS-",B143) -> WHS-W362424 | G143: 754 | H143: =CONCATENATE("ESS-",B143) -> ESS-W362424 | I143: 754 | J143: =CONCATENATE("SIB-",B143) -> SIB-W362424 | K143: 685 | L143: =CONCATENATE("GRS-",B143) -> GRS-W362424 | M143: 754 | N143: =CONCATENATE("UPB-",B143) -> UPB-W362424 | O143: 754 | P143: =CONCATENATE("MSL-",B143) -> MSL-W362424 | Q143: 754 | R143: =CONCATENATE("DGS-",B143) -> DGS-W362424 | S143: 2
A144: Wall Blind Corner Cabinets, 12" Depth
A145: Wall Cabinet: 1 Door, 30" W x 30" H, Reversible | B145: WBC3030 | C145: 671 | D145: =CONCATENATE("ONB-",B145) -> ONB-WBC3030 | E145: 610 | F145: =CONCATENATE("WHS-",B145) -> WHS-WBC3030 | G145: 671 | H145: =CONCATENATE("ESS-",B145) -> ESS-WBC3030 | I145: 671 | J145: =CONCATENATE("SIB-",B145) -> SIB-WBC3030 | K145: 610 | L145: =CONCATENATE("GRS-",B145) -> GRS-WBC3030 | M145: 671 | N145: =CONCATENATE("UPB-",B145) -> UPB-WBC3030 | O145: 671 | P145: =CONCATENATE("MSL-",B145) -> MSL-WBC3030 | Q145: 671 | R145: =CONCATENATE("DGS-",B145) -> DGS-WBC3030 | S145: 1
A146: Wall Cabinet: 1 Door, 30" W x 36" H, Reversible | B146: WBC3036 | C146: 729 | D146: =CONCATENATE("ONB-",B146) -> ONB-WBC3036 | E146: 663 | F146: =CONCATENATE("WHS-",B146) -> WHS-WBC3036 | G146: 729 | H146: =CONCATENATE("ESS-",B146) -> ESS-WBC3036 | I146: 729 | J146: =CONCATENATE("SIB-",B146) -> SIB-WBC3036 | K146: 663 | L146: =CONCATENATE("GRS-",B146) -> GRS-WBC3036 | M146: 729 | N146: =CONCATENATE("UPB-",B146) -> UPB-WBC3036 | O146: 729 | P146: =CONCATENATE("MSL-",B146) -> MSL-WBC3036 | Q146: 729 | R146: =CONCATENATE("DGS-",B146) -> DGS-WBC3036 | S146: 1
...

Sheet Framed Accessory List Price
C2: ONYX BLACK | E2: WHITE SHAKER | G2: ESPRESSO SHAKER | I2: SIGNATURE BLUE | K2: Gray Shaker | M2: Uptown White | O2: Modern Slate | Q2: Dark Green Slim Shaker
C3: ONB | E3: WHS | G3: ESS | I3: SIB | K3: GRS | M3: UPB | O3: MSL | Q3: DGS
A4: Description | B4: Accessory Name | C4: List Price | D4: Inventory Code | E4: List Price | F4: Inventory Code | G4: List Price | H4: Inventory Code | I4: List Price | J4: Inventory Code | K4: List Price | L4: Inventory Code | M4: List Price | N4: Inventory Code | O4: List Price | P4: Inventory Code | Q4: List Price | R4: Inventory Code
A5: 1/4" Cabinet Skins:
A6: Wall Cabinet Skin: 12" W x 30" H | B6: DEP12*30*1/4 | C6: 47 | D6: =CONCATENATE("ONB-",B6,) -> ONB-DEP12*30*1/4 | E6: 45 | F6: =CONCATENATE("WHS-",B6,) -> WHS-DEP12*30*1/4 | G6: 47 | H6: =CONCATENATE("ESS-",B6,) -> ESS-DEP12*30*1/4 | I6: 47 | J6: =CONCATENATE("SIB-",B6) -> SIB-DEP12*30*1/4 | K6: 45 | L6: =CONCATENATE("GRS-",B6,) -> GRS-DEP12*30*1/4 | M6: 47 | N6: =CONCATENATE("UPB-",B6,) -> UPB-DEP12*30*1/4 | O6: 47 | P6: =CONCATENATE("MSL-",B6,) -> MSL-DEP12*30*1/4 | Q6: 47 | R6: =CONCATENATE("DGS-",B6,) -> DGS-DEP12*30*1/4
A7: Wall Cabinet Skin: 12" W x 36" H | B7: DEP12*36*1/4 | C7: 53 | D7: =CONCATENATE("ONB-",B7,) -> ONB-DEP12*36*1/4 | E7: 50 | F7: =CONCATENATE("WHS-",B7,) -> WHS-DEP12*36*1/4 | G7: 53 | H7: =CONCATENATE("ESS-",B7,) -> ESS-DEP12*36*1/4 | I7: 53 | J7: =CONCATENATE("SIB-",B7) -> SIB-DEP12*36*1/4 | K7: 50 | L7: =CONCATENATE("GRS-",B7,) -> GRS-DEP12*36*1/4 | M7: 53 | N7: =CONCATENATE("UPB-",B7,) -> UPB-DEP12*36*1/4 | O7: 53 | P7: =CONCATENATE("MSL-",B7,) -> MSL-DEP12*36*1/4 | Q7: 53 | R7: =CONCATENATE("DGS-",B7,) -> DGS-DEP12*36*1/4
A8: Wall Cabinet Skin: 12" W x 42" H | B8: DEP12*42*1/4 | C8: 58 | D8: =CONCATENATE("ONB-",B8,) -> ONB-DEP12*42*1/4 | E8: 55 | F8: =CONCATENATE("WHS-",B8,) -> WHS-DEP12*42*1/4 | G8: 58 | H8: =CONCATENATE("ESS-",B8,) -> ESS-DEP12*42*1/4 | I8: 58 | J8: =CONCATENATE("SIB-",B8) -> SIB-DEP12*42*1/4 | K8: 55 | L8: =CONCATENATE("GRS-",B8,) -> GRS-DEP12*42*1/4 | M8: 58 | N8: =CONCATENATE("UPB-",B8,) -> UPB-DEP12*42*1/4 | O8: 58 | P8: =CONCATENATE("MSL-",B8,) -> MSL-DEP12*42*1/4 | Q8: 58 | R8: =CONCATENATE("DGS-",B8,) -> DGS-DEP12*42*1/4
A9: Base Cabinet Skin: 21" W x 34.5" H | B9: DEP21*34.5*1/4 | C9: 79 | D9: =CONCATENATE("ONB-",B9,) -> ONB-DEP21*34.5*1/4 | E9: 75 | F9: =CONCATENATE("WHS-",B9,) -> WHS-DEP21*34.5*1/4 | G9: 79 | H9: =CONCATENATE("ESS-",B9,) -> ESS-DEP21*34.5*1/4 | I9: 79 | J9: =CONCATENATE("SIB-",B9) -> SIB-DEP21*34.5*1/4 | K9: 75 | L9: =CONCATENATE("GRS-",B9,) -> GRS-DEP21*34.5*1/4 | M9: 79 | N9: =CONCATENATE("UPB-",B9,) -> UPB-DEP21*34.5*1/4 | O9: 79 | P9: =CONCATENATE("MSL-",B9,) -> MSL-DEP21*34.5*1/4 | Q9: 79 | R9: =CONCATENATE("DGS-",B9,) -> DGS-DEP21*34.5*1/4
A10: Base Cabinet Skin: 24" W x 34.5" H | B10: DEP24*34.5*1/4 | C10: 89 | D10: =CONCATENATE("ONB-",B10,) -> ONB-DEP24*34.5*1/4 | E10: 85 | F10: =CONCATENATE("WHS-",B10,) -> WHS-DEP24*34.5*1/4 | G10: 89 | H10: =CONCATENATE("ESS-",B10,) -> ESS-DEP24*34.5*1/4 | I10: 89 | J10: =CONCATENATE("SIB-",B10) -> SIB-DEP24*34.5*1/4 | K10: 85 | L10: =CONCATENATE("GRS-",B10,) -> GRS-DEP24*34.5*1/4 | M10: 89 | N10: =CONCATENATE("UPB-",B10,) -> UPB-DEP24*34.5*1/4 | O10: 89 | P10: =CONCATENATE("MSL-",B10,) -> MSL-DEP24*34.5*1/4 | Q10: 89 | R10: =CONCATENATE("DGS-",B10,) -> DGS-DEP24*34.5*1/4
A11: Pantry Cabinet Skin: 24" W x 96" H | B11: DEP24*96*1/4 | C11: 184 | D11: =CONCATENATE("ONB-",B11,) -> ONB-DEP24*96*1/4 | E11: 175 | F11: =CONCATENATE("WHS-",B11,) -> WHS-DEP24*96*1/4 | G11: 184 | H11: =CONCATENATE("ESS-",B11,) -> ESS-DEP24*96*1/4 | I11: 184 | J11: =CONCATENATE("SIB-",B11) -> SIB-DEP24*96*1/4 | K11: 175 | L11: =CONCATENATE("GRS-",B11,) -> GRS-DEP24*96*1/4 | M11: 184 | N11: =CONCATENATE("UPB-",B11,) -> UPB-DEP24*96*1/4 | O11: 184 | P11: =CONCATENATE("MSL-",B11,) -> MSL-DEP24*96*1/4 | Q11: 184 | R11: =CONCATENATE("DGS-",B11,) -> DGS-DEP24*96*1/4
A12: 1/4" Cabinet Panel: 34.5" W x 96" H | B12: PNL 34.5*96*1/4 | C12: 336 | D12: =CONCATENATE("ONB-",B12,) -> ONB-PNL 34.5*96*1/4 | E12: 321 | F12: =CONCATENATE("WHS-",B12,) -> WHS-PNL 34.5*96*1/4 | G12: 336 | H12: =CONCATENATE("ESS-",B12,) -> ESS-PNL 34.5*96*1/4 | I12: 336 | J12: =CONCATENATE("SIB-",B12) -> SIB-PNL 34.5*96*1/4 | K12: 321 | L12: =CONCATENATE("GRS-",B12,) -> GRS-PNL 34.5*96*1/4 | M12: 336 | N12: =CONCATENATE("UPB-",B12,) -> UPB-PNL 34.5*96*1/4 | O12: 336 | P12: =CONCATENATE("MSL-",B12,) -> MSL-PNL 34.5*96*1/4 | Q12: 336 | R12: =CONCATENATE("DGS-",B12,) -> DGS-PNL 34.5*96*1/4
A13: 1/2" Cabinet Panels:
A14: Island Back Panel: 34.5" W x 96" H | B14: PNL34.5*96*1/2-VERTICAL | C14: 375 | D14: =CONCATENATE("ONB-",B14,) -> ONB-PNL34.5*96*1/2-VERTICAL | E14: 350 | F14: =CONCATENATE("WHS-",B14,) -> WHS-PNL34.5*96*1/2-VERTICAL | G14: 375 | H14: =CONCATENATE("ESS-",B14,) -> ESS-PNL34.5*96*1/2-VERTICAL | I14: 375 | J14: =CONCATENATE("SIB-",B14) -> SIB-PNL34.5*96*1/2-VERTICAL | K14: 350 | L14: =CONCATENATE("GRS-",B14,) -> GRS-PNL34.5*96*1/2-VERTICAL | M14: 375 | N14: =CONCATENATE("UPB-",B14,) -> UPB-PNL34.5*96*1/2-VERTICAL | O14: 375 | P14: =CONCATENATE("MSL-",B14,) -> MSL-PNL34.5*96*1/2-VERTICAL | Q14: 375 | R14: =CONCATENATE("DGS-",B14,) -> DGS-PNL34.5*96*1/2-VERTICAL
A15: Dishwasher Return Panel: 24" W x 34.5" H, 3" Return filler included | B15: DWR3 | C15: 130 | D15: =CONCATENATE("ONB-",B15,) -> ONB-DWR3 | E15: 123 | F15: =CONCATENATE("WHS-",B15) -> WHS-DWR3 | G15: 130 | H15: =CONCATENATE("ESS-",B15) -> ESS-DWR3 | I15: 130 | J15: =CONCATENATE("SIB-",B15) -> SIB-DWR3 | K15: 123.05 | L15: =CONCATENATE("GRS-",B15,) -> GRS-DWR3 | M15: 130 | N15: =CONCATENATE("UPB-",B15,) -> UPB-DWR3 | O15: 130 | P15: =CONCATENATE("MSL-",B15,) -> MSL-DWR3 | Q15: 130 | R15: =CONCATENATE("DGS-",B15,) -> DGS-DWR3
A16: Refrigerator Return Panel: 24" W x 96" H, 1.5" return filler included | B16: REP1.5x96 | C16: 435 | D16: =CONCATENATE("ONB-",B16,) -> ONB-REP1.5x96 | E16: 425 | F16: =CONCATENATE("WHS-",B16) -> WHS-REP1.5x96 | G16: 435 | H16: =CONCATENATE("ESS-",B16) -> ESS-REP1.5x96 | I16: 435 | J16: =CONCATENATE("SIB-",B16) -> SIB-REP1.5x96 | K16: 425 | L16: =CONCATENATE("GRS-",B16,) -> GRS-REP1.5x96 | M16: 435 | N16: =CONCATENATE("UPB-",B16,) -> UPB-REP1.5x96 | O16: 435 | P16: =CONCATENATE("MSL-",B16,) -> MSL-REP1.5x96 | Q16: 435 | R16: =CONCATENATE("DGS-",B16,) -> DGS-REP1.5x96
A17: Refrigerator Return Panel: 24" W x 96" H, 3" return filler included | B17: REP3x96 | C17: 480 | D17: =CONCATENATE("ONB-",B17,) -> ONB-REP3x96 | E17: 467 | F17: =CONCATENATE("WHS-",B17) -> WHS-REP3x96 | G17: 480 | H17: =CONCATENATE("ESS-",B17) -> ESS-REP3x96 | I17: 480 | J17: =CONCATENATE("SIB-",B17) -> SIB-REP3x96 | K17: 467 | L17: =CONCATENATE("GRS-",B17,) -> GRS-REP3x96 | M17: 480 | N17: =CONCATENATE("UPB-",B17,) -> UPB-REP3x96 | O17: 480 | P17: =CONCATENATE("MSL-",B17,) -> MSL-REP3x96 | Q17: 480 | R17: =CONCATENATE("DGS-",B17,) -> DGS-REP3x96
A18: Cabinet Fillers, 3/4" Thick:
A19: Base Cabinet Filler: 3" W x 30" H | B19: BF3 | C19: 67 | D19: =CONCATENATE("ONB-",B19,) -> ONB-BF3 | E19: 64 | F19: =CONCATENATE("WHS-",B19,) -> WHS-BF3 | G19: 67 | H19: =CONCATENATE("ESS-",B19,) -> ESS-BF3 | I19: 67 | J19: =CONCATENATE("SIB-",B19) -> SIB-BF3 | K19: 64.2 | L19: =CONCATENATE("GRS-",B19,) -> GRS-BF3 | M19: 67 | N19: =CONCATENATE("UPB-",B19,) -> UPB-BF3 | O19: 67 | P19: =CONCATENATE("MSL-",B19,) -> MSL-BF3 | Q19: 67 | R19: =CONCATENATE("DGS-",B19,) -> DGS-BF3
A20: Base Cabinet Filler: 6" W x 30" H | B20: BF6 | C20: 123 | D20: =CONCATENATE("ONB-",B20,) -> ONB-BF6 | E20: 118 | F20: =CONCATENATE("WHS-",B20,) -> WHS-BF6 | G20: 123 | H20: =CONCATENATE("ESS-",B20,) -> ESS-BF6 | I20: 123 | J20: =CONCATENATE("SIB-",B20) -> SIB-BF6 | K20: 117.7 | L20: =CONCATENATE("GRS-",B20,) -> GRS-BF6 | M20: 123 | N20: =CONCATENATE("UPB-",B20,) -> UPB-BF6 | O20: 123 | P20: =CONCATENATE("MSL-",B20,) -> MSL-BF6 | Q20: 123 | R20: =CONCATENATE("DGS-",B20,) -> DGS-BF6
A21: Wall Cabinet Filler: 3" W x 30" H | B21: WF330 | C21: 45 | D21: =CONCATENATE("ONB-",B21,) -> ONB-WF330 | E21: 43 | F21: =CONCATENATE("WHS-",B21,) -> WHS-WF330 | G21: 45 | H21: =CONCATENATE("ESS-",B21,) -> ESS-WF330 | I21: 45 | J21: =CONCATENATE("SIB-",B21) -> SIB-WF330 | K21: 42.8 | L21: =CONCATENATE("GRS-",B21,) -> GRS-WF330 | M21: 45 | N21: =CONCATENATE("UPB-",B21,) -> UPB-WF330 | O21: 45 | P21: =CONCATENATE("MSL-",B21,) -> MSL-WF330 | Q21: 45 | R21: =CONCATENATE("DGS-",B21,) -> DGS-WF330
A22: Wall Cabinet Filler: 3" W x 36" H | B22: WF336 | C22: 50 | D22: =CONCATENATE("ONB-",B22,) -> ONB-WF336 | E22: 48 | F22: =CONCATENATE("WHS-",B22,) -> WHS-WF336 | G22: 50 | H22: =CONCATENATE("ESS-",B22,) -> ESS-WF336 | I22: 50 | J22: =CONCATENATE("SIB-",B22) -> SIB-WF336 | K22: 48.15 | L22: =CONCATENATE("GRS-",B22,) -> GRS-WF336 | M22: 50 | N22: =CONCATENATE("UPB-",B22,) -> UPB-WF336 | O22: 50 | P22: =CONCATENATE("MSL-",B22,) -> MSL-WF336 | Q22: 50 | R22: =CONCATENATE("DGS-",B22,) -> DGS-WF336
A23: Wall Cabinet Filler: 3" W x 42" H | B23: WF342 | C23: 59 | D23: =CONCATENATE("ONB-",B23,) -> ONB-WF342 | E23: 57 | F23: =CONCATENATE("WHS-",B23,) -> WHS-WF342 | G23: 59 | H23: =CONCATENATE("ESS-",B23,) -> ESS-WF342 | I23: 59 | J23: =CONCATENATE("SIB-",B23) -> SIB-WF342 | K23: 56.71 | L23: =CONCATENATE("GRS-",B23,) -> GRS-WF342 | M23: 59 | N23: =CONCATENATE("UPB-",B23,) -> UPB-WF342 | O23: 59 | P23: =CONCATENATE("MSL-",B23,) -> MSL-WF342 | Q23: 59 | R23: =CONCATENATE("DGS-",B23,) -> DGS-WF342
A24: Wall (Tall) Cabinet Filler: 3" W x 96" H | B24: WF396 | C24: 136 | D24: =CONCATENATE("ONB-",B24,) -> ONB-WF396 | E24: 130 | F24: =CONCATENATE("WHS-",B24,) -> WHS-WF396 | G24: 136 | H24: =CONCATENATE("ESS-",B24,) -> ESS-WF396 | I24: 136 | J24: =CONCATENATE("SIB-",B24) -> SIB-WF396 | K24: 129.47 | L24: =CONCATENATE("GRS-",B24,) -> GRS-WF396 | M24: 136 | N24: =CONCATENATE("UPB-",B24,) -> UPB-WF396 | O24: 136 | P24: =CONCATENATE("MSL-",B24,) -> MSL-WF396 | Q24: 136 | R24: =CONCATENATE("DGS-",B24,) -> DGS-WF396
A25: Wall Cabinet Filler: 6" W x 30" H | B25: WF630 | C25: 78 | D25: =CONCATENATE("ONB-",B25,) -> ONB-WF630 | E25: 75 | F25: =CONCATENATE("WHS-",B25,) -> WHS-WF630 | G25: 78 | H25: =CONCATENATE("ESS-",B25,) -> ESS-WF630 | I25: 78 | J25: =CONCATENATE("SIB-",B25) -> SIB-WF630 | K25: 74.9 | L25: =CONCATENATE("GRS-",B25,) -> GRS-WF630 | M25: 78 | N25: =CONCATENATE("UPB-",B25,) -> UPB-WF630 | O25: 78 | P25: =CONCATENATE("MSL-",B25,) -> MSL-WF630 | Q25: 78 | R25: =CONCATENATE("DGS-",B25,) -> DGS-WF630
A26: Wall Cabinet Filler: 6" W x 36" H | B26: WF636 | C26: 90 | D26: =CONCATENATE("ONB-",B26,) -> ONB-WF636 | E26: 86 | F26: =CONCATENATE("WHS-",B26,) -> WHS-WF636 | G26: 90 | H26: =CONCATENATE("ESS-",B26,) -> ESS-WF636 | I26: 90 | J26: =CONCATENATE("SIB-",B26) -> SIB-WF636 | K26: 85.6 | L26: =CONCATENATE("GRS-",B26,) -> GRS-WF636 | M26: 90 | N26: =CONCATENATE("UPB-",B26,) -> UPB-WF636 | O26: 90 | P26: =CONCATENATE("MSL-",B26,) -> MSL-WF636 | Q26: 90 | R26: =CONCATENATE("DGS-",B26,) -> DGS-WF636
A27: Wall Cabinet Filler: 6" W x 42" H | B27: WF642 | C27: 118 | D27: =CONCATENATE("ONB-",B27,) -> ONB-WF642 | E27: 112 | F27: =CONCATENATE("WHS-",B27,) -> WHS-WF642 | G27: 118 | H27: =CONCATENATE("ESS-",B27,) -> ESS-WF642 | I27: 118 | J27: =CONCATENATE("SIB-",B27) -> SIB-WF642 | K27: 112.35 | L27: =CONCATENATE("GRS-",B27,) -> GRS-WF642 | M27: 118 | N27: =CONCATENATE("UPB-",B27,) -> UPB-WF642 | O27: 118 | P27: =CONCATENATE("MSL-",B27,) -> MSL-WF642 | Q27: 118 | R27: =CONCATENATE("DGS-",B27,) -> DGS-WF642
A28: Wall (Tall) Cabinet Filler: 6" W x 96" H | B28: WF696 | C28: 272 | D28: =CONCATENATE("ONB-",B28,) -> ONB-WF696 | E28: 260 | F28: =CONCATENATE("WHS-",B28,) -> WHS-WF696 | G28: 272 | H28: =CONCATENATE("ESS-",B28,) -> ESS-WF696 | I28: 272 | J28: =CONCATENATE("SIB-",B28) -> SIB-WF696 | K28: 260.01 | L28: =CONCATENATE("GRS-",B28,) -> GRS-WF696 | M28: 272 | N28: =CONCATENATE("UPB-",B28,) -> UPB-WF696 | O28: 272 | P28: =CONCATENATE("MSL-",B28,) -> MSL-WF696 | Q28: 272 | R28: =CONCATENATE("DGS-",B28,) -> DGS-WF696
A29: Tall Filler: 1.5" W x 96" H, includes dado for use as return | B29: TF1.5*96 | C29: 67 | D29: =CONCATENATE("ONB-",B29,) -> ONB-TF1.5*96 | E29: 64 | F29: =CONCATENATE("WHS-",B29,) -> WHS-TF1.5*96 | G29: 67 | H29: =CONCATENATE("ESS-",B29,) -> ESS-TF1.5*96 | I29: 67 | J29: =CONCATENATE("SIB-",B29) -> SIB-TF1.5*96 | K29: 64.2 | L29: =CONCATENATE("GRS-",B29,) -> GRS-TF1.5*96 | M29: 67 | N29: =CONCATENATE("UPB-",B29,) -> UPB-TF1.5*96 | O29: 67 | P29: =CONCATENATE("MSL-",B29,) -> MSL-TF1.5*96 | Q29: 67 | R29: =CONCATENATE("DGS-",B29,) -> DGS-TF1.5*96
A30: Tall Filler: 3" W x 96" H | B30: TF396 | C30: 134 | D30: =CONCATENATE("ONB-",B30,) -> ONB-TF396 | E30: 129 | F30: =CONCATENATE("WHS-",B30,) -> WHS-TF396 | G30: 134 | H30: =CONCATENATE("ESS-",B30,) -> ESS-TF396 | I30: 134 | J30: =CONCATENATE("SIB-",B30) -> SIB-TF396 | K30: 128.4 | L30: =CONCATENATE("GRS-",B30,) -> GRS-TF396 | M30: 134 | N30: =CONCATENATE("UPB-",B30,) -> UPB-TF396 | O30: 134 | P30: =CONCATENATE("MSL-",B30,) -> MSL-TF396 | Q30: 134 | R30: =CONCATENATE("DGS-",B30,) -> DGS-TF396
A31: Tall Filler: 6" W x 96" H | B31: TF696 | C31: 224 | D31: =CONCATENATE("ONB-",B31,) -> ONB-TF696 | E31: 214 | F31: =CONCATENATE("WHS-",B31,) -> WHS-TF696 | G31: 224 | H31: =CONCATENATE("ESS-",B31,) -> ESS-TF696 | I31: 224 | J31: =CONCATENATE("SIB-",B31) -> SIB-TF696 | K31: 214 | L31: =CONCATENATE("GRS-",B31,) -> GRS-TF696 | M31: 224 | N31: =CONCATENATE("UPB-",B31,) -> UPB-TF696 | O31: 224 | P31: =CONCATENATE("MSL-",B31,) -> MSL-TF696 | Q31: 224 | R31: =CONCATENATE("DGS-",B31,) -> DGS-TF696
A32: Molding, 96" Length:
A33: Scribe Molding: 3/4" Tall & 1/4" Thick, Rounded on one edge | B33: SM8 | C33: 37 | D33: =CONCATENATE("ONB-",B33,) -> ONB-SM8 | E33: 35 | F33: =CONCATENATE("WHS-",B33,) -> WHS-SM8 | G33: 37 | H33: =CONCATENATE("ESS-",B33,) -> ESS-SM8 | I33: 37 | J33: =CONCATENATE("SIB-",B33) -> SIB-SM8 | K33: 35.31 | L33: =CONCATENATE("GRS-",B33,) -> GRS-SM8 | M33: 37 | N33: =CONCATENATE("UPB-",B33,) -> UPB-SM8 | O33: 37 | P33: =CONCATENATE("MSL-",B33,) -> MSL-SM8 | Q33: 37 | R33: =CONCATENATE("DGS-",B33,) -> DGS-SM8
A34: Batten Molding: 3/4" Tall & 1/4" Thick, Rounded on two edges | B34: SDM8 | C34: 44 | D34: =CONCATENATE("ONB-",B34,) -> ONB-SDM8 | E34: 42 | F34: =CONCATENATE("WHS-",B34,) -> WHS-SDM8 | G34: 44 | H34: =CONCATENATE("ESS-",B34,) -> ESS-SDM8 | I34: 44 | J34: =CONCATENATE("SIB-",B34) -> SIB-SDM8 | K34: 42 | L34: =CONCATENATE("GRS-",B34,) -> GRS-SDM8 | M34: 44 | N34: =CONCATENATE("UPB-",B34,) -> UPB-SDM8 | O34: 44 | P34: =CONCATENATE("MSL-",B34,) -> MSL-SDM8 | Q34: 44 | R34: =CONCATENATE("DGS-",B34,) -> DGS-SDM8
A35: Cove Molding: 3/4" Tall | B35: Cove Molding | C35: 112 | D35: =CONCATENATE("ONB-",B35,) -> ONB-Cove Molding | E35: 107 | F35: =CONCATENATE("WHS-",B35,) -> WHS-Cove Molding | G35: 112 | H35: =CONCATENATE("ESS-",B35,) -> ESS-Cove Molding | I35: 112 | J35: =CONCATENATE("SIB-",B35) -> SIB-Cove Molding | K35: 107 | L35: =CONCATENATE("GRS-",B35,) -> GRS-Cove Molding | M35: 112 | N35: =CONCATENATE("UPB-",B35,) -> UPB-Cove Molding | O35: 112 | P35: =CONCATENATE("MSL-",B35,) -> MSL-Cove Molding | Q35: 112 | R35: =CONCATENATE("DGS-",B35,) -> DGS-Cove Molding
A36: Outside Corner Molding: 3/4" x 3/4" | B36: OCM8 | C36: 75 | D36: =CONCATENATE("ONB-",B36,) -> ONB-OCM8 | E36: 72 | F36: =CONCATENATE("WHS-",B36,) -> WHS-OCM8 | G36: 75 | H36: =CONCATENATE("ESS-",B36,) -> ESS-OCM8 | I36: 75 | J36: =CONCATENATE("SIB-",B36) -> SIB-OCM8 | K36: 71.69 | L36: =CONCATENATE("GRS-",B36,) -> GRS-OCM8 | M36: 75 | N36: =CONCATENATE("UPB-",B36,) -> UPB-OCM8 | O36: 75 | P36: =CONCATENATE("MSL-",B36,) -> MSL-OCM8 | Q36: 75 | R36: =CONCATENATE("DGS-",B36,) -> DGS-OCM8
A37: Light Rail Molding: 1 1/2" Tall | B37: LM8 | C37: 106 | D37: =CONCATENATE("ONB-",B37,) -> ONB-LM8 | E37: 102 | F37: =CONCATENATE("WHS-",B37,) -> WHS-LM8 | G37: 106 | H37: =CONCATENATE("ESS-",B37,) -> ESS-LM8 | I37: 106 | J37: =CONCATENATE("SIB-",B37) -> SIB-LM8 | K37: 101.65 | L37: =CONCATENATE("GRS-",B37,) -> GRS-LM8 | M37: 106 | N37: =CONCATENATE("UPB-",B37,) -> UPB-LM8 | O37: 106 | P37: =CONCATENATE("MSL-",B37,) -> MSL-LM8 | Q37: 106 | R37: =CONCATENATE("DGS-",B37,) -> DGS-LM8
A38: Quarter Round Molding: 3/4" x 3/4" | B38: QRM8 | C38: 67 | D38: =CONCATENATE("ONB-",B38,) -> ONB-QRM8 | E38: 64 | F38: =CONCATENATE("WHS-",B38,) -> WHS-QRM8 | G38: 67 | H38: =CONCATENATE("ESS-",B38,) -> ESS-QRM8 | I38: 67 | J38: =CONCATENATE("SIB-",B38) -> SIB-QRM8 | K38: 64.2 | L38: =CONCATENATE("GRS-",B38,) -> GRS-QRM8 | M38: 67 | N38: =CONCATENATE("UPB-",B38,) -> UPB-QRM8 | O38: 67 | P38: =CONCATENATE("MSL-",B38,) -> MSL-QRM8 | Q38: 67 | R38: =CONCATENATE("DGS-",B38,) -> DGS-QRM8
A39: Crown Molding: Rises 2 1/4" tall from cabinet | B39: SCM2 1/4 | C39: 171 | D39: =CONCATENATE("ONB-",B39,) -> ONB-SCM2 1/4 | E39: 107 | F39: =CONCATENATE("WHS-",B39,) -> WHS-SCM2 1/4 | G39: 171 | H39: =CONCATENATE("ESS-",B39,) -> ESS-SCM2 1/4 | I39: 171 | J39: =CONCATENATE("SIB-",B39) -> SIB-SCM2 1/4 | K39: 107 | L39: =CONCATENATE("GRS-",B39,) -> GRS-SCM2 1/4 | M39: 171 | N39: =CONCATENATE("UPB-",B39,) -> UPB-SCM2 1/4 | O39: 171 | P39: =CONCATENATE("MSL-",B39,) -> MSL-SCM2 1/4 | Q39: 171 | R39: =CONCATENATE("DGS-",B39,) -> DGS-SCM2 1/4
A40: Crown Molding: Rises 2 1/4" tall from cabinet | B40: SCM2 1/4-HEEL | C40: N/A | D40: =CONCATENATE("ONB-",B40,) -> ONB-SCM2 1/4-HEEL | E40: 144 | F40: =CONCATENATE("WHS-",B40,) -> WHS-SCM2 1/4-HEEL | G40: N/A | H40: =CONCATENATE("ESS-",B40,) -> ESS-SCM2 1/4-HEEL | I40: N/A | J40: =CONCATENATE("SIB-",B40) -> SIB-SCM2 1/4-HEEL | K40: N/A | L40: =CONCATENATE("GRS-",B40,) -> GRS-SCM2 1/4-HEEL | M40: 214 | N40: =CONCATENATE("UPB-",B40,) -> UPB-SCM2 1/4-HEEL | O40: N/A | P40: =CONCATENATE("MSL-",B40,) -> MSL-SCM2 1/4-HEEL | Q40: N/A | R40: =CONCATENATE("DGS-",B40,) -> DGS-SCM2 1/4-HEEL
A41: Crown Molding: Rises 3 5/8" tall from cabinet | B41: SCM3 5/8 | C41: 198 | D41: =CONCATENATE("ONB-",B41,) -> ONB-SCM3 5/8 | E41: 127 | F41: =CONCATENATE("WHS-",B41,) -> WHS-SCM3 5/8 | G41: 198 | H41: =CONCATENATE("ESS-",B41,) -> ESS-SCM3 5/8 | I41: 198 | J41: =CONCATENATE("SIB-",B41) -> SIB-SCM3 5/8 | K41: 127 | L41: =CONCATENATE("GRS-",B41,) -> GRS-SCM3 5/8 | M41: 198 | N41: =CONCATENATE("UPB-",B41,) -> UPB-SCM3 5/8 | O41: 198 | P41: =CONCATENATE("MSL-",B41,) -> MSL-SCM3 5/8 | Q41: 198 | R41: =CONCATENATE("DGS-",B41,) -> DGS-SCM3 5/8
A42: Crown Molding: Rises 3 5/8" tall from cabinet | B42: SCM3 5/8-HEEL | C42: N/A | D42: =CONCATENATE("ONB-",B42,) -> ONB-SCM3 5/8-HEEL | E42: 171 | F42: =CONCATENATE("WHS-",B42,) -> WHS-SCM3 5/8-HEEL | G42: N/A | H42: =CONCATENATE("ESS-",B42,) -> ESS-SCM3 5/8-HEEL | I42: N/A | J42: =CONCATENATE("SIB-",B42) -> SIB-SCM3 5/8-HEEL | K42: N/A | L42: =CONCATENATE("GRS-",B42,) -> GRS-SCM3 5/8-HEEL | M42: 249 | N42: =CONCATENATE("UPB-",B42,) -> UPB-SCM3 5/8-HEEL | O42: N/A | P42: =CONCATENATE("MSL-",B42,) -> MSL-SCM3 5/8-HEEL | Q42: N/A | R42: =CONCATENATE("DGS-",B42,) -> DGS-SCM3 5/8-HEEL
A43: Base Molding: 4" Tall & 3/4" Thick | B43: BM8 | C43: 168 | D43: =CONCATENATE("ONB-",B43,) -> ONB-BM8 | E43: 161 | F43: =CONCATENATE("WHS-",B43,) -> WHS-BM8 | G43: 168 | H43: =CONCATENATE("ESS-",B43,) -> ESS-BM8 | I43: 168 | J43: =CONCATENATE("SIB-",B43) -> SIB-BM8 | K43: 160.5 | L43: =CONCATENATE("GRS-",B43,) -> GRS-BM8 | M43: 168 | N43: =CONCATENATE("UPB-",B43,) -> UPB-BM8 | O43: 168 | P43: =CONCATENATE("MSL-",B43,) -> MSL-BM8 | Q43: 168 | R43: =CONCATENATE("DGS-",B43,) -> DGS-BM8
A44: Toe Kick: 4" Tall & 1/4" Thick: | B44: TK8 | C44: 49 | D44: =CONCATENATE("ONB-",B44,) -> ONB-TK8 | E44: 47 | F44: =CONCATENATE("WHS-",B44,) -> WHS-TK8 | G44: 49 | H44: =CONCATENATE("ESS-",B44,) -> ESS-TK8 | I44: 49 | J44: =CONCATENATE("SIB-",B44) -> SIB-TK8 | K44: 47.08 | L44: =CONCATENATE("GRS-",B44,) -> GRS-TK8 | M44: 49 | N44: =CONCATENATE("UPB-",B44,) -> UPB-TK8 | O44: 49 | P44: =CONCATENATE("MSL-",B44,) -> MSL-TK8 | Q44: 49 | R44: =CONCATENATE("DGS-",B44,) -> DGS-TK8
A45: Decorative (False) Doors:
A46: Base False Door: 20 1/2" W x 29 1/4" H | B46: BFD21 | C46: 231 | D46: =CONCATENATE("ONB-",B46,) -> ONB-BFD21 | E46: 210 | F46: =CONCATENATE("WHS-",B46,) -> WHS-BFD21 | G46: 231 | H46: =CONCATENATE("ESS-",B46,) -> ESS-BFD21 | I46: 231 | J46: =CONCATENATE("SIB-",B46) -> SIB-BFD21 | K46: 210 | L46: =CONCATENATE("GRS-",B46,) -> GRS-BFD21 | M46: 231 | N46: =CONCATENATE("UPB-",B46,) -> UPB-BFD21 | O46: 231 | P46: =CONCATENATE("MSL-",B46,) -> MSL-BFD21 | Q46: 231 | R46: =CONCATENATE("DGS-",B46,) -> DGS-BFD21
A47: Base False Door: 23 1/2" W x 29 1/4" H | B47: BFD24 | C47: 290 | D47: =CONCATENATE("ONB-",B47,) -> ONB-BFD24 | E47: 235 | F47: =CONCATENATE("WHS-",B47,) -> WHS-BFD24 | G47: 290 | H47: =CONCATENATE("ESS-",B47,) -> ESS-BFD24 | I47: 290 | J47: =CONCATENATE("SIB-",B47) -> SIB-BFD24 | K47: 235.4 | L47: =CONCATENATE("GRS-",B47,) -> GRS-BFD24 | M47: 290 | N47: =CONCATENATE("UPB-",B47,) -> UPB-BFD24 | O47: 290 | P47: =CONCATENATE("MSL-",B47,) -> MSL-BFD24 | Q47: 290 | R47: =CONCATENATE("DGS-",B47,) -> DGS-BFD24
A48: Wall False Door: 11 1/2" W x 29 1/2" H | B48: FD1230 | C48: 146 | D48: =CONCATENATE("ONB-",B48,) -> ONB-FD1230 | E48: 139 | F48: =CONCATENATE("WHS-",B48,) -> WHS-FD1230 | G48: 146 | H48: =CONCATENATE("ESS-",B48,) -> ESS-FD1230 | I48: 146 | J48: =CONCATENATE("SIB-",B48) -> SIB-FD1230 | K48: 139.1 | L48: =CONCATENATE("GRS-",B48,) -> GRS-FD1230 | M48: 146 | N48: =CONCATENATE("UPB-",B48,) -> UPB-FD1230 | O48: 146 | P48: =CONCATENATE("MSL-",B48,) -> MSL-FD1230 | Q48: 146 | R48: =CONCATENATE("DGS-",B48,) -> DGS-FD1230
A49: Wall False Door: 11 1/2" W x 35 1/2" H | B49: FD1236 | C49: 162 | D49: =CONCATENATE("ONB-",B49,) -> ONB-FD1236 | E49: 155 | F49: =CONCATENATE("WHS-",B49,) -> WHS-FD1236 | G49: 162 | H49: =CONCATENATE("ESS-",B49,) -> ESS-FD1236 | I49: 162 | J49: =CONCATENATE("SIB-",B49) -> SIB-FD1236 | K49: 155.15 | L49: =CONCATENATE("GRS-",B49,) -> GRS-FD1236 | M49: 162 | N49: =CONCATENATE("UPB-",B49,) -> UPB-FD1236 | O49: 162 | P49: =CONCATENATE("MSL-",B49,) -> MSL-FD1236 | Q49: 162 | R49: =CONCATENATE("DGS-",B49,) -> DGS-FD1236
A50: Wall False Door: 11 1/2" W x 41 1/2" H | B50: FD1242 | C50: 168 | D50: =CONCATENATE("ONB-",B50,) -> ONB-FD1242 | E50: 161 | F50: =CONCATENATE("WHS-",B50,) -> WHS-FD1242 | G50: 168 | H50: =CONCATENATE("ESS-",B50,) -> ESS-FD1242 | I50: 168 | J50: =CONCATENATE("SIB-",B50) -> SIB-FD1242 | K50: 160.5 | L50: =CONCATENATE("GRS-",B50,) -> GRS-FD1242 | M50: 168 | N50: =CONCATENATE("UPB-",B50,) -> UPB-FD1242 | O50: 168 | P50: =CONCATENATE("MSL-",B50,) -> MSL-FD1242 | Q50: 168 | R50: =CONCATENATE("DGS-",B50,) -> DGS-FD1242
A51: Vanity Mirrors:
A52: Mirror: 24" W x 30" H | B52: MIRROR2430 | C52: 213 | D52: =CONCATENATE("ONB-",B52,) -> ONB-MIRROR2430 | E52: 200 | F52: =CONCATENATE("WHS-",B52) -> WHS-MIRROR2430 | G52: 213 | H52: =CONCATENATE("ESS-",B52) -> ESS-MIRROR2430 | I52: 213 | J52: =CONCATENATE("SIB-",B52) -> SIB-MIRROR2430 | K52: 200 | L52: =CONCATENATE("GRS-",B52,) -> GRS-MIRROR2430 | M52: 213 | N52: =CONCATENATE("UPB-",B52,) -> UPB-MIRROR2430 | O52: 213 | P52: =CONCATENATE("MSL-",B52,) -> MSL-MIRROR2430 | Q52: 213 | R52: =CONCATENATE("DGS-",B52,) -> DGS-MIRROR2430
A53: Mirror: 30" W x 30" H | B53: MIRROR3030 | C53: 266 | D53: =CONCATENATE("ONB-",B53,) -> ONB-MIRROR3030 | E53: 250 | F53: =CONCATENATE("WHS-",B53) -> WHS-MIRROR3030 | G53: 266 | H53: =CONCATENATE("ESS-",B53) -> ESS-MIRROR3030 | I53: 266 | J53: =CONCATENATE("SIB-",B53) -> SIB-MIRROR3030 | K53: 250 | L53: =CONCATENATE("GRS-",B53,) -> GRS-MIRROR3030 | M53: 266 | N53: =CONCATENATE("UPB-",B53,) -> UPB-MIRROR3030 | O53: 266 | P53: =CONCATENATE("MSL-",B53,) -> MSL-MIRROR3030 | Q53: 266 | R53: =CONCATENATE("DGS-",B53,) -> DGS-MIRROR3030
A54: Turn Post: 3" W x 34.5" H x 3" D | B54: POST | C54: 392 | D54: =CONCATENATE("ONB-",B54,) -> ONB-POST | E54: 375 | F54: =CONCATENATE("WHS-",B54,) -> WHS-POST | G54: 392 | H54: =CONCATENATE("ESS-",B54,) -> ESS-POST | I54: 392 | J54: =CONCATENATE("SIB-",B54) -> SIB-POST | K54: 374.5 | L54: =CONCATENATE("GRS-",B54,) -> GRS-POST | M54: 392 | N54: =CONCATENATE("UPB-",B54,) -> UPB-POST | O54: 392 | P54: =CONCATENATE("MSL-",B54,) -> MSL-POST | Q54: 392 | R54: =CONCATENATE("DGS-",B54,) -> DGS-POST
A55: Trash Cabinet Kit: Pullout assembly, (2) 27 qt. Trash Cans | B55: TRASH KIT-18 | C55: 550 | D55: TRASH KIT-18 | E55: 550 | F55: TRASH KIT-18 | G55: 550 | H55: TRASH KIT-18 | I55: 550 | J55: TRASH KIT-18 | K55: 550 | L55: TRASH KIT-18 | M55: 550 | N55: TRASH KIT-18 | O55: 550 | P55: TRASH KIT-18 | Q55: 550 | R55: =CONCATENATE("DGS-",B55,) -> DGS-TRASH KIT-18
A56: Miscellaneous Accessories:
A57: Touch Up Kit: Matching paint pen, putty, and application razor | B57: TOUCH UP | C57: 96 | D57: =CONCATENATE("ONB-",B57,) -> ONB-TOUCH UP | E57: 96 | F57: =CONCATENATE("WHS-",B57,) -> WHS-TOUCH UP | G57: 96 | H57: =CONCATENATE("ESS-",B57,) -> ESS-TOUCH UP | I57: 96 | J57: =CONCATENATE("SIB-",B57) -> SIB-TOUCH UP | K57: 96 | L57: =CONCATENATE("GRS-",B57,) -> GRS-TOUCH UP | M57: 96 | N57: =CONCATENATE("UPB-",B57,) -> UPB-TOUCH UP | O57: 96 | P57: =CONCATENATE("MSL-",B57,) -> MSL-TOUCH UP | Q57: 96 | R57: =CONCATENATE("DGS-",B57,) -> DGS-TOUCH UP
A58: Matching Gallon Paint (Painted finishes ONLY) | B58: Gallon Paint | C58: 373 | D58: =CONCATENATE("ONB-",B58,) -> ONB-Gallon Paint | E58: 350 | F58: =CONCATENATE("WHS-",B58,) -> WHS-Gallon Paint | G58: N/A | H58: =CONCATENATE("ESS-",B58,) -> ESS-Gallon Paint | I58: 373 | J58: =CONCATENATE("SIB-",B58) -> SIB-Gallon Paint | K58: 350 | L58: =CONCATENATE("GRS-",B58,) -> GRS-Gallon Paint | M58: 373 | N58: =CONCATENATE("UPB-",B58,) -> UPB-Gallon Paint | O58: N/A | P58: =CONCATENATE("MSL-",B58,) -> MSL-Gallon Paint | Q58: 373 | R58: =CONCATENATE("DGS-",B58,) -> DGS-Gallon Paint
A59: Matching Spray Can (Painted finishes ONLY) | B59: Rattle Can | C59: 106 | D59: =CONCATENATE("ONB-",B59,) -> ONB-Rattle Can | E59: 100 | F59: =CONCATENATE("WHS-",B59,) -> WHS-Rattle Can | G59: N/A | H59: =CONCATENATE("ESS-",B59,) -> ESS-Rattle Can | I59: 106 | J59: =CONCATENATE("SIB-",B59) -> SIB-Rattle Can | K59: 100 | L59: =CONCATENATE("GRS-",B59,) -> GRS-Rattle Can | M59: 106 | N59: =CONCATENATE("UPB-",B59,) -> UPB-Rattle Can | O59: N/A | P59: =CONCATENATE("MSL-",B59,) -> MSL-Rattle Can | Q59: 106 | R59: =CONCATENATE("DGS-",B59,) -> DGS-Rattle Can

Sheet Frameless Catalog List Price
C2: GLOSSY WHITE | E2: SLICED OAK SHAKER | G2: BLACK WALNUT | I2: WEATHERED OAK SHAKER | K2: GLOSSY GREY | M2: NATURAL OAK | O2: WHITE OAK | Q2: MATTE WHITE | S2: MATTE GREY | U2: MATTE BLUE | W2: GLOSSY BLACK
A3: Description | B3: Cabinet Name | C3: List Price | D3: Inventory Code | E3: List Price | F3: Inventory Code | G3: List Price | H3: Inventory Code | I3: List Price | J3: Inventory Code | K3: List Price | L3: Inventory Code | M3: List Price | N3: Inventory Code | O3: List Price | P3: Inventory Code | Q3: List Price | R3: Inventory Code | S3: List Price | T3: Inventory Code | U3: List Price | V3: Inventory Code | W3: List Price | X3: Inventory Code | Y3: Handles
A4: Base Cabinets with Drawer, 24" Depth
A5: 12" Base Cabinet: 1 Door & 1 Drawer | B5: B12 | C5: =IF('Summary Sheet'!$M$4="Plywood",VLOOKUP($B5,'Pwood & PB List'!$B$4:$V$158,9,FALSE),IF('Summary Sheet'!$M$4="PB w/ Wood Drawers",VLOOKUP($B5,'Pwood & PB List'!$B$4:$V$158,13,FALSE),IF('Summary Sheet'!$M$4="PB w/ PB Drawers",VLOOKUP($B5,'Pwood & PB List'!$B$4:$V$158,17,FALSE)))) -> 747.5 | D5: =CONCATENATE("GLW-",B5) -> GLW-B12 | E5: =IF('Summary Sheet'!$M$4="Plywood",VLOOKUP($B5,'Pwood & PB List'!$B$4:$V$158,10,FALSE),IF('Summary Sheet'!$M$4="PB w/ Wood Drawers",VLOOKUP($B5,'Pwood & PB List'!$B$4:$V$158,14,FALSE),IF('Summary Sheet'!$M$4="PB w/ PB Drawers",VLOOKUP($B5,'Pwood & PB List'!$B$4:$V$158,18,FALSE)))) -> 729.33 | F5: =CONCATENATE("SLO-",B5) -> SLO-B12 | G5: =IF('Summary Sheet'!$M$4="Plywood",VLOOKUP($B5,'Pwood & PB List'!$B$4:$V$158,11,FALSE),IF('Summary Sheet'!$M$4="PB w/ Wood Drawers",VLOOKUP($B5,'Pwood & PB List'!$B$4:$V$158,15,FALSE),IF('Summary Sheet'!$M$4="PB w/ PB Drawers",VLOOKUP($B5,'Pwood & PB List'!$B$4:$V$158,19,FALSE)))) -> 709.895 | H5: =CONCATENATE("BLW-",B5) -> BLW-B12 | I5: =IF('Summary Sheet'!$M$4="Plywood",VLOOKUP($B5,'Pwood & PB List'!$B$4:$V$158,10,FALSE),IF('Summary Sheet'!$M$4="PB w/ Wood Drawers",VLOOKUP($B5,'Pwood & PB List'!$B$4:$V$158,14,FALSE),IF('Summary Sheet'!$M$4="PB w/ PB Drawers",VLOOKUP($B5,'Pwood & PB List'!$B$4:$V$158,18,FALSE)))) -> 729.33 | J5: =CONCATENATE("WEO-",B5) -> WEO-B12 | K5: =IF('Summary Sheet'!$M$4="Plywood",VLOOKUP($B5,'Pwood & PB List'!$B$4:$V$158,9,FALSE),IF('Summary Sheet'!$M$4="PB w/ Wood Drawers",VLOOKUP($B5,'Pwood & PB List'!$B$4:$V$158,13,FALSE),IF('Summary Sheet'!$M$4="PB w/ PB Drawers",VLOOKUP($B5,'Pwood & PB List'!$B$4:$V$158,17,FALSE)))) -> 747.5 | L5: =CONCATENATE("GLG-",B5) -> GLG-B12 | M5: =IF('Summary Sheet'!$M$4="Plywood",VLOOKUP($B5,'Pwood & PB List'!$B$4:$V$158,12,FALSE),IF('Summary Sheet'!$M$4="PB w/ Wood Drawers",VLOOKUP($B5,'Pwood & PB List'!$B$4:$V$158,16,FALSE),IF('Summary Sheet'!$M$4="PB w/ PB Drawers",VLOOKUP($B5,'Pwood & PB List'!$B$4:$V$158,20,FALSE)))) -> 688.16 | N5: =CONCATENATE("NAO-",B5) -> NAO-B12 | O5: =IF('Summary Sheet'!$M$4="Plywood",VLOOKUP($B5,'Pwood & PB List'!$B$4:$V$158,12,FALSE),IF('Summary Sheet'!$M$4="PB w/ Wood Drawers",VLOOKUP($B5,'Pwood & PB List'!$B$4:$V$158,16,FALSE),IF('Summary Sheet'!$M$4="PB w/ PB Drawers",VLOOKUP($B5,'Pwood & PB List'!$B$4:$V$158,20,FALSE)))) -> 688.16 | P5: =CONCATENATE("WHO-",B5) -> WHO-B12 | Q5: =IF('Summary Sheet'!$M$4="Plywood",VLOOKUP($B5,'Pwood & PB List'!$B$4:$V$158,9,FALSE),IF('Summary Sheet'!$M$4="PB w/ Wood Drawers",VLOOKUP($B5,'Pwood & PB List'!$B$4:$V$158,13,FALSE),IF('Summary Sheet'!$M$4="PB w/ PB Drawers",VLOOKUP($B5,'Pwood & PB List'!$B$4:$V$158,17,FALSE)))) -> 747.5 | R5: =CONCATENATE("MAW-",B5) -> MAW-B12 | S5: =IF('Summary Sheet'!$M$4="Plywood",VLOOKUP($B5,'Pwood & PB List'!$B$4:$V$158,9,FALSE),IF('Summary Sheet'!$M$4="PB w/ Wood Drawers",VLOOKUP($B5,'Pwood & PB List'!$B$4:$V$158,13,FALSE),IF('Summary Sheet'!$M$4="PB w/ PB Drawers",VLOOKUP($B5,'Pwood & PB List'!$B$4:$V$158,17,FALSE)))) -> 747.5 | T5: =CONCATENATE("MAG-",B5) -> MAG-B12 | U5: =IF('Summary Sheet'!$M$4="Plywood",VLOOKUP($B5,'Pwood & PB List'!$B$4:$V$158,9,FALSE),IF('Summary Sheet'!$M$4="PB w/ Wood Drawers",VLOOKUP($B5,'Pwood & PB List'!$B$4:$V$158,13,FALSE),IF('Summary Sheet'!$M$4="PB w/ PB Drawers",VLOOKUP($B5,'Pwood & PB List'!$B$4:$V$158,17,FALSE)))) -> 747.5 | V5: =CONCATENATE("MAB-",B5) -> MAB-B12 | W5: =IF('Summary Sheet'!$M$4="Plywood",VLOOKUP($B5,'Pwood & PB List'!$B$4:$V$158,9,FALSE),IF('Summary Sheet'!$M$4="PB w/ Wood Drawers",VLOOKUP($B5,'Pwood & PB List'!$B$4:$V$158,13,FALSE),IF('Summary Sheet'!$M$4="PB w/ PB Drawers",VLOOKUP($B5,'Pwood & PB List'!$B$4:$V$158,17,FALSE)))) -> 747.5 | X5: =CONCATENATE("GLB-",B5) -> GLB-B12 | Y5: 2
A6: 15" Base Cabinet: 1 Door & 1 Drawer | B6: B15 | C6: =IF('Summary Sheet'!$M$4="Plywood",VLOOKUP($B6,'Pwood & PB List'!$B$4:$V$158,9,FALSE),IF('Summary Sheet'!$M$4="PB w/ Wood Drawers",VLOOKUP($B6,'Pwood & PB List'!$B$4:$V$158,13,FALSE),IF('Summary Sheet'!$M$4="PB w/ PB Drawers",VLOOKUP($B6,'Pwood & PB List'!$B$4:$V$158,17,FALSE)))) -> 828.23 | D6: =CONCATENATE("GLW-",B6) -> GLW-B15 | E6: =IF('Summary Sheet'!$M$4="Plywood",VLOOKUP($B6,'Pwood & PB List'!$B$4:$V$158,10,FALSE),IF('Summary Sheet'!$M$4="PB w/ Wood Drawers",VLOOKUP($B6,'Pwood & PB List'!$B$4:$V$158,14,FALSE),IF('Summary Sheet'!$M$4="PB w/ PB Drawers",VLOOKUP($B6,'Pwood & PB List'!$B$4:$V$158,18,FALSE)))) -> 805.46 | F6: =CONCATENATE("SLO-",B6) -> SLO-B15 | G6: =IF('Summary Sheet'!$M$4="Plywood",VLOOKUP($B6,'Pwood & PB List'!$B$4:$V$158,11,FALSE),IF('Summary Sheet'!$M$4="PB w/ Wood Drawers",VLOOKUP($B6,'Pwood & PB List'!$B$4:$V$158,15,FALSE),IF('Summary Sheet'!$M$4="PB w/ PB Drawers",VLOOKUP($B6,'Pwood & PB List'!$B$4:$V$158,19,FALSE)))) -> 781.195 | H6: =CONCATENATE("BLW-",B6) -> BLW-B15 | I6: =IF('Summary Sheet'!$M$4="Plywood",VLOOKUP($B6,'Pwood & PB List'!$B$4:$V$158,10,FALSE),IF('Summary Sheet'!$M$4="PB w/ Wood Drawers",VLOOKUP($B6,'Pwood & PB List'!$B$4:$V$158,14,FALSE),IF('Summary Sheet'!$M$4="PB w/ PB Drawers",VLOOKUP($B6,'Pwood & PB List'!$B$4:$V$158,18,FALSE)))) -> 805.46 | J6: =CONCATENATE("WEO-",B6) -> WEO-B15 | K6: =IF('Summary Sheet'!$M$4="Plywood",VLOOKUP($B6,'Pwood & PB List'!$B$4:$V$158,9,FALSE),IF('Summary Sheet'!$M$4="PB w/ Wood Drawers",VLOOKUP($B6,'Pwood & PB List'!$B$4:$V$158,13,FALSE),IF('Summary Sheet'!$M$4="PB w/ PB Drawers",VLOOKUP($B6,'Pwood & PB List'!$B$4:$V$158,17,FALSE)))) -> 828.23 | L6: =CONCATENATE("GLG-",B6) -> GLG-B15 | M6: =IF('Summary Sheet'!$M$4="Plywood",VLOOKUP($B6,'Pwood & PB List'!$B$4:$V$158,12,FALSE),IF('Summary Sheet'!$M$4="PB w/ Wood Drawers",VLOOKUP($B6,'Pwood & PB List'!$B$4:$V$158,16,FALSE),IF('Summary Sheet'!$M$4="PB w/ PB Drawers",VLOOKUP($B6,'Pwood & PB List'!$B$4:$V$158,20,FALSE)))) -> 753.825 | N6: =CONCATENATE("NAO-",B6) -> NAO-B15 | O6: =IF('Summary Sheet'!$M$4="Plywood",VLOOKUP($B6,'Pwood & PB List'!$B$4:$V$158,12,FALSE),IF('Summary Sheet'!$M$4="PB w/ Wood Drawers",VLOOKUP($B6,'Pwood & PB List'!$B$4:$V$158,16,FALSE),IF('Summary Sheet'!$M$4="PB w/ PB Drawers",VLOOKUP($B6,'Pwood & PB List'!$B$4:$V$158,20,FALSE)))) -> 753.825 | P6: =CONCATENATE("WHO-",B6) -> WHO-B15 | Q6: =IF('Summary Sheet'!$M$4="Plywood",VLOOKUP($B6,'Pwood & PB List'!$B$4:$V$158,9,FALSE),IF('Summary Sheet'!$M$4="PB w/ Wood Drawers",VLOOKUP($B6,'Pwood & PB List'!$B$4:$V$158,13,FALSE),IF('Summary Sheet'!$M$4="PB w/ PB Drawers",VLOOKUP($B6,'Pwood & PB List'!$B$4:$V$158,17,FALSE)))) -> 828.23 | R6: =CONCATENATE("MAW-",B6) -> MAW-B15 | S6: =IF('Summary Sheet'!$M$4="Plywood",VLOOKUP($B6,'Pwood & PB List'!$B$4:$V$158,9,FALSE),IF('Summary Sheet'!$M$4="PB w/ Wood Drawers",VLOOKUP($B6,'Pwood & PB List'!$B$4:$V$158,13,FALSE),IF('Summary Sheet'!$M$4="PB w/ PB Drawers",VLOOKUP($B6,'Pwood & PB List'!$B$4:$V$158,17,FALSE)))) -> 828.23 | T6: =CONCATENATE("MAG-",B6) -> MAG-B15 | U6: =IF('Summary Sheet'!$M$4="Plywood",VLOOKUP($B6,'Pwood & PB List'!$B$4:$V$158,9,FALSE),IF('Summary Sheet'!$M$4="PB w/ Wood Drawers",VLOOKUP($B6,'Pwood & PB List'!$B$4:$V$158,13,FALSE),IF('Summary Sheet'!$M$4="PB w/ PB Drawers",VLOOKUP($B6,'Pwood & PB List'!$B$4:$V$158,17,FALSE)))) -> 828.23 | V6: =CONCATENATE("MAB-",B6) -> MAB-B15 | W6: =IF('Summary Sheet'!$M$4="Plywood",VLOOKUP($B6,'Pwood & PB List'!$B$4:$V$158,9,FALSE),IF('Summary Sheet'!$M$4="PB w/ Wood Drawers",VLOOKUP($B6,'Pwood & PB List'!$B$4:$V$158,13,FALSE),IF('Summary Sheet'!$M$4="PB w/ PB Drawers",VLOOKUP($B6,'Pwood & PB List'!$B$4:$V$158,17,FALSE)))) -> 828.23 | X6: =CONCATENATE("GLB-",B6) -> GLB-B15 | Y6: 2
A7: 18" Base Cabinet: 1 Door & 1 Drawer | B7: B18 | C7: =IF('Summary Sheet'!$M$4="Plywood",VLOOKUP($B7,'Pwood & PB List'!$B$4:$V$158,9,FALSE),IF('Summary Sheet'!$M$4="PB w/ Wood Drawers",VLOOKUP($B7,'Pwood & PB List'!$B$4:$V$158,13,FALSE),IF('Summary Sheet'!$M$4="PB w/ PB Drawers",VLOOKUP($B7,'Pwood & PB List'!$B$4:$V$158,17,FALSE)))) -> 908.845 | D7: =CONCATENATE("GLW-",B7) -> GLW-B18 | E7: =IF('Summary Sheet'!$M$4="Plywood",VLOOKUP($B7,'Pwood & PB List'!$B$4:$V$158,10,FALSE),IF('Summary Sheet'!$M$4="PB w/ Wood Drawers",VLOOKUP($B7,'Pwood & PB List'!$B$4:$V$158,14,FALSE),IF('Summary Sheet'!$M$4="PB w/ PB Drawers",VLOOKUP($B7,'Pwood & PB List'!$B$4:$V$158,18,FALSE)))) -> 881.59 | F7: =CONCATENATE("SLO-",B7) -> SLO-B18 | G7: =IF('Summary Sheet'!$M$4="Plywood",VLOOKUP($B7,'Pwood & PB List'!$B$4:$V$158,11,FALSE),IF('Summary Sheet'!$M$4="PB w/ Wood Drawers",VLOOKUP($B7,'Pwood & PB List'!$B$4:$V$158,15,FALSE),IF('Summary Sheet'!$M$4="PB w/ PB Drawers",VLOOKUP($B7,'Pwood & PB List'!$B$4:$V$158,19,FALSE)))) -> 852.38 | H7: =CONCATENATE("BLW-",B7) -> BLW-B18 | I7: =IF('Summary Sheet'!$M$4="Plywood",VLOOKUP($B7,'Pwood & PB List'!$B$4:$V$158,10,FALSE),IF('Summary Sheet'!$M$4="PB w/ Wood Drawers",VLOOKUP($B7,'Pwood & PB List'!$B$4:$V$158,14,FALSE),IF('Summary Sheet'!$M$4="PB w/ PB Drawers",VLOOKUP($B7,'Pwood & PB List'!$B$4:$V$158,18,FALSE)))) -> 881.59 | J7: =CONCATENATE("WEO-",B7) -> WEO-B18 | K7: =IF('Summary Sheet'!$M$4="Plywood",VLOOKUP($B7,'Pwood & PB List'!$B$4:$V$158,9,FALSE),IF('Summary Sheet'!$M$4="PB w/ Wood Drawers",VLOOKUP($B7,'Pwood & PB List'!$B$4:$V$158,13,FALSE),IF('Summary Sheet'!$M$4="PB w/ PB Drawers",VLOOKUP($B7,'Pwood & PB List'!$B$4:$V$158,17,FALSE)))) -> 908.845 | L7: =CONCATENATE("GLG-",B7) -> GLG-B18 | M7: =IF('Summary Sheet'!$M$4="Plywood",VLOOKUP($B7,'Pwood & PB List'!$B$4:$V$158,12,FALSE),IF('Summary Sheet'!$M$4="PB w/ Wood Drawers",VLOOKUP($B7,'Pwood & PB List'!$B$4:$V$158,16,FALSE),IF('Summary Sheet'!$M$4="PB w/ PB Drawers",VLOOKUP($B7,'Pwood & PB List'!$B$4:$V$158,20,FALSE)))) -> 819.605 | N7: =CONCATENATE("NAO-",B7) -> NAO-B18 | O7: =IF('Summary Sheet'!$M$4="Plywood",VLOOKUP($B7,'Pwood & PB List'!$B$4:$V$158,12,FALSE),IF('Summary Sheet'!$M$4="PB w/ Wood Drawers",VLOOKUP($B7,'Pwood & PB List'!$B$4:$V$158,16,FALSE),IF('Summary Sheet'!$M$4="PB w/ PB Drawers",VLOOKUP($B7,'Pwood & PB List'!$B$4:$V$158,20,FALSE)))) -> 819.605 | P7: =CONCATENATE("WHO-",B7) -> WHO-B18 | Q7: =IF('Summary Sheet'!$M$4="Plywood",VLOOKUP($B7,'Pwood & PB List'!$B$4:$V$158,9,FALSE),IF('Summary Sheet'!$M$4="PB w/ Wood Drawers",VLOOKUP($B7,'Pwood & PB List'!$B$4:$V$158,13,FALSE),IF('Summary Sheet'!$M$4="PB w/ PB Drawers",VLOOKUP($B7,'Pwood & PB List'!$B$4:$V$158,17,FALSE)))) -> 908.845 | R7: =CONCATENATE("MAW-",B7) -> MAW-B18 | S7: =IF('Summary Sheet'!$M$4="Plywood",VLOOKUP($B7,'Pwood & PB List'!$B$4:$V$158,9,FALSE),IF('Summary Sheet'!$M$4="PB w/ Wood Drawers",VLOOKUP($B7,'Pwood & PB List'!$B$4:$V$158,13,FALSE),IF('Summary Sheet'!$M$4="PB w/ PB Drawers",VLOOKUP($B7,'Pwood & PB List'!$B$4:$V$158,17,FALSE)))) -> 908.845 | T7: =CONCATENATE("MAG-",B7) -> MAG-B18 | U7: =IF('Summary Sheet'!$M$4="Plywood",VLOOKUP($B7,'Pwood & PB List'!$B$4:$V$158,9,FALSE),IF('Summary Sheet'!$M$4="PB w/ Wood Drawers",VLOOKUP($B7,'Pwood & PB List'!$B$4:$V$158,13,FALSE),IF('Summary Sheet'!$M$4="PB w/ PB Drawers",VLOOKUP($B7,'Pwood & PB List'!$B$4:$V$158,17,FALSE)))) -> 908.845 | V7: =CONCATENATE("MAB-",B7) -> MAB-B18 | W7: =IF('Summary Sheet'!$M$4="Plywood",VLOOKUP($B7,'Pwood & PB List'!$B$4:$V$158,9,FALSE),IF('Summary Sheet'!$M$4="PB w/ Wood Drawers",VLOOKUP($B7,'Pwood & PB List'!$B$4:$V$158,13,FALSE),IF('Summary Sheet'!$M$4="PB w/ PB Drawers",VLOOKUP($B7,'Pwood & PB List'!$B$4:$V$158,17,FALSE)))) -> 908.845 | X7: =CONCATENATE("GLB-",B7) -> GLB-B18 | Y7: 2
A8: 18" Base Trash Cabinet: 1 Door & 1 Drawer With Trash Can Pullout | B8: BTC18 | C8: =IF('Summary Sheet'!$M$4="Plywood",VLOOKUP($B8,'Pwood & PB List'!$B$4:$V$158,9,FALSE),IF('Summary Sheet'!$M$4="PB w/ Wood Drawers",VLOOKUP($B8,'Pwood & PB List'!$B$4:$V$158,13,FALSE),IF('Summary Sheet'!$M$4="PB w/ PB Drawers",VLOOKUP($B8,'Pwood & PB List'!$B$4:$V$158,17,FALSE)))) -> 1358.495 | D8: =CONCATENATE("GLW-",B8) -> GLW-BTC18 | E8: =IF('Summary Sheet'!$M$4="Plywood",VLOOKUP($B8,'Pwood & PB List'!$B$4:$V$158,10,FALSE),IF('Summary Sheet'!$M$4="PB w/ Wood Drawers",VLOOKUP($B8,'Pwood & PB List'!$B$4:$V$158,14,FALSE),IF('Summary Sheet'!$M$4="PB w/ PB Drawers",VLOOKUP($B8,'Pwood & PB List'!$B$4:$V$158,18,FALSE)))) -> 1331.24 | F8: =CONCATENATE("SLO-",B8) -> SLO-BTC18 | G8: =IF('Summary Sheet'!$M$4="Plywood",VLOOKUP($B8,'Pwood & PB List'!$B$4:$V$158,11,FALSE),IF('Summary Sheet'!$M$4="PB w/ Wood Drawers",VLOOKUP($B8,'Pwood & PB List'!$B$4:$V$158,15,FALSE),IF('Summary Sheet'!$M$4="PB w/ PB Drawers",VLOOKUP($B8,'Pwood & PB List'!$B$4:$V$158,19,FALSE)))) -> 1302.03 | H8: =CONCATENATE("BLW-",B8) -> BLW-BTC18 | I8: =IF('Summary Sheet'!$M$4="Plywood",VLOOKUP($B8,'Pwood & PB List'!$B$4:$V$158,10,FALSE),IF('Summary Sheet'!$M$4="PB w/ Wood Drawers",VLOOKUP($B8,'Pwood & PB List'!$B$4:$V$158,14,FALSE),IF('Summary Sheet'!$M$4="PB w/ PB Drawers",VLOOKUP($B8,'Pwood & PB List'!$B$4:$V$158,18,FALSE)))) -> 1331.24 | J8: =CONCATENATE("WEO-",B8) -> WEO-BTC18 | K8: =IF('Summary Sheet'!$M$4="Plywood",VLOOKUP($B8,'Pwood & PB List'!$B$4:$V$158,9,FALSE),IF('Summary Sheet'!$M$4="PB w/ Wood Drawers",VLOOKUP($B8,'Pwood & PB List'!$B$4:$V$158,13,FALSE),IF('Summary Sheet'!$M$4="PB w/ PB Drawers",VLOOKUP($B8,'Pwood & PB List'!$B$4:$V$158,17,FALSE)))) -> 1358.495 | L8: =CONCATENATE("GLG-",B8) -> GLG-BTC18 | M8: =IF('Summary Sheet'!$M$4="Plywood",VLOOKUP($B8,'Pwood & PB List'!$B$4:$V$158,12,FALSE),IF('Summary Sheet'!$M$4="PB w/ Wood Drawers",VLOOKUP($B8,'Pwood & PB List'!$B$4:$V$158,16,FALSE),IF('Summary Sheet'!$M$4="PB w/ PB Drawers",VLOOKUP($B8,'Pwood & PB List'!$B$4:$V$158,20,FALSE)))) -> 1269.255 | N8: =CONCATENATE("NAO-",B8) -> NAO-BTC18 | O8: =IF('Summary Sheet'!$M$4="Plywood",VLOOKUP($B8,'Pwood & PB List'!$B$4:$V$158,12,FALSE),IF('Summary Sheet'!$M$4="PB w/ Wood Drawers",VLOOKUP($B8,'Pwood & PB List'!$B$4:$V$158,16,FALSE),IF('Summary Sheet'!$M$4="PB w/ PB Drawers",VLOOKUP($B8,'Pwood & PB List'!$B$4:$V$158,20,FALSE)))) -> 1269.255 | P8: =CONCATENATE("WHO-",B8) -> WHO-BTC18 | Q8: =IF('Summary Sheet'!$M$4="Plywood",VLOOKUP($B8,'Pwood & PB List'!$B$4:$V$158,9,FALSE),IF('Summary Sheet'!$M$4="PB w/ Wood Drawers",VLOOKUP($B8,'Pwood & PB List'!$B$4:$V$158,13,FALSE),IF('Summary Sheet'!$M$4="PB w/ PB Drawers",VLOOKUP($B8,'Pwood & PB List'!$B$4:$V$158,17,FALSE)))) -> 1358.495 | R8: =CONCATENATE("MAW-",B8) -> MAW-BTC18 | S8: =IF('Summary Sheet'!$M$4="Plywood",VLOOKUP($B8,'Pwood & PB List'!$B$4:$V$158,9,FALSE),IF('Summary Sheet'!$M$4="PB w/ Wood Drawers",VLOOKUP($B8,'Pwood & PB List'!$B$4:$V$158,13,FALSE),IF('Summary Sheet'!$M$4="PB w/ PB Drawers",VLOOKUP($B8,'Pwood & PB List'!$B$4:$V$158,17,FALSE)))) -> 1358.495 | T8: =CONCATENATE("MAG-",B8) -> MAG-BTC18 | U8: =IF('Summary Sheet'!$M$4="Plywood",VLOOKUP($B8,'Pwood & PB List'!$B$4:$V$158,9,FALSE),IF('Summary Sheet'!$M$4="PB w/ Wood Drawers",VLOOKUP($B8,'Pwood & PB List'!$B$4:$V$158,13,FALSE),IF('Summary Sheet'!$M$4="PB w/ PB Drawers",VLOOKUP($B8,'Pwood & PB List'!$B$4:$V$158,17,FALSE)))) -> 1358.495 | V8: =CONCATENATE("MAB-",B8) -> MAB-BTC18 | W8: =IF('Summary Sheet'!$M$4="Plywood",VLOOKUP($B8,'Pwood & PB List'!$B$4:$V$158,9,FALSE),IF('Summary Sheet'!$M$4="PB w/ Wood Drawers",VLOOKUP($B8,'Pwood & PB List'!$B$4:$V$158,13,FALSE),IF('Summary Sheet'!$M$4="PB w/ PB Drawers",VLOOKUP($B8,'Pwood & PB List'!$B$4:$V$158,17,FALSE)))) -> 1358.495 | X8: =CONCATENATE("GLB-",B8) -> GLB-BTC18 | Y8: 2
A9: 21" Base Cabinet: 1 Door & 1 Drawer | B9: B21 | C9: =IF('Summary Sheet'!$M$4="Plywood",VLOOKUP($B9,'Pwood & PB List'!$B$4:$V$158,9,FALSE),IF('Summary Sheet'!$M$4="PB w/ Wood Drawers",VLOOKUP($B9,'Pwood & PB List'!$B$4:$V$158,13,FALSE),IF('Summary Sheet'!$M$4="PB w/ PB Drawers",VLOOKUP($B9,'Pwood & PB List'!$B$4:$V$158,17,FALSE)))) -> 989.575 | D9: =CONCATENATE("GLW-",B9) -> GLW-B21 | E9: =IF('Summary Sheet'!$M$4="Plywood",VLOOKUP($B9,'Pwood & PB List'!$B$4:$V$158,10,FALSE),IF('Summary Sheet'!$M$4="PB w/ Wood Drawers",VLOOKUP($B9,'Pwood & PB List'!$B$4:$V$158,14,FALSE),IF('Summary Sheet'!$M$4="PB w/ PB Drawers",VLOOKUP($B9,'Pwood & PB List'!$B$4:$V$158,18,FALSE)))) -> 957.72 | F9: =CONCATENATE("SLO-",B9) -> SLO-B21 | G9: =IF('Summary Sheet'!$M$4="Plywood",VLOOKUP($B9,'Pwood & PB List'!$B$4:$V$158,11,FALSE),IF('Summary Sheet'!$M$4="PB w/ Wood Drawers",VLOOKUP($B9,'Pwood & PB List'!$B$4:$V$158,15,FALSE),IF('Summary Sheet'!$M$4="PB w/ PB Drawers",VLOOKUP($B9,'Pwood & PB List'!$B$4:$V$158,19,FALSE)))) -> 923.565 | H9: =CONCATENATE("BLW-",B9) -> BLW-B21 | I9: =IF('Summary Sheet'!$M$4="Plywood",VLOOKUP($B9,'Pwood & PB List'!$B$4:$V$158,10,FALSE),IF('Summary Sheet'!$M$4="PB w/ Wood Drawers",VLOOKUP($B9,'Pwood & PB List'!$B$4:$V$158,14,FALSE),IF('Summary Sheet'!$M$4="PB w/ PB Drawers",VLOOKUP($B9,'Pwood & PB List'!$B$4:$V$158,18,FALSE)))) -> 957.72 | J9: =CONCATENATE("WEO-",B9) -> WEO-B21 | K9: =IF('Summary Sheet'!$M$4="Plywood",VLOOKUP($B9,'Pwood & PB List'!$B$4:$V$158,9,FALSE),IF('Summary Sheet'!$M$4="PB w/ Wood Drawers",VLOOKUP($B9,'Pwood & PB List'!$B$4:$V$158,13,FALSE),IF('Summary Sheet'!$M$4="PB w/ PB Drawers",VLOOKUP($B9,'Pwood & PB List'!$B$4:$V$158,17,FALSE)))) -> 989.575 | L9: =CONCATENATE("GLG-",B9) -> GLG-B21 | M9: =IF('Summary Sheet'!$M$4="Plywood",VLOOKUP($B9,'Pwood & PB List'!$B$4:$V$158,12,FALSE),IF('Summary Sheet'!$M$4="PB w/ Wood Drawers",VLOOKUP($B9,'Pwood & PB List'!$B$4:$V$158,16,FALSE),IF('Summary Sheet'!$M$4="PB w/ PB Drawers",VLOOKUP($B9,'Pwood & PB List'!$B$4:$V$158,20,FALSE)))) -> 885.27 | N9: =CONCATENATE("NAO-",B9) -> NAO-B21 | O9: =IF('Summary Sheet'!$M$4="Plywood",VLOOKUP($B9,'Pwood & PB List'!$B$4:$V$158,12,FALSE),IF('Summary Sheet'!$M$4="PB w/ Wood Drawers",VLOOKUP($B9,'Pwood & PB List'!$B$4:$V$158,16,FALSE),IF('Summary Sheet'!$M$4="PB w/ PB Drawers",VLOOKUP($B9,'Pwood & PB List'!$B$4:$V$158,20,FALSE)))) -> 885.27 | P9: =CONCATENATE("WHO-",B9) -> WHO-B21 | Q9: =IF('Summary Sheet'!$M$4="Plywood",VLOOKUP($B9,'Pwood & PB List'!$B$4:$V$158,9,FALSE),IF('Summary Sheet'!$M$4="PB w/ Wood Drawers",VLOOKUP($B9,'Pwood & PB List'!$B$4:$V$158,13,FALSE),IF('Summary Sheet'!$M$4="PB w/ PB Drawers",VLOOKUP($B9,'Pwood & PB List'!$B$4:$V$158,17,FALSE)))) -> 989.575 | R9: =CONCATENATE("MAW-",B9) -> MAW-B21 | S9: =IF('Summary Sheet'!$M$4="Plywood",VLOOKUP($B9,'Pwood & PB List'!$B$4:$V$158,9,FALSE),IF('Summary Sheet'!$M$4="PB w/ Wood Drawers",VLOOKUP($B9,'Pwood & PB List'!$B$4:$V$158,13,FALSE),IF('Summary Sheet'!$M$4="PB w/ PB Drawers",VLOOKUP($B9,'Pwood & PB List'!$B$4:$V$158,17,FALSE)))) -> 989.575 | T9: =CONCATENATE("MAG-",B9) -> MAG-B21 | U9: =IF('Summary Sheet'!$M$4="Plywood",VLOOKUP($B9,'Pwood & PB List'!$B$4:$V$158,9,FALSE),IF('Summary Sheet'!$M$4="PB w/ Wood Drawers",VLOOKUP($B9,'Pwood & PB List'!$B$4:$V$158,13,FALSE),IF('Summary Sheet'!$M$4="PB w/ PB Drawers",VLOOKUP($B9,'Pwood & PB List'!$B$4:$V$158,17,FALSE)))) -> 989.575 | V9: =CONCATENATE("MAB-",B9) -> MAB-B21 | W9: =IF('Summary Sheet'!$M$4="Plywood",VLOOKUP($B9,'Pwood & PB List'!$B$4:$V$158,9,FALSE),IF('Summary Sheet'!$M$4="PB w/ Wood Drawers",VLOOKUP($B9,'Pwood & PB List'!$B$4:$V$158,13,FALSE),IF('Summary Sheet'!$M$4="PB w/ PB Drawers",VLOOKUP($B9,'Pwood & PB List'!$B$4:$V$158,17,FALSE)))) -> 989.575 | X9: =CONCATENATE("GLB-",B9) -> GLB-B21 | Y9: 2
A10: 24" Base Cabinet: 2 Doors & 1 Drawer | B10: B24 | C10: =IF('Summary Sheet'!$M$4="Plywood",VLOOKUP($B10,'Pwood & PB List'!$B$4:$V$158,9,FALSE),IF('Summary Sheet'!$M$4="PB w/ Wood Drawers",VLOOKUP($B10,'Pwood & PB List'!$B$4:$V$158,13,FALSE),IF('Summary Sheet'!$M$4="PB w/ PB Drawers",VLOOKUP($B10,'Pwood & PB List'!$B$4:$V$158,17,FALSE)))) -> 1087.555 | D10: =CONCATENATE("GLW-",B10) -> GLW-B24 | E10: =IF('Summary Sheet'!$M$4="Plywood",VLOOKUP($B10,'Pwood & PB List'!$B$4:$V$158,10,FALSE),IF('Summary Sheet'!$M$4="PB w/ Wood Drawers",VLOOKUP($B10,'Pwood & PB List'!$B$4:$V$158,14,FALSE),IF('Summary Sheet'!$M$4="PB w/ PB Drawers",VLOOKUP($B10,'Pwood & PB List'!$B$4:$V$158,18,FALSE)))) -> 1051.1 | F10: =CONCATENATE("SLO-",B10) -> SLO-B24 | G10: =IF('Summary Sheet'!$M$4="Plywood",VLOOKUP($B10,'Pwood & PB List'!$B$4:$V$158,11,FALSE),IF('Summary Sheet'!$M$4="PB w/ Wood Drawers",VLOOKUP($B10,'Pwood & PB List'!$B$4:$V$158,15,FALSE),IF('Summary Sheet'!$M$4="PB w/ PB Drawers",VLOOKUP($B10,'Pwood & PB List'!$B$4:$V$158,19,FALSE)))) -> 1012.345 | H10: =CONCATENATE("BLW-",B10) -> BLW-B24 | I10: =IF('Summary Sheet'!$M$4="Plywood",VLOOKUP($B10,'Pwood & PB List'!$B$4:$V$158,10,FALSE),IF('Summary Sheet'!$M$4="PB w/ Wood Drawers",VLOOKUP($B10,'Pwood & PB List'!$B$4:$V$158,14,FALSE),IF('Summary Sheet'!$M$4="PB w/ PB Drawers",VLOOKUP($B10,'Pwood & PB List'!$B$4:$V$158,18,FALSE)))) -> 1051.1 | J10: =CONCATENATE("WEO-",B10) -> WEO-B24 | K10: =IF('Summary Sheet'!$M$4="Plywood",VLOOKUP($B10,'Pwood & PB List'!$B$4:$V$158,9,FALSE),IF('Summary Sheet'!$M$4="PB w/ Wood Drawers",VLOOKUP($B10,'Pwood & PB List'!$B$4:$V$158,13,FALSE),IF('Summary Sheet'!$M$4="PB w/ PB Drawers",VLOOKUP($B10,'Pwood & PB List'!$B$4:$V$158,17,FALSE)))) -> 1087.555 | L10: =CONCATENATE("GLG-",B10) -> GLG-B24 | M10: =IF('Summary Sheet'!$M$4="Plywood",VLOOKUP($B10,'Pwood & PB List'!$B$4:$V$158,12,FALSE),IF('Summary Sheet'!$M$4="PB w/ Wood Drawers",VLOOKUP($B10,'Pwood & PB List'!$B$4:$V$158,16,FALSE),IF('Summary Sheet'!$M$4="PB w/ PB Drawers",VLOOKUP($B10,'Pwood & PB List'!$B$4:$V$158,20,FALSE)))) -> 968.645 | N10: =CONCATENATE("NAO-",B10) -> NAO-B24 | O10: =IF('Summary Sheet'!$M$4="Plywood",VLOOKUP($B10,'Pwood & PB List'!$B$4:$V$158,12,FALSE),IF('Summary Sheet'!$M$4="PB w/ Wood Drawers",VLOOKUP($B10,'Pwood & PB List'!$B$4:$V$158,16,FALSE),IF('Summary Sheet'!$M$4="PB w/ PB Drawers",VLOOKUP($B10,'Pwood & PB List'!$B$4:$V$158,20,FALSE)))) -> 968.645 | P10: =CONCATENATE("WHO-",B10) -> WHO-B24 | Q10: =IF('Summary Sheet'!$M$4="Plywood",VLOOKUP($B10,'Pwood & PB List'!$B$4:$V$158,9,FALSE),IF('Summary Sheet'!$M$4="PB w/ Wood Drawers",VLOOKUP($B10,'Pwood & PB List'!$B$4:$V$158,13,FALSE),IF('Summary Sheet'!$M$4="PB w/ PB Drawers",VLOOKUP($B10,'Pwood & PB List'!$B$4:$V$158,17,FALSE)))) -> 1087.555 | R10: =CONCATENATE("MAW-",B10) -> MAW-B24 | S10: =IF('Summary Sheet'!$M$4="Plywood",VLOOKUP($B10,'Pwood & PB List'!$B$4:$V$158,9,FALSE),IF('Summary Sheet'!$M$4="PB w/ Wood Drawers",VLOOKUP($B10,'Pwood & PB List'!$B$4:$V$158,13,FALSE),IF('Summary Sheet'!$M$4="PB w/ PB Drawers",VLOOKUP($B10,'Pwood & PB List'!$B$4:$V$158,17,FALSE)))) -> 1087.555 | T10: =CONCATENATE("MAG-",B10) -> MAG-B24 | U10: =IF('Summary Sheet'!$M$4="Plywood",VLOOKUP($B10,'Pwood & PB List'!$B$4:$V$158,9,FALSE),IF('Summary Sheet'!$M$4="PB w/ Wood Drawers",VLOOKUP($B10,'Pwood & PB List'!$B$4:$V$158,13,FALSE),IF('Summary Sheet'!$M$4="PB w/ PB Drawers",VLOOKUP($B10,'Pwood & PB List'!$B$4:$V$158,17,FALSE)))) -> 1087.555 | V10: =CONCATENATE("MAB-",B10) -> MAB-B24 | W10: =IF('Summary Sheet'!$M$4="Plywood",VLOOKUP($B10,'Pwood & PB List'!$B$4:$V$158,9,FALSE),IF('Summary Sheet'!$M$4="PB w/ Wood Drawers",VLOOKUP($B10,'Pwood & PB List'!$B$4:$V$158,13,FALSE),IF('Summary Sheet'!$M$4="PB w/ PB Drawers",VLOOKUP($B10,'Pwood & PB List'!$B$4:$V$158,17,FALSE)))) -> 1087.555 | X10: =CONCATENATE("GLB-",B10) -> GLB-B24 | Y10: 3
A11: 27" Base Cabinet: 2 Doors & 1 Drawer | B11: B27 | C11: =IF('Summary Sheet'!$M$4="Plywood",VLOOKUP($B11,'Pwood & PB List'!$B$4:$V$158,9,FALSE),IF('Summary Sheet'!$M$4="PB w/ Wood Drawers",VLOOKUP($B11,'Pwood & PB List'!$B$4:$V$158,13,FALSE),IF('Summary Sheet'!$M$4="PB w/ PB Drawers",VLOOKUP($B11,'Pwood & PB List'!$B$4:$V$158,17,FALSE)))) -> 1168.17 | D11: =CONCATENATE("GLW-",B11) -> GLW-B27 | E11: =IF('Summary Sheet'!$M$4="Plywood",VLOOKUP($B11,'Pwood & PB List'!$B$4:$V$158,10,FALSE),IF('Summary Sheet'!$M$4="PB w/ Wood Drawers",VLOOKUP($B11,'Pwood & PB List'!$B$4:$V$158,14,FALSE),IF('Summary Sheet'!$M$4="PB w/ PB Drawers",VLOOKUP($B11,'Pwood & PB List'!$B$4:$V$158,18,FALSE)))) -> 1127.115 | F11: =CONCATENATE("SLO-",B11) -> SLO-B27 | G11: =IF('Summary Sheet'!$M$4="Plywood",VLOOKUP($B11,'Pwood & PB List'!$B$4:$V$158,11,FALSE),IF('Summary Sheet'!$M$4="PB w/ Wood Drawers",VLOOKUP($B11,'Pwood & PB List'!$B$4:$V$158,15,FALSE),IF('Summary Sheet'!$M$4="PB w/ PB Drawers",VLOOKUP($B11,'Pwood & PB List'!$B$4:$V$158,19,FALSE)))) -> 1083.415 | H11: =CONCATENATE("BLW-",B11) -> BLW-B27 | I11: =IF('Summary Sheet'!$M$4="Plywood",VLOOKUP($B11,'Pwood & PB List'!$B$4:$V$158,10,FALSE),IF('Summary Sheet'!$M$4="PB w/ Wood Drawers",VLOOKUP($B11,'Pwood & PB List'!$B$4:$V$158,14,FALSE),IF('Summary Sheet'!$M$4="PB w/ PB Drawers",VLOOKUP($B11,'Pwood & PB List'!$B$4:$V$158,18,FALSE)))) -> 1127.115 | J11: =CONCATENATE("WEO-",B11) -> WEO-B27 | K11: =IF('Summary Sheet'!$M$4="Plywood",VLOOKUP($B11,'Pwood & PB List'!$B$4:$V$158,9,FALSE),IF('Summary Sheet'!$M$4="PB w/ Wood Drawers",VLOOKUP($B11,'Pwood & PB List'!$B$4:$V$158,13,FALSE),IF('Summary Sheet'!$M$4="PB w/ PB Drawers",VLOOKUP($B11,'Pwood & PB List'!$B$4:$V$158,17,FALSE)))) -> 1168.17 | L11: =CONCATENATE("GLG-",B11) -> GLG-B27 | M11: =IF('Summary Sheet'!$M$4="Plywood",VLOOKUP($B11,'Pwood & PB List'!$B$4:$V$158,12,FALSE),IF('Summary Sheet'!$M$4="PB w/ Wood Drawers",VLOOKUP($B11,'Pwood & PB List'!$B$4:$V$158,16,FALSE),IF('Summary Sheet'!$M$4="PB w/ PB Drawers",VLOOKUP($B11,'Pwood & PB List'!$B$4:$V$158,20,FALSE)))) -> 1034.31 | N11: =CONCATENATE("NAO-",B11) -> NAO-B27 | O11: =IF('Summary Sheet'!$M$4="Plywood",VLOOKUP($B11,'Pwood & PB List'!$B$4:$V$158,12,FALSE),IF('Summary Sheet'!$M$4="PB w/ Wood Drawers",VLOOKUP($B11,'Pwood & PB List'!$B$4:$V$158,16,FALSE),IF('Summary Sheet'!$M$4="PB w/ PB Drawers",VLOOKUP($B11,'Pwood & PB List'!$B$4:$V$158,20,FALSE)))) -> 1034.31 | P11: =CONCATENATE("WHO-",B11) -> WHO-B27 | Q11: =IF('Summary Sheet'!$M$4="Plywood",VLOOKUP($B11,'Pwood & PB List'!$B$4:$V$158,9,FALSE),IF('Summary Sheet'!$M$4="PB w/ Wood Drawers",VLOOKUP($B11,'Pwood & PB List'!$B$4:$V$158,13,FALSE),IF('Summary Sheet'!$M$4="PB w/ PB Drawers",VLOOKUP($B11,'Pwood & PB List'!$B$4:$V$158,17,FALSE)))) -> 1168.17 | R11: =CONCATENATE("MAW-",B11) -> MAW-B27 | S11: =IF('Summary Sheet'!$M$4="Plywood",VLOOKUP($B11,'Pwood & PB List'!$B$4:$V$158,9,FALSE),IF('Summary Sheet'!$M$4="PB w/ Wood Drawers",VLOOKUP($B11,'Pwood & PB List'!$B$4:$V$158,13,FALSE),IF('Summary Sheet'!$M$4="PB w/ PB Drawers",VLOOKUP($B11,'Pwood & PB List'!$B$4:$V$158,17,FALSE)))) -> 1168.17 | T11: =CONCATENATE("MAG-",B11) -> MAG-B27 | U11: =IF('Summary Sheet'!$M$4="Plywood",VLOOKUP($B11,'Pwood & PB List'!$B$4:$V$158,9,FALSE),IF('Summary Sheet'!$M$4="PB w/ Wood Drawers",VLOOKUP($B11,'Pwood & PB List'!$B$4:$V$158,13,FALSE),IF('Summary Sheet'!$M$4="PB w/ PB Drawers",VLOOKUP($B11,'Pwood & PB List'!$B$4:$V$158,17,FALSE)))) -> 1168.17 | V11: =CONCATENATE("MAB-",B11) -> MAB-B27 | W11: =IF('Summary Sheet'!$M$4="Plywood",VLOOKUP($B11,'Pwood & PB List'!$B$4:$V$158,9,FALSE),IF('Summary Sheet'!$M$4="PB w/ Wood Drawers",VLOOKUP($B11,'Pwood & PB List'!$B$4:$V$158,13,FALSE),IF('Summary Sheet'!$M$4="PB w/ PB Drawers",VLOOKUP($B11,'Pwood & PB List'!$B$4:$V$158,17,FALSE)))) -> 1168.17 | X11: =CONCATENATE("GLB-",B11) -> GLB-B27 | Y11: 3
A12: 30" Base Cabinet: 2 Doors & 1 Drawer | B12: B30 | C12: =IF('Summary Sheet'!$M$4="Plywood",VLOOKUP($B12,'Pwood & PB List'!$B$4:$V$158,9,FALSE),IF('Summary Sheet'!$M$4="PB w/ Wood Drawers",VLOOKUP($B12,'Pwood & PB List'!$B$4:$V$158,13,FALSE),IF('Summary Sheet'!$M$4="PB w/ PB Drawers",VLOOKUP($B12,'Pwood & PB List'!$B$4:$V$158,17,FALSE)))) -> 1254.42 | D12: =CONCATENATE("GLW-",B12) -> GLW-B30 | E12: =IF('Summary Sheet'!$M$4="Plywood",VLOOKUP($B12,'Pwood & PB List'!$B$4:$V$158,10,FALSE),IF('Summary Sheet'!$M$4="PB w/ Wood Drawers",VLOOKUP($B12,'Pwood & PB List'!$B$4:$V$158,14,FALSE),IF('Summary Sheet'!$M$4="PB w/ PB Drawers",VLOOKUP($B12,'Pwood & PB List'!$B$4:$V$158,18,FALSE)))) -> 1208.88 | F12: =CONCATENATE("SLO-",B12) -> SLO-B30 | G12: =IF('Summary Sheet'!$M$4="Plywood",VLOOKUP($B12,'Pwood & PB List'!$B$4:$V$158,11,FALSE),IF('Summary Sheet'!$M$4="PB w/ Wood Drawers",VLOOKUP($B12,'Pwood & PB List'!$B$4:$V$158,15,FALSE),IF('Summary Sheet'!$M$4="PB w/ PB Drawers",VLOOKUP($B12,'Pwood & PB List'!$B$4:$V$158,19,FALSE)))) -> 1160.35 | H12: =CONCATENATE("BLW-",B12) -> BLW-B30 | I12: =IF('Summary Sheet'!$M$4="Plywood",VLOOKUP($B12,'Pwood & PB List'!$B$4:$V$158,10,FALSE),IF('Summary Sheet'!$M$4="PB w/ Wood Drawers",VLOOKUP($B12,'Pwood & PB List'!$B$4:$V$158,14,FALSE),IF('Summary Sheet'!$M$4="PB w/ PB Drawers",VLOOKUP($B12,'Pwood & PB List'!$B$4:$V$158,18,FALSE)))) -> 1208.88 | J12: =CONCATENATE("WEO-",B12) -> WEO-B30 | K12: =IF('Summary Sheet'!$M$4="Plywood",VLOOKUP($B12,'Pwood & PB List'!$B$4:$V$158,9,FALSE),IF('Summary Sheet'!$M$4="PB w/ Wood Drawers",VLOOKUP($B12,'Pwood & PB List'!$B$4:$V$158,13,FALSE),IF('Summary Sheet'!$M$4="PB w/ PB Drawers",VLOOKUP($B12,'Pwood & PB List'!$B$4:$V$158,17,FALSE)))) -> 1254.42 | L12: =CONCATENATE("GLG-",B12) -> GLG-B30 | M12: =IF('Summary Sheet'!$M$4="Plywood",VLOOKUP($B12,'Pwood & PB List'!$B$4:$V$158,12,FALSE),IF('Summary Sheet'!$M$4="PB w/ Wood Drawers",VLOOKUP($B12,'Pwood & PB List'!$B$4:$V$158,16,FALSE),IF('Summary Sheet'!$M$4="PB w/ PB Drawers",VLOOKUP($B12,'Pwood & PB List'!$B$4:$V$158,20,FALSE)))) -> 1105.61 | N12: =CONCATENATE("NAO-",B12) -> NAO-B30 | O12: =IF('Summary Sheet'!$M$4="Plywood",VLOOKUP($B12,'Pwood & PB List'!$B$4:$V$158,12,FALSE),IF('Summary Sheet'!$M$4="PB w/ Wood Drawers",VLOOKUP($B12,'Pwood & PB List'!$B$4:$V$158,16,FALSE),IF('Summary Sheet'!$M$4="PB w/ PB Drawers",VLOOKUP($B12,'Pwood & PB List'!$B$4:$V$158,20,FALSE)))) -> 1105.61 | P12: =CONCATENATE("WHO-",B12) -> WHO-B30 | Q12: =IF('Summary Sheet'!$M$4="Plywood",VLOOKUP($B12,'Pwood & PB List'!$B$4:$V$158,9,FALSE),IF('Summary Sheet'!$M$4="PB w/ Wood Drawers",VLOOKUP($B12,'Pwood & PB List'!$B$4:$V$158,13,FALSE),IF('Summary Sheet'!$M$4="PB w/ PB Drawers",VLOOKUP($B12,'Pwood & PB List'!$B$4:$V$158,17,FALSE)))) -> 1254.42 | R12: =CONCATENATE("MAW-",B12) -> MAW-B30 | S12: =IF('Summary Sheet'!$M$4="Plywood",VLOOKUP($B12,'Pwood & PB List'!$B$4:$V$158,9,FALSE),IF('Summary Sheet'!$M$4="PB w/ Wood Drawers",VLOOKUP($B12,'Pwood & PB List'!$B$4:$V$158,13,FALSE),IF('Summary Sheet'!$M$4="PB w/ PB Drawers",VLOOKUP($B12,'Pwood & PB List'!$B$4:$V$158,17,FALSE)))) -> 1254.42 | T12: =CONCATENATE("MAG-",B12) -> MAG-B30 | U12: =IF('Summary Sheet'!$M$4="Plywood",VLOOKUP($B12,'Pwood & PB List'!$B$4:$V$158,9,FALSE),IF('Summary Sheet'!$M$4="PB w/ Wood Drawers",VLOOKUP($B12,'Pwood & PB List'!$B$4:$V$158,13,FALSE),IF('Summary Sheet'!$M$4="PB w/ PB Drawers",VLOOKUP($B12,'Pwood & PB List'!$B$4:$V$158,17,FALSE)))) -> 1254.42 | V12: =CONCATENATE("MAB-",B12) -> MAB-B30 | W12: =IF('Summary Sheet'!$M$4="Plywood",VLOOKUP($B12,'Pwood & PB List'!$B$4:$V$158,9,FALSE),IF('Summary Sheet'!$M$4="PB w/ Wood Drawers",VLOOKUP($B12,'Pwood & PB List'!$B$4:$V$158,13,FALSE),IF('Summary Sheet'!$M$4="PB w/ PB Drawers",VLOOKUP($B12,'Pwood & PB List'!$B$4:$V$158,17,FALSE)))) -> 1254.42 | X12: =CONCATENATE("GLB-",B12) -> GLB-B30 | Y12: 3
A13: 33" Base Cabinet: 2 Doors & 1 Drawer | B13: B33 | C13: =IF('Summary Sheet'!$M$4="Plywood",VLOOKUP($B13,'Pwood & PB List'!$B$4:$V$158,9,FALSE),IF('Summary Sheet'!$M$4="PB w/ Wood Drawers",VLOOKUP($B13,'Pwood & PB List'!$B$4:$V$158,13,FALSE),IF('Summary Sheet'!$M$4="PB w/ PB Drawers",VLOOKUP($B13,'Pwood & PB List'!$B$4:$V$158,17,FALSE)))) -> 1335.035 | D13: =CONCATENATE("GLW-",B13) -> GLW-B33 | E13: =IF('Summary Sheet'!$M$4="Plywood",VLOOKUP($B13,'Pwood & PB List'!$B$4:$V$158,10,FALSE),IF('Summary Sheet'!$M$4="PB w/ Wood Drawers",VLOOKUP($B13,'Pwood & PB List'!$B$4:$V$158,14,FALSE),IF('Summary Sheet'!$M$4="PB w/ PB Drawers",VLOOKUP($B13,'Pwood & PB List'!$B$4:$V$158,18,FALSE)))) -> 1284.895 | F13: =CONCATENATE("SLO-",B13) -> SLO-B33 | G13: =IF('Summary Sheet'!$M$4="Plywood",VLOOKUP($B13,'Pwood & PB List'!$B$4:$V$158,11,FALSE),IF('Summary Sheet'!$M$4="PB w/ Wood Drawers",VLOOKUP($B13,'Pwood & PB List'!$B$4:$V$158,15,FALSE),IF('Summary Sheet'!$M$4="PB w/ PB Drawers",VLOOKUP($B13,'Pwood & PB List'!$B$4:$V$158,19,FALSE)))) -> 1231.42 | H13: =CONCATENATE("BLW-",B13) -> BLW-B33 | I13: =IF('Summary Sheet'!$M$4="Plywood",VLOOKUP($B13,'Pwood & PB List'!$B$4:$V$158,10,FALSE),IF('Summary Sheet'!$M$4="PB w/ Wood Drawers",VLOOKUP($B13,'Pwood & PB List'!$B$4:$V$158,14,FALSE),IF('Summary Sheet'!$M$4="PB w/ PB Drawers",VLOOKUP($B13,'Pwood & PB List'!$B$4:$V$158,18,FALSE)))) -> 1284.895 | J13: =CONCATENATE("WEO-",B13) -> WEO-B33 | K13: =IF('Summary Sheet'!$M$4="Plywood",VLOOKUP($B13,'Pwood & PB List'!$B$4:$V$158,9,FALSE),IF('Summary Sheet'!$M$4="PB w/ Wood Drawers",VLOOKUP($B13,'Pwood & PB List'!$B$4:$V$158,13,FALSE),IF('Summary Sheet'!$M$4="PB w/ PB Drawers",VLOOKUP($B13,'Pwood & PB List'!$B$4:$V$158,17,FALSE)))) -> 1335.035 | L13: =CONCATENATE("GLG-",B13) -> GLG-B33 | M13: =IF('Summary Sheet'!$M$4="Plywood",VLOOKUP($B13,'Pwood & PB List'!$B$4:$V$158,12,FALSE),IF('Summary Sheet'!$M$4="PB w/ Wood Drawers",VLOOKUP($B13,'Pwood & PB List'!$B$4:$V$158,16,FALSE),IF('Summary Sheet'!$M$4="PB w/ PB Drawers",VLOOKUP($B13,'Pwood & PB List'!$B$4:$V$158,20,FALSE)))) -> 1171.275 | N13: =CONCATENATE("NAO-",B13) -> NAO-B33 | O13: =IF('Summary Sheet'!$M$4="Plywood",VLOOKUP($B13,'Pwood & PB List'!$B$4:$V$158,12,FALSE),IF('Summary Sheet'!$M$4="PB w/ Wood Drawers",VLOOKUP($B13,'Pwood & PB List'!$B$4:$V$158,16,FALSE),IF('Summary Sheet'!$M$4="PB w/ PB Drawers",VLOOKUP($B13,'Pwood & PB List'!$B$4:$V$158,20,FALSE)))) -> 1171.275 | P13: =CONCATENATE("WHO-",B13) -> WHO-B33 | Q13: =IF('Summary Sheet'!$M$4="Plywood",VLOOKUP($B13,'Pwood & PB List'!$B$4:$V$158,9,FALSE),IF('Summary Sheet'!$M$4="PB w/ Wood Drawers",VLOOKUP($B13,'Pwood & PB List'!$B$4:$V$158,13,FALSE),IF('Summary Sheet'!$M$4="PB w/ PB Drawers",VLOOKUP($B13,'Pwood & PB List'!$B$4:$V$158,17,FALSE)))) -> 1335.035 | R13: =CONCATENATE("MAW-",B13) -> MAW-B33 | S13: =IF('Summary Sheet'!$M$4="Plywood",VLOOKUP($B13,'Pwood & PB List'!$B$4:$V$158,9,FALSE),IF('Summary Sheet'!$M$4="PB w/ Wood Drawers",VLOOKUP($B13,'Pwood & PB List'!$B$4:$V$158,13,FALSE),IF('Summary Sheet'!$M$4="PB w/ PB Drawers",VLOOKUP($B13,'Pwood & PB List'!$B$4:$V$158,17,FALSE)))) -> 1335.035 | T13: =CONCATENATE("MAG-",B13) -> MAG-B33 | U13: =IF('Summary Sheet'!$M$4="Plywood",VLOOKUP($B13,'Pwood & PB List'!$B$4:$V$158,9,FALSE),IF('Summary Sheet'!$M$4="PB w/ Wood Drawers",VLOOKUP($B13,'Pwood & PB List'!$B$4:$V$158,13,FALSE),IF('Summary Sheet'!$M$4="PB w/ PB Drawers",VLOOKUP($B13,'Pwood & PB List'!$B$4:$V$158,17,FALSE)))) -> 1335.035 | V13: =CONCATENATE("MAB-",B13) -> MAB-B33 | W13: =IF('Summary Sheet'!$M$4="Plywood",VLOOKUP($B13,'Pwood & PB List'!$B$4:$V$158,9,FALSE),IF('Summary Sheet'!$M$4="PB w/ Wood Drawers",VLOOKUP($B13,'Pwood & PB List'!$B$4:$V$158,13,FALSE),IF('Summary Sheet'!$M$4="PB w/ PB Drawers",VLOOKUP($B13,'Pwood & PB List'!$B$4:$V$158,17,FALSE)))) -> 1335.035 | X13: =CONCATENATE("GLB-",B13) -> GLB-B33 | Y13: 3
A14: 36" Base Cabinet: 2 Doors & 1 Drawer | B14: B36 | C14: =IF('Summary Sheet'!$M$4="Plywood",VLOOKUP($B14,'Pwood & PB List'!$B$4:$V$158,9,FALSE),IF('Summary Sheet'!$M$4="PB w/ Wood Drawers",VLOOKUP($B14,'Pwood & PB List'!$B$4:$V$158,13,FALSE),IF('Summary Sheet'!$M$4="PB w/ PB Drawers",VLOOKUP($B14,'Pwood & PB List'!$B$4:$V$158,17,FALSE)))) -> 1415.65 | D14: =CONCATENATE("GLW-",B14) -> GLW-B36 | E14: =IF('Summary Sheet'!$M$4="Plywood",VLOOKUP($B14,'Pwood & PB List'!$B$4:$V$158,10,FALSE),IF('Summary Sheet'!$M$4="PB w/ Wood Drawers",VLOOKUP($B14,'Pwood & PB List'!$B$4:$V$158,14,FALSE),IF('Summary Sheet'!$M$4="PB w/ PB Drawers",VLOOKUP($B14,'Pwood & PB List'!$B$4:$V$158,18,FALSE)))) -> 1360.91 | F14: =CONCATENATE("SLO-",B14) -> SLO-B36 | G14: =IF('Summary Sheet'!$M$4="Plywood",VLOOKUP($B14,'Pwood & PB List'!$B$4:$V$158,11,FALSE),IF('Summary Sheet'!$M$4="PB w/ Wood Drawers",VLOOKUP($B14,'Pwood & PB List'!$B$4:$V$158,15,FALSE),IF('Summary Sheet'!$M$4="PB w/ PB Drawers",VLOOKUP($B14,'Pwood & PB List'!$B$4:$V$158,19,FALSE)))) -> 1302.49 | H14: =CONCATENATE("BLW-",B14) -> BLW-B36 | I14: =IF('Summary Sheet'!$M$4="Plywood",VLOOKUP($B14,'Pwood & PB List'!$B$4:$V$158,10,FALSE),IF('Summary Sheet'!$M$4="PB w/ Wood Drawers",VLOOKUP($B14,'Pwood & PB List'!$B$4:$V$158,14,FALSE),IF('Summary Sheet'!$M$4="PB w/ PB Drawers",VLOOKUP($B14,'Pwood & PB List'!$B$4:$V$158,18,FALSE)))) -> 1360.91 | J14: =CONCATENATE("WEO-",B14) -> WEO-B36 | K14: =IF('Summary Sheet'!$M$4="Plywood",VLOOKUP($B14,'Pwood & PB List'!$B$4:$V$158,9,FALSE),IF('Summary Sheet'!$M$4="PB w/ Wood Drawers",VLOOKUP($B14,'Pwood & PB List'!$B$4:$V$158,13,FALSE),IF('Summary Sheet'!$M$4="PB w/ PB Drawers",VLOOKUP($B14,'Pwood & PB List'!$B$4:$V$158,17,FALSE)))) -> 1415.65 | L14: =CONCATENATE("GLG-",B14) -> GLG-B36 | M14: =IF('Summary Sheet'!$M$4="Plywood",VLOOKUP($B14,'Pwood & PB List'!$B$4:$V$158,12,FALSE),IF('Summary Sheet'!$M$4="PB w/ Wood Drawers",VLOOKUP($B14,'Pwood & PB List'!$B$4:$V$158,16,FALSE),IF('Summary Sheet'!$M$4="PB w/ PB Drawers",VLOOKUP($B14,'Pwood & PB List'!$B$4:$V$158,20,FALSE)))) -> 1236.825 | N14: =CONCATENATE("NAO-",B14) -> NAO-B36 | O14: =IF('Summary Sheet'!$M$4="Plywood",VLOOKUP($B14,'Pwood & PB List'!$B$4:$V$158,12,FALSE),IF('Summary Sheet'!$M$4="PB w/ Wood Drawers",VLOOKUP($B14,'Pwood & PB List'!$B$4:$V$158,16,FALSE),IF('Summary Sheet'!$M$4="PB w/ PB Drawers",VLOOKUP($B14,'Pwood & PB List'!$B$4:$V$158,20,FALSE)))) -> 1236.825 | P14: =CONCATENATE("WHO-",B14) -> WHO-B36 | Q14: =IF('Summary Sheet'!$M$4="Plywood",VLOOKUP($B14,'Pwood & PB List'!$B$4:$V$158,9,FALSE),IF('Summary Sheet'!$M$4="PB w/ Wood Drawers",VLOOKUP($B14,'Pwood & PB List'!$B$4:$V$158,13,FALSE),IF('Summary Sheet'!$M$4="PB w/ PB Drawers",VLOOKUP($B14,'Pwood & PB List'!$B$4:$V$158,17,FALSE)))) -> 1415.65 | R14: =CONCATENATE("MAW-",B14) -> MAW-B36 | S14: =IF('Summary Sheet'!$M$4="Plywood",VLOOKUP($B14,'Pwood & PB List'!$B$4:$V$158,9,FALSE),IF('Summary Sheet'!$M$4="PB w/ Wood Drawers",VLOOKUP($B14,'Pwood & PB List'!$B$4:$V$158,13,FALSE),IF('Summary Sheet'!$M$4="PB w/ PB Drawers",VLOOKUP($B14,'Pwood & PB List'!$B$4:$V$158,17,FALSE)))) -> 1415.65 | T14: =CONCATENATE("MAG-",B14) -> MAG-B36 | U14: =IF('Summary Sheet'!$M$4="Plywood",VLOOKUP($B14,'Pwood & PB List'!$B$4:$V$158,9,FALSE),IF('Summary Sheet'!$M$4="PB w/ Wood Drawers",VLOOKUP($B14,'Pwood & PB List'!$B$4:$V$158,13,FALSE),IF('Summary Sheet'!$M$4="PB w/ PB Drawers",VLOOKUP($B14,'Pwood & PB List'!$B$4:$V$158,17,FALSE)))) -> 1415.65 | V14: =CONCATENATE("MAB-",B14) -> MAB-B36 | W14: =IF('Summary Sheet'!$M$4="Plywood",VLOOKUP($B14,'Pwood & PB List'!$B$4:$V$158,9,FALSE),IF('Summary Sheet'!$M$4="PB w/ Wood Drawers",VLOOKUP($B14,'Pwood & PB List'!$B$4:$V$158,13,FALSE),IF('Summary Sheet'!$M$4="PB w/ PB Drawers",VLOOKUP($B14,'Pwood & PB List'!$B$4:$V$158,17,FALSE)))) -> 1415.65 | X14: =CONCATENATE("GLB-",B14) -> GLB-B36 | Y14: 3
A15: Base Cabinets with Full-Height Door, 24" Depth
A16: 12" Base Cabinet: 1 Full-Height Door | B16: B09FD | C16: =IF('Summary Sheet'!$M$4="Plywood",VLOOKUP($B16,'Pwood & PB List'!$B$4:$V$158,9,FALSE),IF('Summary Sheet'!$M$4="PB w/ Wood Drawers",VLOOKUP($B16,'Pwood & PB List'!$B$4:$V$158,13,FALSE),IF('Summary Sheet'!$M$4="PB w/ PB Drawers",VLOOKUP($B16,'Pwood & PB List'!$B$4:$V$158,17,FALSE)))) -> 515.43 | D16: =CONCATENATE("GLW-",B16) -> GLW-B09FD | E16: =IF('Summary Sheet'!$M$4="Plywood",VLOOKUP($B16,'Pwood & PB List'!$B$4:$V$158,10,FALSE),IF('Summary Sheet'!$M$4="PB w/ Wood Drawers",VLOOKUP($B16,'Pwood & PB List'!$B$4:$V$158,14,FALSE),IF('Summary Sheet'!$M$4="PB w/ PB Drawers",VLOOKUP($B16,'Pwood & PB List'!$B$4:$V$158,18,FALSE)))) -> 501.86 | F16: =CONCATENATE("SLO-",B16) -> SLO-B09FD | G16: =IF('Summary Sheet'!$M$4="Plywood",VLOOKUP($B16,'Pwood & PB List'!$B$4:$V$158,11,FALSE),IF('Summary Sheet'!$M$4="PB w/ Wood Drawers",VLOOKUP($B16,'Pwood & PB List'!$B$4:$V$158,15,FALSE),IF('Summary Sheet'!$M$4="PB w/ PB Drawers",VLOOKUP($B16,'Pwood & PB List'!$B$4:$V$158,19,FALSE)))) -> 487.255 | H16: =CONCATENATE("BLW-",B16) -> BLW-B09FD | I16: =IF('Summary Sheet'!$M$4="Plywood",VLOOKUP($B16,'Pwood & PB List'!$B$4:$V$158,10,FALSE),IF('Summary Sheet'!$M$4="PB w/ Wood Drawers",VLOOKUP($B16,'Pwood & PB List'!$B$4:$V$158,14,FALSE),IF('Summary Sheet'!$M$4="PB w/ PB Drawers",VLOOKUP($B16,'Pwood & PB List'!$B$4:$V$158,18,FALSE)))) -> 501.86 | J16: =CONCATENATE("WEO-",B16) -> WEO-B09FD | K16: =IF('Summary Sheet'!$M$4="Plywood",VLOOKUP($B16,'Pwood & PB List'!$B$4:$V$158,9,FALSE),IF('Summary Sheet'!$M$4="PB w/ Wood Drawers",VLOOKUP($B16,'Pwood & PB List'!$B$4:$V$158,13,FALSE),IF('Summary Sheet'!$M$4="PB w/ PB Drawers",VLOOKUP($B16,'Pwood & PB List'!$B$4:$V$158,17,FALSE)))) -> 515.43 | L16: =CONCATENATE("GLG-",B16) -> GLG-B09FD | M16: =IF('Summary Sheet'!$M$4="Plywood",VLOOKUP($B16,'Pwood & PB List'!$B$4:$V$158,12,FALSE),IF('Summary Sheet'!$M$4="PB w/ Wood Drawers",VLOOKUP($B16,'Pwood & PB List'!$B$4:$V$158,16,FALSE),IF('Summary Sheet'!$M$4="PB w/ PB Drawers",VLOOKUP($B16,'Pwood & PB List'!$B$4:$V$158,20,FALSE)))) -> 470.925 | N16: =CONCATENATE("NAO-",B16) -> NAO-B09FD | O16: =IF('Summary Sheet'!$M$4="Plywood",VLOOKUP($B16,'Pwood & PB List'!$B$4:$V$158,12,FALSE),IF('Summary Sheet'!$M$4="PB w/ Wood Drawers",VLOOKUP($B16,'Pwood & PB List'!$B$4:$V$158,16,FALSE),IF('Summary Sheet'!$M$4="PB w/ PB Drawers",VLOOKUP($B16,'Pwood & PB List'!$B$4:$V$158,20,FALSE)))) -> 470.925 | P16: =CONCATENATE("WHO-",B16) -> WHO-B09FD | Q16: =IF('Summary Sheet'!$M$4="Plywood",VLOOKUP($B16,'Pwood & PB List'!$B$4:$V$158,9,FALSE),IF('Summary Sheet'!$M$4="PB w/ Wood Drawers",VLOOKUP($B16,'Pwood & PB List'!$B$4:$V$158,13,FALSE),IF('Summary Sheet'!$M$4="PB w/ PB Drawers",VLOOKUP($B16,'Pwood & PB List'!$B$4:$V$158,17,FALSE)))) -> 515.43 | R16: =CONCATENATE("MAW-",B16) -> MAW-B09FD | S16: =IF('Summary Sheet'!$M$4="Plywood",VLOOKUP($B16,'Pwood & PB List'!$B$4:$V$158,9,FALSE),IF('Summary Sheet'!$M$4="PB w/ Wood Drawers",VLOOKUP($B16,'Pwood & PB List'!$B$4:$V$158,13,FALSE),IF('Summary Sheet'!$M$4="PB w/ PB Drawers",VLOOKUP($B16,'Pwood & PB List'!$B$4:$V$158,17,FALSE)))) -> 515.43 | T16: =CONCATENATE("MAG-",B16) -> MAG-B09FD | U16: =IF('Summary Sheet'!$M$4="Plywood",VLOOKUP($B16,'Pwood & PB List'!$B$4:$V$158,9,FALSE),IF('Summary Sheet'!$M$4="PB w/ Wood Drawers",VLOOKUP($B16,'Pwood & PB List'!$B$4:$V$158,13,FALSE),IF('Summary Sheet'!$M$4="PB w/ PB Drawers",VLOOKUP($B16,'Pwood & PB List'!$B$4:$V$158,17,FALSE)))) -> 515.43 | V16: =CONCATENATE("MAB-",B16) -> MAB-B09FD | W16: =IF('Summary Sheet'!$M$4="Plywood",VLOOKUP($B16,'Pwood & PB List'!$B$4:$V$158,9,FALSE),IF('Summary Sheet'!$M$4="PB w/ Wood Drawers",VLOOKUP($B16,'Pwood & PB List'!$B$4:$V$158,13,FALSE),IF('Summary Sheet'!$M$4="PB w/ PB Drawers",VLOOKUP($B16,'Pwood & PB List'!$B$4:$V$158,17,FALSE)))) -> 515.43 | X16: =CONCATENATE("GLB-",B16) -> GLB-B09FD | Y16: 1
A17: 15" Base Cabinet: 1 Full-Height Door | B17: B12FD | C17: =IF('Summary Sheet'!$M$4="Plywood",VLOOKUP($B17,'Pwood & PB List'!$B$4:$V$158,9,FALSE),IF('Summary Sheet'!$M$4="PB w/ Wood Drawers",VLOOKUP($B17,'Pwood & PB List'!$B$4:$V$158,13,FALSE),IF('Summary Sheet'!$M$4="PB w/ PB Drawers",VLOOKUP($B17,'Pwood & PB List'!$B$4:$V$158,17,FALSE)))) -> 747.96 | D17: =CONCATENATE("GLW-",B17) -> GLW-B12FD | E17: =IF('Summary Sheet'!$M$4="Plywood",VLOOKUP($B17,'Pwood & PB List'!$B$4:$V$158,10,FALSE),IF('Summary Sheet'!$M$4="PB w/ Wood Drawers",VLOOKUP($B17,'Pwood & PB List'!$B$4:$V$158,14,FALSE),IF('Summary Sheet'!$M$4="PB w/ PB Drawers",VLOOKUP($B17,'Pwood & PB List'!$B$4:$V$158,18,FALSE)))) -> 729.675 | F17: =CONCATENATE("SLO-",B17) -> SLO-B12FD | G17: =IF('Summary Sheet'!$M$4="Plywood",VLOOKUP($B17,'Pwood & PB List'!$B$4:$V$158,11,FALSE),IF('Summary Sheet'!$M$4="PB w/ Wood Drawers",VLOOKUP($B17,'Pwood & PB List'!$B$4:$V$158,15,FALSE),IF('Summary Sheet'!$M$4="PB w/ PB Drawers",VLOOKUP($B17,'Pwood & PB List'!$B$4:$V$158,19,FALSE)))) -> 710.24 | H17: =CONCATENATE("BLW-",B17) -> BLW-B12FD | I17: =IF('Summary Sheet'!$M$4="Plywood",VLOOKUP($B17,'Pwood & PB List'!$B$4:$V$158,10,FALSE),IF('Summary Sheet'!$M$4="PB w/ Wood Drawers",VLOOKUP($B17,'Pwood & PB List'!$B$4:$V$158,14,FALSE),IF('Summary Sheet'!$M$4="PB w/ PB Drawers",VLOOKUP($B17,'Pwood & PB List'!$B$4:$V$158,18,FALSE)))) -> 729.675 | J17: =CONCATENATE("WEO-",B17) -> WEO-B12FD | K17: =IF('Summary Sheet'!$M$4="Plywood",VLOOKUP($B17,'Pwood & PB List'!$B$4:$V$158,9,FALSE),IF('Summary Sheet'!$M$4="PB w/ Wood Drawers",VLOOKUP($B17,'Pwood & PB List'!$B$4:$V$158,13,FALSE),IF('Summary Sheet'!$M$4="PB w/ PB Drawers",VLOOKUP($B17,'Pwood & PB List'!$B$4:$V$158,17,FALSE)))) -> 747.96 | L17: =CONCATENATE("GLG-",B17) -> GLG-B12FD | M17: =IF('Summary Sheet'!$M$4="Plywood",VLOOKUP($B17,'Pwood & PB List'!$B$4:$V$158,12,FALSE),IF('Summary Sheet'!$M$4="PB w/ Wood Drawers",VLOOKUP($B17,'Pwood & PB List'!$B$4:$V$158,16,FALSE),IF('Summary Sheet'!$M$4="PB w/ PB Drawers",VLOOKUP($B17,'Pwood & PB List'!$B$4:$V$158,20,FALSE)))) -> 688.39 | N17: =CONCATENATE("NAO-",B17) -> NAO-B12FD | O17: =IF('Summary Sheet'!$M$4="Plywood",VLOOKUP($B17,'Pwood & PB List'!$B$4:$V$158,12,FALSE),IF('Summary Sheet'!$M$4="PB w/ Wood Drawers",VLOOKUP($B17,'Pwood & PB List'!$B$4:$V$158,16,FALSE),IF('Summary Sheet'!$M$4="PB w/ PB Drawers",VLOOKUP($B17,'Pwood & PB List'!$B$4:$V$158,20,FALSE)))) -> 688.39 | P17: =CONCATENATE("WHO-",B17) -> WHO-B12FD | Q17: =IF('Summary Sheet'!$M$4="Plywood",VLOOKUP($B17,'Pwood & PB List'!$B$4:$V$158,9,FALSE),IF('Summary Sheet'!$M$4="PB w/ Wood Drawers",VLOOKUP($B17,'Pwood & PB List'!$B$4:$V$158,13,FALSE),IF('Summary Sheet'!$M$4="PB w/ PB Drawers",VLOOKUP($B17,'Pwood & PB List'!$B$4:$V$158,17,FALSE)))) -> 747.96 | R17: =CONCATENATE("MAW-",B17) -> MAW-B12FD | S17: =IF('Summary Sheet'!$M$4="Plywood",VLOOKUP($B17,'Pwood & PB List'!$B$4:$V$158,9,FALSE),IF('Summary Sheet'!$M$4="PB w/ Wood Drawers",VLOOKUP($B17,'Pwood & PB List'!$B$4:$V$158,13,FALSE),IF('Summary Sheet'!$M$4="PB w/ PB Drawers",VLOOKUP($B17,'Pwood & PB List'!$B$4:$V$158,17,FALSE)))) -> 747.96 | T17: =CONCATENATE("MAG-",B17) -> MAG-B12FD | U17: =IF('Summary Sheet'!$M$4="Plywood",VLOOKUP($B17,'Pwood & PB List'!$B$4:$V$158,9,FALSE),IF('Summary Sheet'!$M$4="PB w/ Wood Drawers",VLOOKUP($B17,'Pwood & PB List'!$B$4:$V$158,13,FALSE),IF('Summary Sheet'!$M$4="PB w/ PB Drawers",VLOOKUP($B17,'Pwood & PB List'!$B$4:$V$158,17,FALSE)))) -> 747.96 | V17: =CONCATENATE("MAB-",B17) -> MAB-B12FD | W17: =IF('Summary Sheet'!$M$4="Plywood",VLOOKUP($B17,'Pwood & PB List'!$B$4:$V$158,9,FALSE),IF('Summary Sheet'!$M$4="PB w/ Wood Drawers",VLOOKUP($B17,'Pwood & PB List'!$B$4:$V$158,13,FALSE),IF('Summary Sheet'!$M$4="PB w/ PB Drawers",VLOOKUP($B17,'Pwood & PB List'!$B$4:$V$158,17,FALSE)))) -> 747.96 | X17: =CONCATENATE("GLB-",B17) -> GLB-B12FD | Y17: 1
A18: 15" Base Cabinet: 1 Full-Height Door | B18: B15FD | C18: =IF('Summary Sheet'!$M$4="Plywood",VLOOKUP($B18,'Pwood & PB List'!$B$4:$V$158,9,FALSE),IF('Summary Sheet'!$M$4="PB w/ Wood Drawers",VLOOKUP($B18,'Pwood & PB List'!$B$4:$V$158,13,FALSE),IF('Summary Sheet'!$M$4="PB w/ PB Drawers",VLOOKUP($B18,'Pwood & PB List'!$B$4:$V$158,17,FALSE)))) -> 828.69 | D18: =CONCATENATE("GLW-",B18) -> GLW-B15FD | E18: =IF('Summary Sheet'!$M$4="Plywood",VLOOKUP($B18,'Pwood & PB List'!$B$4:$V$158,10,FALSE),IF('Summary Sheet'!$M$4="PB w/ Wood Drawers",VLOOKUP($B18,'Pwood & PB List'!$B$4:$V$158,14,FALSE),IF('Summary Sheet'!$M$4="PB w/ PB Drawers",VLOOKUP($B18,'Pwood & PB List'!$B$4:$V$158,18,FALSE)))) -> 805.92 | F18: =CONCATENATE("SLO-",B18) -> SLO-B15FD | G18: =IF('Summary Sheet'!$M$4="Plywood",VLOOKUP($B18,'Pwood & PB List'!$B$4:$V$158,11,FALSE),IF('Summary Sheet'!$M$4="PB w/ Wood Drawers",VLOOKUP($B18,'Pwood & PB List'!$B$4:$V$158,15,FALSE),IF('Summary Sheet'!$M$4="PB w/ PB Drawers",VLOOKUP($B18,'Pwood & PB List'!$B$4:$V$158,19,FALSE)))) -> 781.54 | H18: =CONCATENATE("BLW-",B18) -> BLW-B15FD | I18: =IF('Summary Sheet'!$M$4="Plywood",VLOOKUP($B18,'Pwood & PB List'!$B$4:$V$158,10,FALSE),IF('Summary Sheet'!$M$4="PB w/ Wood Drawers",VLOOKUP($B18,'Pwood & PB List'!$B$4:$V$158,14,FALSE),IF('Summary Sheet'!$M$4="PB w/ PB Drawers",VLOOKUP($B18,'Pwood & PB List'!$B$4:$V$158,18,FALSE)))) -> 805.92 | J18: =CONCATENATE("WEO-",B18) -> WEO-B15FD | K18: =IF('Summary Sheet'!$M$4="Plywood",VLOOKUP($B18,'Pwood & PB List'!$B$4:$V$158,9,FALSE),IF('Summary Sheet'!$M$4="PB w/ Wood Drawers",VLOOKUP($B18,'Pwood & PB List'!$B$4:$V$158,13,FALSE),IF('Summary Sheet'!$M$4="PB w/ PB Drawers",VLOOKUP($B18,'Pwood & PB List'!$B$4:$V$158,17,FALSE)))) -> 828.69 | L18: =CONCATENATE("GLG-",B18) -> GLG-B15FD | M18: =IF('Summary Sheet'!$M$4="Plywood",VLOOKUP($B18,'Pwood & PB List'!$B$4:$V$158,12,FALSE),IF('Summary Sheet'!$M$4="PB w/ Wood Drawers",VLOOKUP($B18,'Pwood & PB List'!$B$4:$V$158,16,FALSE),IF('Summary Sheet'!$M$4="PB w/ PB Drawers",VLOOKUP($B18,'Pwood & PB List'!$B$4:$V$158,20,FALSE)))) -> 754.055 | N18: =CONCATENATE("NAO-",B18) -> NAO-B15FD | O18: =IF('Summary Sheet'!$M$4="Plywood",VLOOKUP($B18,'Pwood & PB List'!$B$4:$V$158,12,FALSE),IF('Summary Sheet'!$M$4="PB w/ Wood Drawers",VLOOKUP($B18,'Pwood & PB List'!$B$4:$V$158,16,FALSE),IF('Summary Sheet'!$M$4="PB w/ PB Drawers",VLOOKUP($B18,'Pwood & PB List'!$B$4:$V$158,20,FALSE)))) -> 754.055 | P18: =CONCATENATE("WHO-",B18) -> WHO-B15FD | Q18: =IF('Summary Sheet'!$M$4="Plywood",VLOOKUP($B18,'Pwood & PB List'!$B$4:$V$158,9,FALSE),IF('Summary Sheet'!$M$4="PB w/ Wood Drawers",VLOOKUP($B18,'Pwood & PB List'!$B$4:$V$158,13,FALSE),IF('Summary Sheet'!$M$4="PB w/ PB Drawers",VLOOKUP($B18,'Pwood & PB List'!$B$4:$V$158,17,FALSE)))) -> 828.69 | R18: =CONCATENATE("MAW-",B18) -> MAW-B15FD | S18: =IF('Summary Sheet'!$M$4="Plywood",VLOOKUP($B18,'Pwood & PB List'!$B$4:$V$158,9,FALSE),IF('Summary Sheet'!$M$4="PB w/ Wood Drawers",VLOOKUP($B18,'Pwood & PB List'!$B$4:$V$158,13,FALSE),IF('Summary Sheet'!$M$4="PB w/ PB Drawers",VLOOKUP($B18,'Pwood & PB List'!$B$4:$V$158,17,FALSE)))) -> 828.69 | T18: =CONCATENATE("MAG-",B18) -> MAG-B15FD | U18: =IF('Summary Sheet'!$M$4="Plywood",VLOOKUP($B18,'Pwood & PB List'!$B$4:$V$158,9,FALSE),IF('Summary Sheet'!$M$4="PB w/ Wood Drawers",VLOOKUP($B18,'Pwood & PB List'!$B$4:$V$158,13,FALSE),IF('Summary Sheet'!$M$4="PB w/ PB Drawers",VLOOKUP($B18,'Pwood & PB List'!$B$4:$V$158,17,FALSE)))) -> 828.69 | V18: =CONCATENATE("MAB-",B18) -> MAB-B15FD | W18: =IF('Summary Sheet'!$M$4="Plywood",VLOOKUP($B18,'Pwood & PB List'!$B$4:$V$158,9,FALSE),IF('Summary Sheet'!$M$4="PB w/ Wood Drawers",VLOOKUP($B18,'Pwood & PB List'!$B$4:$V$158,13,FALSE),IF('Summary Sheet'!$M$4="PB w/ PB Drawers",VLOOKUP($B18,'Pwood & PB List'!$B$4:$V$158,17,FALSE)))) -> 828.69 | X18: =CONCATENATE("GLB-",B18) -> GLB-B15FD | Y18: 1
A19: 18" Base Cabinet: 1 Full-Height Door | B19: B18FD | C19: =IF('Summary Sheet'!$M$4="Plywood",VLOOKUP($B19,'Pwood & PB List'!$B$4:$V$158,9,FALSE),IF('Summary Sheet'!$M$4="PB w/ Wood Drawers",VLOOKUP($B19,'Pwood & PB List'!$B$4:$V$158,13,FALSE),IF('Summary Sheet'!$M$4="PB w/ PB Drawers",VLOOKUP($B19,'Pwood & PB List'!$B$4:$V$158,17,FALSE)))) -> 909.535 | D19: =CONCATENATE("GLW-",B19) -> GLW-B18FD | E19: =IF('Summary Sheet'!$M$4="Plywood",VLOOKUP($B19,'Pwood & PB List'!$B$4:$V$158,10,FALSE),IF('Summary Sheet'!$M$4="PB w/ Wood Drawers",VLOOKUP($B19,'Pwood & PB List'!$B$4:$V$158,14,FALSE),IF('Summary Sheet'!$M$4="PB w/ PB Drawers",VLOOKUP($B19,'Pwood & PB List'!$B$4:$V$158,18,FALSE)))) -> 882.05 | F19: =CONCATENATE("SLO-",B19) -> SLO-B18FD | G19: =IF('Summary Sheet'!$M$4="Plywood",VLOOKUP($B19,'Pwood & PB List'!$B$4:$V$158,11,FALSE),IF('Summary Sheet'!$M$4="PB w/ Wood Drawers",VLOOKUP($B19,'Pwood & PB List'!$B$4:$V$158,15,FALSE),IF('Summary Sheet'!$M$4="PB w/ PB Drawers",VLOOKUP($B19,'Pwood & PB List'!$B$4:$V$158,19,FALSE)))) -> 852.84 | H19: =CONCATENATE("BLW-",B19) -> BLW-B18FD | I19: =IF('Summary Sheet'!$M$4="Plywood",VLOOKUP($B19,'Pwood & PB List'!$B$4:$V$158,10,FALSE),IF('Summary Sheet'!$M$4="PB w/ Wood Drawers",VLOOKUP($B19,'Pwood & PB List'!$B$4:$V$158,14,FALSE),IF('Summary Sheet'!$M$4="PB w/ PB Drawers",VLOOKUP($B19,'Pwood & PB List'!$B$4:$V$158,18,FALSE)))) -> 882.05 | J19: =CONCATENATE("WEO-",B19) -> WEO-B18FD | K19: =IF('Summary Sheet'!$M$4="Plywood",VLOOKUP($B19,'Pwood & PB List'!$B$4:$V$158,9,FALSE),IF('Summary Sheet'!$M$4="PB w/ Wood Drawers",VLOOKUP($B19,'Pwood & PB List'!$B$4:$V$158,13,FALSE),IF('Summary Sheet'!$M$4="PB w/ PB Drawers",VLOOKUP($B19,'Pwood & PB List'!$B$4:$V$158,17,FALSE)))) -> 909.535 | L19: =CONCATENATE("GLG-",B19) -> GLG-B18FD | M19: =IF('Summary Sheet'!$M$4="Plywood",VLOOKUP($B19,'Pwood & PB List'!$B$4:$V$158,12,FALSE),IF('Summary Sheet'!$M$4="PB w/ Wood Drawers",VLOOKUP($B19,'Pwood & PB List'!$B$4:$V$158,16,FALSE),IF('Summary Sheet'!$M$4="PB w/ PB Drawers",VLOOKUP($B19,'Pwood & PB List'!$B$4:$V$158,20,FALSE)))) -> 819.835 | N19: =CONCATENATE("NAO-",B19) -> NAO-B18FD | O19: =IF('Summary Sheet'!$M$4="Plywood",VLOOKUP($B19,'Pwood & PB List'!$B$4:$V$158,12,FALSE),IF('Summary Sheet'!$M$4="PB w/ Wood Drawers",VLOOKUP($B19,'Pwood & PB List'!$B$4:$V$158,16,FALSE),IF('Summary Sheet'!$M$4="PB w/ PB Drawers",VLOOKUP($B19,'Pwood & PB List'!$B$4:$V$158,20,FALSE)))) -> 819.835 | P19: =CONCATENATE("WHO-",B19) -> WHO-B18FD | Q19: =IF('Summary Sheet'!$M$4="Plywood",VLOOKUP($B19,'Pwood & PB List'!$B$4:$V$158,9,FALSE),IF('Summary Sheet'!$M$4="PB w/ Wood Drawers",VLOOKUP($B19,'Pwood & PB List'!$B$4:$V$158,13,FALSE),IF('Summary Sheet'!$M$4="PB w/ PB Drawers",VLOOKUP($B19,'Pwood & PB List'!$B$4:$V$158,17,FALSE)))) -> 909.535 | R19: =CONCATENATE("MAW-",B19) -> MAW-B18FD | S19: =IF('Summary Sheet'!$M$4="Plywood",VLOOKUP($B19,'Pwood & PB List'!$B$4:$V$158,9,FALSE),IF('Summary Sheet'!$M$4="PB w/ Wood Drawers",VLOOKUP($B19,'Pwood & PB List'!$B$4:$V$158,13,FALSE),IF('Summary Sheet'!$M$4="PB w/ PB Drawers",VLOOKUP($B19,'Pwood & PB List'!$B$4:$V$158,17,FALSE)))) -> 909.535 | T19: =CONCATENATE("MAG-",B19) -> MAG-B18FD | U19: =IF('Summary Sheet'!$M$4="Plywood",VLOOKUP($B19,'Pwood & PB List'!$B$4:$V$158,9,FALSE),IF('Summary Sheet'!$M$4="PB w/ Wood Drawers",VLOOKUP($B19,'Pwood & PB List'!$B$4:$V$158,13,FALSE),IF('Summary Sheet'!$M$4="PB w/ PB Drawers",VLOOKUP($B19,'Pwood & PB List'!$B$4:$V$158,17,FALSE)))) -> 909.535 | V19: =CONCATENATE("MAB-",B19) -> MAB-B18FD | W19: =IF('Summary Sheet'!$M$4="Plywood",VLOOKUP($B19,'Pwood & PB List'!$B$4:$V$158,9,FALSE),IF('Summary Sheet'!$M$4="PB w/ Wood Drawers",VLOOKUP($B19,'Pwood & PB List'!$B$4:$V$158,13,FALSE),IF('Summary Sheet'!$M$4="PB w/ PB Drawers",VLOOKUP($B19,'Pwood & PB List'!$B$4:$V$158,17,FALSE)))) -> 909.535 | X19: =CONCATENATE("GLB-",B19) -> GLB-B18FD | Y19: 1
A20: 21" Base Cabinet: 1 Full-Height Door | B20: B21FD | C20: =IF('Summary Sheet'!$M$4="Plywood",VLOOKUP($B20,'Pwood & PB List'!$B$4:$V$158,9,FALSE),IF('Summary Sheet'!$M$4="PB w/ Wood Drawers",VLOOKUP($B20,'Pwood & PB List'!$B$4:$V$158,13,FALSE),IF('Summary Sheet'!$M$4="PB w/ PB Drawers",VLOOKUP($B20,'Pwood & PB List'!$B$4:$V$158,17,FALSE)))) -> 990.38 | D20: =CONCATENATE("GLW-",B20) -> GLW-B21FD | E20: =IF('Summary Sheet'!$M$4="Plywood",VLOOKUP($B20,'Pwood & PB List'!$B$4:$V$158,10,FALSE),IF('Summary Sheet'!$M$4="PB w/ Wood Drawers",VLOOKUP($B20,'Pwood & PB List'!$B$4:$V$158,14,FALSE),IF('Summary Sheet'!$M$4="PB w/ PB Drawers",VLOOKUP($B20,'Pwood & PB List'!$B$4:$V$158,18,FALSE)))) -> 958.295 | F20: =CONCATENATE("SLO-",B20) -> SLO-B21FD | G20: =IF('Summary Sheet'!$M$4="Plywood",VLOOKUP($B20,'Pwood & PB List'!$B$4:$V$158,11,FALSE),IF('Summary Sheet'!$M$4="PB w/ Wood Drawers",VLOOKUP($B20,'Pwood & PB List'!$B$4:$V$158,15,FALSE),IF('Summary Sheet'!$M$4="PB w/ PB Drawers",VLOOKUP($B20,'Pwood & PB List'!$B$4:$V$158,19,FALSE)))) -> 924.14 | H20: =CONCATENATE("BLW-",B20) -> BLW-B21FD | I20: =IF('Summary Sheet'!$M$4="Plywood",VLOOKUP($B20,'Pwood & PB List'!$B$4:$V$158,10,FALSE),IF('Summary Sheet'!$M$4="PB w/ Wood Drawers",VLOOKUP($B20,'Pwood & PB List'!$B$4:$V$158,14,FALSE),IF('Summary Sheet'!$M$4="PB w/ PB Drawers",VLOOKUP($B20,'Pwood & PB List'!$B$4:$V$158,18,FALSE)))) -> 958.295 | J20: =CONCATENATE("WEO-",B20) -> WEO-B21FD | K20: =IF('Summary Sheet'!$M$4="Plywood",VLOOKUP($B20,'Pwood & PB List'!$B$4:$V$158,9,FALSE),IF('Summary Sheet'!$M$4="PB w/ Wood Drawers",VLOOKUP($B20,'Pwood & PB List'!$B$4:$V$158,13,FALSE),IF('Summary Sheet'!$M$4="PB w/ PB Drawers",VLOOKUP($B20,'Pwood & PB List'!$B$4:$V$158,17,FALSE)))) -> 990.38 | L20: =CONCATENATE("GLG-",B20) -> GLG-B21FD | M20: =IF('Summary Sheet'!$M$4="Plywood",VLOOKUP($B20,'Pwood & PB List'!$B$4:$V$158,12,FALSE),IF('Summary Sheet'!$M$4="PB w/ Wood Drawers",VLOOKUP($B20,'Pwood & PB List'!$B$4:$V$158,16,FALSE),IF('Summary Sheet'!$M$4="PB w/ PB Drawers",VLOOKUP($B20,'Pwood & PB List'!$B$4:$V$158,20,FALSE)))) -> 885.615 | N20: =CONCATENATE("NAO-",B20) -> NAO-B21FD | O20: =IF('Summary Sheet'!$M$4="Plywood",VLOOKUP($B20,'Pwood & PB List'!$B$4:$V$158,12,FALSE),IF('Summary Sheet'!$M$4="PB w/ Wood Drawers",VLOOKUP($B20,'Pwood & PB List'!$B$4:$V$158,16,FALSE),IF('Summary Sheet'!$M$4="PB w/ PB Drawers",VLOOKUP($B20,'Pwood & PB List'!$B$4:$V$158,20,FALSE)))) -> 885.615 | P20: =CONCATENATE("WHO-",B20) -> WHO-B21FD | Q20: =IF('Summary Sheet'!$M$4="Plywood",VLOOKUP($B20,'Pwood & PB List'!$B$4:$V$158,9,FALSE),IF('Summary Sheet'!$M$4="PB w/ Wood Drawers",VLOOKUP($B20,'Pwood & PB List'!$B$4:$V$158,13,FALSE),IF('Summary Sheet'!$M$4="PB w/ PB Drawers",VLOOKUP($B20,'Pwood & PB List'!$B$4:$V$158,17,FALSE)))) -> 990.38 | R20: =CONCATENATE("MAW-",B20) -> MAW-B21FD | S20: =IF('Summary Sheet'!$M$4="Plywood",VLOOKUP($B20,'Pwood & PB List'!$B$4:$V$158,9,FALSE),IF('Summary Sheet'!$M$4="PB w/ Wood Drawers",VLOOKUP($B20,'Pwood & PB List'!$B$4:$V$158,13,FALSE),IF('Summary Sheet'!$M$4="PB w/ PB Drawers",VLOOKUP($B20,'Pwood & PB List'!$B$4:$V$158,17,FALSE)))) -> 990.38 | T20: =CONCATENATE("MAG-",B20) -> MAG-B21FD | U20: =IF('Summary Sheet'!$M$4="Plywood",VLOOKUP($B20,'Pwood & PB List'!$B$4:$V$158,9,FALSE),IF('Summary Sheet'!$M$4="PB w/ Wood Drawers",VLOOKUP($B20,'Pwood & PB List'!$B$4:$V$158,13,FALSE),IF('Summary Sheet'!$M$4="PB w/ PB Drawers",VLOOKUP($B20,'Pwood & PB List'!$B$4:$V$158,17,FALSE)))) -> 990.38 | V20: =CONCATENATE("MAB-",B20) -> MAB-B21FD | W20: =IF('Summary Sheet'!$M$4="Plywood",VLOOKUP($B20,'Pwood & PB List'!$B$4:$V$158,9,FALSE),IF('Summary Sheet'!$M$4="PB w/ Wood Drawers",VLOOKUP($B20,'Pwood & PB List'!$B$4:$V$158,13,FALSE),IF('Summary Sheet'!$M$4="PB w/ PB Drawers",VLOOKUP($B20,'Pwood & PB List'!$B$4:$V$158,17,FALSE)))) -> 990.38 | X20: =CONCATENATE("GLB-",B20) -> GLB-B21FD | Y20: 1
A21: 24" Base Cabinet: 1 Full-Height Door | B21: B24FD | C21: =IF('Summary Sheet'!$M$4="Plywood",VLOOKUP($B21,'Pwood & PB List'!$B$4:$V$158,9,FALSE),IF('Summary Sheet'!$M$4="PB w/ Wood Drawers",VLOOKUP($B21,'Pwood & PB List'!$B$4:$V$158,13,FALSE),IF('Summary Sheet'!$M$4="PB w/ PB Drawers",VLOOKUP($B21,'Pwood & PB List'!$B$4:$V$158,17,FALSE)))) -> 1088.13 | D21: =CONCATENATE("GLW-",B21) -> GLW-B24FD | E21: =IF('Summary Sheet'!$M$4="Plywood",VLOOKUP($B21,'Pwood & PB List'!$B$4:$V$158,10,FALSE),IF('Summary Sheet'!$M$4="PB w/ Wood Drawers",VLOOKUP($B21,'Pwood & PB List'!$B$4:$V$158,14,FALSE),IF('Summary Sheet'!$M$4="PB w/ PB Drawers",VLOOKUP($B21,'Pwood & PB List'!$B$4:$V$158,18,FALSE)))) -> 1051.675 | F21: =CONCATENATE("SLO-",B21) -> SLO-B24FD | G21: =IF('Summary Sheet'!$M$4="Plywood",VLOOKUP($B21,'Pwood & PB List'!$B$4:$V$158,11,FALSE),IF('Summary Sheet'!$M$4="PB w/ Wood Drawers",VLOOKUP($B21,'Pwood & PB List'!$B$4:$V$158,15,FALSE),IF('Summary Sheet'!$M$4="PB w/ PB Drawers",VLOOKUP($B21,'Pwood & PB List'!$B$4:$V$158,19,FALSE)))) -> 1012.805 | H21: =CONCATENATE("BLW-",B21) -> BLW-B24FD | I21: =IF('Summary Sheet'!$M$4="Plywood",VLOOKUP($B21,'Pwood & PB List'!$B$4:$V$158,10,FALSE),IF('Summary Sheet'!$M$4="PB w/ Wood Drawers",VLOOKUP($B21,'Pwood & PB List'!$B$4:$V$158,14,FALSE),IF('Summary Sheet'!$M$4="PB w/ PB Drawers",VLOOKUP($B21,'Pwood & PB List'!$B$4:$V$158,18,FALSE)))) -> 1051.675 | J21: =CONCATENATE("WEO-",B21) -> WEO-B24FD | K21: =IF('Summary Sheet'!$M$4="Plywood",VLOOKUP($B21,'Pwood & PB List'!$B$4:$V$158,9,FALSE),IF('Summary Sheet'!$M$4="PB w/ Wood Drawers",VLOOKUP($B21,'Pwood & PB List'!$B$4:$V$158,13,FALSE),IF('Summary Sheet'!$M$4="PB w/ PB Drawers",VLOOKUP($B21,'Pwood & PB List'!$B$4:$V$158,17,FALSE)))) -> 1088.13 | L21: =CONCATENATE("GLG-",B21) -> GLG-B24FD | M21: =IF('Summary Sheet'!$M$4="Plywood",VLOOKUP($B21,'Pwood & PB List'!$B$4:$V$158,12,FALSE),IF('Summary Sheet'!$M$4="PB w/ Wood Drawers",VLOOKUP($B21,'Pwood & PB List'!$B$4:$V$158,16,FALSE),IF('Summary Sheet'!$M$4="PB w/ PB Drawers",VLOOKUP($B21,'Pwood & PB List'!$B$4:$V$158,20,FALSE)))) -> 968.99 | N21: =CONCATENATE("NAO-",B21) -> NAO-B24FD | O21: =IF('Summary Sheet'!$M$4="Plywood",VLOOKUP($B21,'Pwood & PB List'!$B$4:$V$158,12,FALSE),IF('Summary Sheet'!$M$4="PB w/ Wood Drawers",VLOOKUP($B21,'Pwood & PB List'!$B$4:$V$158,16,FALSE),IF('Summary Sheet'!$M$4="PB w/ PB Drawers",VLOOKUP($B21,'Pwood & PB List'!$B$4:$V$158,20,FALSE)))) -> 968.99 | P21: =CONCATENATE("WHO-",B21) -> WHO-B24FD | Q21: =IF('Summary Sheet'!$M$4="Plywood",VLOOKUP($B21,'Pwood & PB List'!$B$4:$V$158,9,FALSE),IF('Summary Sheet'!$M$4="PB w/ Wood Drawers",VLOOKUP($B21,'Pwood & PB List'!$B$4:$V$158,13,FALSE),IF('Summary Sheet'!$M$4="PB w/ PB Drawers",VLOOKUP($B21,'Pwood & PB List'!$B$4:$V$158,17,FALSE)))) -> 1088.13 | R21: =CONCATENATE("MAW-",B21) -> MAW-B24FD | S21: =IF('Summary Sheet'!$M$4="Plywood",VLOOKUP($B21,'Pwood & PB List'!$B$4:$V$158,9,FALSE),IF('Summary Sheet'!$M$4="PB w/ Wood Drawers",VLOOKUP($B21,'Pwood & PB List'!$B$4:$V$158,13,FALSE),IF('Summary Sheet'!$M$4="PB w/ PB Drawers",VLOOKUP($B21,'Pwood & PB List'!$B$4:$V$158,17,FALSE)))) -> 1088.13 | T21: =CONCATENATE("MAG-",B21) -> MAG-B24FD | U21: =IF('Summary Sheet'!$M$4="Plywood",VLOOKUP($B21,'Pwood & PB List'!$B$4:$V$158,9,FALSE),IF('Summary Sheet'!$M$4="PB w/ Wood Drawers",VLOOKUP($B21,'Pwood & PB List'!$B$4:$V$158,13,FALSE),IF('Summary Sheet'!$M$4="PB w/ PB Drawers",VLOOKUP($B21,'Pwood & PB List'!$B$4:$V$158,17,FALSE)))) -> 1088.13 | V21: =CONCATENATE("MAB-",B21) -> MAB-B24FD | W21: =IF('Summary Sheet'!$M$4="Plywood",VLOOKUP($B21,'Pwood & PB List'!$B$4:$V$158,9,FALSE),IF('Summary Sheet'!$M$4="PB w/ Wood Drawers",VLOOKUP($B21,'Pwood & PB List'!$B$4:$V$158,13,FALSE),IF('Summary Sheet'!$M$4="PB w/ PB Drawers",VLOOKUP($B21,'Pwood & PB List'!$B$4:$V$158,17,FALSE)))) -> 1088.13 | X21: =CONCATENATE("GLB-",B21) -> GLB-B24FD | Y21: 2
A22: 27" Base Cabinet: 1 Full-Height Door | B22: B27FD | C22: =IF('Summary Sheet'!$M$4="Plywood",VLOOKUP($B22,'Pwood & PB List'!$B$4:$V$158,9,FALSE),IF('Summary Sheet'!$M$4="PB w/ Wood Drawers",VLOOKUP($B22,'Pwood & PB List'!$B$4:$V$158,13,FALSE),IF('Summary Sheet'!$M$4="PB w/ PB Drawers",VLOOKUP($B22,'Pwood & PB List'!$B$4:$V$158,17,FALSE)))) -> 1168.86 | D22: =CONCATENATE("GLW-",B22) -> GLW-B27FD | E22: =IF('Summary Sheet'!$M$4="Plywood",VLOOKUP($B22,'Pwood & PB List'!$B$4:$V$158,10,FALSE),IF('Summary Sheet'!$M$4="PB w/ Wood Drawers",VLOOKUP($B22,'Pwood & PB List'!$B$4:$V$158,14,FALSE),IF('Summary Sheet'!$M$4="PB w/ PB Drawers",VLOOKUP($B22,'Pwood & PB List'!$B$4:$V$158,18,FALSE)))) -> 1127.805 | F22: =CONCATENATE("SLO-",B22) -> SLO-B27FD | G22: =IF('Summary Sheet'!$M$4="Plywood",VLOOKUP($B22,'Pwood & PB List'!$B$4:$V$158,11,FALSE),IF('Summary Sheet'!$M$4="PB w/ Wood Drawers",VLOOKUP($B22,'Pwood & PB List'!$B$4:$V$158,15,FALSE),IF('Summary Sheet'!$M$4="PB w/ PB Drawers",VLOOKUP($B22,'Pwood & PB List'!$B$4:$V$158,19,FALSE)))) -> 1083.99 | H22: =CONCATENATE("BLW-",B22) -> BLW-B27FD | I22: =IF('Summary Sheet'!$M$4="Plywood",VLOOKUP($B22,'Pwood & PB List'!$B$4:$V$158,10,FALSE),IF('Summary Sheet'!$M$4="PB w/ Wood Drawers",VLOOKUP($B22,'Pwood & PB List'!$B$4:$V$158,14,FALSE),IF('Summary Sheet'!$M$4="PB w/ PB Drawers",VLOOKUP($B22,'Pwood & PB List'!$B$4:$V$158,18,FALSE)))) -> 1127.805 | J22: =CONCATENATE("WEO-",B22) -> WEO-B27FD | K22: =IF('Summary Sheet'!$M$4="Plywood",VLOOKUP($B22,'Pwood & PB List'!$B$4:$V$158,9,FALSE),IF('Summary Sheet'!$M$4="PB w/ Wood Drawers",VLOOKUP($B22,'Pwood & PB List'!$B$4:$V$158,13,FALSE),IF('Summary Sheet'!$M$4="PB w/ PB Drawers",VLOOKUP($B22,'Pwood & PB List'!$B$4:$V$158,17,FALSE)))) -> 1168.86 | L22: =CONCATENATE("GLG-",B22) -> GLG-B27FD | M22: =IF('Summary Sheet'!$M$4="Plywood",VLOOKUP($B22,'Pwood & PB List'!$B$4:$V$158,12,FALSE),IF('Summary Sheet'!$M$4="PB w/ Wood Drawers",VLOOKUP($B22,'Pwood & PB List'!$B$4:$V$158,16,FALSE),IF('Summary Sheet'!$M$4="PB w/ PB Drawers",VLOOKUP($B22,'Pwood & PB List'!$B$4:$V$158,20,FALSE)))) -> 1034.655 | N22: =CONCATENATE("NAO-",B22) -> NAO-B27FD | O22: =IF('Summary Sheet'!$M$4="Plywood",VLOOKUP($B22,'Pwood & PB List'!$B$4:$V$158,12,FALSE),IF('Summary Sheet'!$M$4="PB w/ Wood Drawers",VLOOKUP($B22,'Pwood & PB List'!$B$4:$V$158,16,FALSE),IF('Summary Sheet'!$M$4="PB w/ PB Drawers",VLOOKUP($B22,'Pwood & PB List'!$B$4:$V$158,20,FALSE)))) -> 1034.655 | P22: =CONCATENATE("WHO-",B22) -> WHO-B27FD | Q22: =IF('Summary Sheet'!$M$4="Plywood",VLOOKUP($B22,'Pwood & PB List'!$B$4:$V$158,9,FALSE),IF('Summary Sheet'!$M$4="PB w/ Wood Drawers",VLOOKUP($B22,'Pwood & PB List'!$B$4:$V$158,13,FALSE),IF('Summary Sheet'!$M$4="PB w/ PB Drawers",VLOOKUP($B22,'Pwood & PB List'!$B$4:$V$158,17,FALSE)))) -> 1168.86 | R22: =CONCATENATE("MAW-",B22) -> MAW-B27FD | S22: =IF('Summary Sheet'!$M$4="Plywood",VLOOKUP($B22,'Pwood & PB List'!$B$4:$V$158,9,FALSE),IF('Summary Sheet'!$M$4="PB w/ Wood Drawers",VLOOKUP($B22,'Pwood & PB List'!$B$4:$V$158,13,FALSE),IF('Summary Sheet'!$M$4="PB w/ PB Drawers",VLOOKUP($B22,'Pwood & PB List'!$B$4:$V$158,17,FALSE)))) -> 1168.86 | T22: =CONCATENATE("MAG-",B22) -> MAG-B27FD | U22: =IF('Summary Sheet'!$M$4="Plywood",VLOOKUP($B22,'Pwood & PB List'!$B$4:$V$158,9,FALSE),IF('Summary Sheet'!$M$4="PB w/ Wood Drawers",VLOOKUP($B22,'Pwood & PB List'!$B$4:$V$158,13,FALSE),IF('Summary Sheet'!$M$4="PB w/ PB Drawers",VLOOKUP($B22,'Pwood & PB List'!$B$4:$V$158,17,FALSE)))) -> 1168.86 | V22: =CONCATENATE("MAB-",B22) -> MAB-B27FD | W22: =IF('Summary Sheet'!$M$4="Plywood",VLOOKUP($B22,'Pwood & PB List'!$B$4:$V$158,9,FALSE),IF('Summary Sheet'!$M$4="PB w/ Wood Drawers",VLOOKUP($B22,'Pwood & PB List'!$B$4:$V$158,13,FALSE),IF('Summary Sheet'!$M$4="PB w/ PB Drawers",VLOOKUP($B22,'Pwood & PB List'!$B$4:$V$158,17,FALSE)))) -> 1168.86 | X22: =CONCATENATE("GLB-",B22) -> GLB-B27FD | Y22: 2
A23: 30" Base Cabinet: 1 Full-Height Door | B23: B30FD | C23: =IF('Summary Sheet'!$M$4="Plywood",VLOOKUP($B23,'Pwood & PB List'!$B$4:$V$158,9,FALSE),IF('Summary Sheet'!$M$4="PB w/ Wood Drawers",VLOOKUP($B23,'Pwood & PB List'!$B$4:$V$158,13,FALSE),IF('Summary Sheet'!$M$4="PB w/ PB Drawers",VLOOKUP($B23,'Pwood & PB List'!$B$4:$V$158,17,FALSE)))) -> 1255.34 | D23: =CONCATENATE("GLW-",B23) -> GLW-B30FD | E23: =IF('Summary Sheet'!$M$4="Plywood",VLOOKUP($B23,'Pwood & PB List'!$B$4:$V$158,10,FALSE),IF('Summary Sheet'!$M$4="PB w/ Wood Drawers",VLOOKUP($B23,'Pwood & PB List'!$B$4:$V$158,14,FALSE),IF('Summary Sheet'!$M$4="PB w/ PB Drawers",VLOOKUP($B23,'Pwood & PB List'!$B$4:$V$158,18,FALSE)))) -> 1209.57 | F23: =CONCATENATE("SLO-",B23) -> SLO-B30FD | G23: =IF('Summary Sheet'!$M$4="Plywood",VLOOKUP($B23,'Pwood & PB List'!$B$4:$V$158,11,FALSE),IF('Summary Sheet'!$M$4="PB w/ Wood Drawers",VLOOKUP($B23,'Pwood & PB List'!$B$4:$V$158,15,FALSE),IF('Summary Sheet'!$M$4="PB w/ PB Drawers",VLOOKUP($B23,'Pwood & PB List'!$B$4:$V$158,19,FALSE)))) -> 1160.925 | H23: =CONCATENATE("BLW-",B23) -> BLW-B30FD | I23: =IF('Summary Sheet'!$M$4="Plywood",VLOOKUP($B23,'Pwood & PB List'!$B$4:$V$158,10,FALSE),IF('Summary Sheet'!$M$4="PB w/ Wood Drawers",VLOOKUP($B23,'Pwood & PB List'!$B$4:$V$158,14,FALSE),IF('Summary Sheet'!$M$4="PB w/ PB Drawers",VLOOKUP($B23,'Pwood & PB List'!$B$4:$V$158,18,FALSE)))) -> 1209.57 | J23: =CONCATENATE("WEO-",B23) -> WEO-B30FD | K23: =IF('Summary Sheet'!$M$4="Plywood",VLOOKUP($B23,'Pwood & PB List'!$B$4:$V$158,9,FALSE),IF('Summary Sheet'!$M$4="PB w/ Wood Drawers",VLOOKUP($B23,'Pwood & PB List'!$B$4:$V$158,13,FALSE),IF('Summary Sheet'!$M$4="PB w/ PB Drawers",VLOOKUP($B23,'Pwood & PB List'!$B$4:$V$158,17,FALSE)))) -> 1255.34 | L23: =CONCATENATE("GLG-",B23) -> GLG-B30FD | M23: =IF('Summary Sheet'!$M$4="Plywood",VLOOKUP($B23,'Pwood & PB List'!$B$4:$V$158,12,FALSE),IF('Summary Sheet'!$M$4="PB w/ Wood Drawers",VLOOKUP($B23,'Pwood & PB List'!$B$4:$V$158,16,FALSE),IF('Summary Sheet'!$M$4="PB w/ PB Drawers",VLOOKUP($B23,'Pwood & PB List'!$B$4:$V$158,20,FALSE)))) -> 1106.07 | N23: =CONCATENATE("NAO-",B23) -> NAO-B30FD | O23: =IF('Summary Sheet'!$M$4="Plywood",VLOOKUP($B23,'Pwood & PB List'!$B$4:$V$158,12,FALSE),IF('Summary Sheet'!$M$4="PB w/ Wood Drawers",VLOOKUP($B23,'Pwood & PB List'!$B$4:$V$158,16,FALSE),IF('Summary Sheet'!$M$4="PB w/ PB Drawers",VLOOKUP($B23,'Pwood & PB List'!$B$4:$V$158,20,FALSE)))) -> 1106.07 | P23: =CONCATENATE("WHO-",B23) -> WHO-B30FD | Q23: =IF('Summary Sheet'!$M$4="Plywood",VLOOKUP($B23,'Pwood & PB List'!$B$4:$V$158,9,FALSE),IF('Summary Sheet'!$M$4="PB w/ Wood Drawers",VLOOKUP($B23,'Pwood & PB List'!$B$4:$V$158,13,FALSE),IF('Summary Sheet'!$M$4="PB w/ PB Drawers",VLOOKUP($B23,'Pwood & PB List'!$B$4:$V$158,17,FALSE)))) -> 1255.34 | R23: =CONCATENATE("MAW-",B23) -> MAW-B30FD | S23: =IF('Summary Sheet'!$M$4="Plywood",VLOOKUP($B23,'Pwood & PB List'!$B$4:$V$158,9,FALSE),IF('Summary Sheet'!$M$4="PB w/ Wood Drawers",VLOOKUP($B23,'Pwood & PB List'!$B$4:$V$158,13,FALSE),IF('Summary Sheet'!$M$4="PB w/ PB Drawers",VLOOKUP($B23,'Pwood & PB List'!$B$4:$V$158,17,FALSE)))) -> 1255.34 | T23: =CONCATENATE("MAG-",B23) -> MAG-B30FD | U23: =IF('Summary Sheet'!$M$4="Plywood",VLOOKUP($B23,'Pwood & PB List'!$B$4:$V$158,9,FALSE),IF('Summary Sheet'!$M$4="PB w/ Wood Drawers",VLOOKUP($B23,'Pwood & PB List'!$B$4:$V$158,13,FALSE),IF('Summary Sheet'!$M$4="PB w/ PB Drawers",VLOOKUP($B23,'Pwood & PB List'!$B$4:$V$158,17,FALSE)))) -> 1255.34 | V23: =CONCATENATE("MAB-",B23) -> MAB-B30FD | W23: =IF('Summary Sheet'!$M$4="Plywood",VLOOKUP($B23,'Pwood & PB List'!$B$4:$V$158,9,FALSE),IF('Summary Sheet'!$M$4="PB w/ Wood Drawers",VLOOKUP($B23,'Pwood & PB List'!$B$4:$V$158,13,FALSE),IF('Summary Sheet'!$M$4="PB w/ PB Drawers",VLOOKUP($B23,'Pwood & PB List'!$B$4:$V$158,17,FALSE)))) -> 1255.34 | X23: =CONCATENATE("GLB-",B23) -> GLB-B30FD | Y23: 2
A24: 33" Base Cabinet: 1 Full-Height Door | B24: B33FD | C24: =IF('Summary Sheet'!$M$4="Plywood",VLOOKUP($B24,'Pwood & PB List'!$B$4:$V$158,9,FALSE),IF('Summary Sheet'!$M$4="PB w/ Wood Drawers",VLOOKUP($B24,'Pwood & PB List'!$B$4:$V$158,13,FALSE),IF('Summary Sheet'!$M$4="PB w/ PB Drawers",VLOOKUP($B24,'Pwood & PB List'!$B$4:$V$158,17,FALSE)))) -> 1335.955 | D24: =CONCATENATE("GLW-",B24) -> GLW-B33FD | E24: =IF('Summary Sheet'!$M$4="Plywood",VLOOKUP($B24,'Pwood & PB List'!$B$4:$V$158,10,FALSE),IF('Summary Sheet'!$M$4="PB w/ Wood Drawers",VLOOKUP($B24,'Pwood & PB List'!$B$4:$V$158,14,FALSE),IF('Summary Sheet'!$M$4="PB w/ PB Drawers",VLOOKUP($B24,'Pwood & PB List'!$B$4:$V$158,18,FALSE)))) -> 1285.7 | F24: =CONCATENATE("SLO-",B24) -> SLO-B33FD | G24: =IF('Summary Sheet'!$M$4="Plywood",VLOOKUP($B24,'Pwood & PB List'!$B$4:$V$158,11,FALSE),IF('Summary Sheet'!$M$4="PB w/ Wood Drawers",VLOOKUP($B24,'Pwood & PB List'!$B$4:$V$158,15,FALSE),IF('Summary Sheet'!$M$4="PB w/ PB Drawers",VLOOKUP($B24,'Pwood & PB List'!$B$4:$V$158,19,FALSE)))) -> 1232.11 | H24: =CONCATENATE("BLW-",B24) -> BLW-B33FD | I24: =IF('Summary Sheet'!$M$4="Plywood",VLOOKUP($B24,'Pwood & PB List'!$B$4:$V$158,10,FALSE),IF('Summary Sheet'!$M$4="PB w/ Wood Drawers",VLOOKUP($B24,'Pwood & PB List'!$B$4:$V$158,14,FALSE),IF('Summary Sheet'!$M$4="PB w/ PB Drawers",VLOOKUP($B24,'Pwood & PB List'!$B$4:$V$158,18,FALSE)))) -> 1285.7 | J24: =CONCATENATE("WEO-",B24) -> WEO-B33FD | K24: =IF('Summary Sheet'!$M$4="Plywood",VLOOKUP($B24,'Pwood & PB List'!$B$4:$V$158,9,FALSE),IF('Summary Sheet'!$M$4="PB w/ Wood Drawers",VLOOKUP($B24,'Pwood & PB List'!$B$4:$V$158,13,FALSE),IF('Summary Sheet'!$M$4="PB w/ PB Drawers",VLOOKUP($B24,'Pwood & PB List'!$B$4:$V$158,17,FALSE)))) -> 1335.955 | L24: =CONCATENATE("GLG-",B24) -> GLG-B33FD | M24: =IF('Summary Sheet'!$M$4="Plywood",VLOOKUP($B24,'Pwood & PB List'!$B$4:$V$158,12,FALSE),IF('Summary Sheet'!$M$4="PB w/ Wood Drawers",VLOOKUP($B24,'Pwood & PB List'!$B$4:$V$158,16,FALSE),IF('Summary Sheet'!$M$4="PB w/ PB Drawers",VLOOKUP($B24,'Pwood & PB List'!$B$4:$V$158,20,FALSE)))) -> 1171.735 | N24: =CONCATENATE("NAO-",B24) -> NAO-B33FD | O24: =IF('Summary Sheet'!$M$4="Plywood",VLOOKUP($B24,'Pwood & PB List'!$B$4:$V$158,12,FALSE),IF('Summary Sheet'!$M$4="PB w/ Wood Drawers",VLOOKUP($B24,'Pwood & PB List'!$B$4:$V$158,16,FALSE),IF('Summary Sheet'!$M$4="PB w/ PB Drawers",VLOOKUP($B24,'Pwood & PB List'!$B$4:$V$158,20,FALSE)))) -> 1171.735 | P24: =CONCATENATE("WHO-",B24) -> WHO-B33FD | Q24: =IF('Summary Sheet'!$M$4="Plywood",VLOOKUP($B24,'Pwood & PB List'!$B$4:$V$158,9,FALSE),IF('Summary Sheet'!$M$4="PB w/ Wood Drawers",VLOOKUP($B24,'Pwood & PB List'!$B$4:$V$158,13,FALSE),IF('Summary Sheet'!$M$4="PB w/ PB Drawers",VLOOKUP($B24,'Pwood & PB List'!$B$4:$V$158,17,FALSE)))) -> 1335.955 | R24: =CONCATENATE("MAW-",B24) -> MAW-B33FD | S24: =IF('Summary Sheet'!$M$4="Plywood",VLOOKUP($B24,'Pwood & PB List'!$B$4:$V$158,9,FALSE),IF('Summary Sheet'!$M$4="PB w/ Wood Drawers",VLOOKUP($B24,'Pwood & PB List'!$B$4:$V$158,13,FALSE),IF('Summary Sheet'!$M$4="PB w/ PB Drawers",VLOOKUP($B24,'Pwood & PB List'!$B$4:$V$158,17,FALSE)))) -> 1335.955 | T24: =CONCATENATE("MAG-",B24) -> MAG-B33FD | U24: =IF('Summary Sheet'!$M$4="Plywood",VLOOKUP($B24,'Pwood & PB List'!$B$4:$V$158,9,FALSE),IF('Summary Sheet'!$M$4="PB w/ Wood Drawers",VLOOKUP($B24,'Pwood & PB List'!$B$4:$V$158,13,FALSE),IF('Summary Sheet'!$M$4="PB w/ PB Drawers",VLOOKUP($B24,'Pwood & PB List'!$B$4:$V$158,17,FALSE)))) -> 1335.955 | V24: =CONCATENATE("MAB-",B24) -> MAB-B33FD | W24: =IF('Summary Sheet'!$M$4="Plywood",VLOOKUP($B24,'Pwood & PB List'!$B$4:$V$158,9,FALSE),IF('Summary Sheet'!$M$4="PB w/ Wood Drawers",VLOOKUP($B24,'Pwood & PB List'!$B$4:$V$158,13,FALSE),IF('Summary Sheet'!$M$4="PB w/ PB Drawers",VLOOKUP($B24,'Pwood & PB List'!$B$4:$V$158,17,FALSE)))) -> 1335.955 | X24: =CONCATENATE("GLB-",B24) -> GLB-B33FD | Y24: 2
A25: 36" Base Cabinet: 1 Full-Height Door | B25: B36FD | C25: =IF('Summary Sheet'!$M$4="Plywood",VLOOKUP($B25,'Pwood & PB List'!$B$4:$V$158,9,FALSE),IF('Summary Sheet'!$M$4="PB w/ Wood Drawers",VLOOKUP($B25,'Pwood & PB List'!$B$4:$V$158,13,FALSE),IF('Summary Sheet'!$M$4="PB w/ PB Drawers",VLOOKUP($B25,'Pwood & PB List'!$B$4:$V$158,17,FALSE)))) -> 1416.685 | D25: =CONCATENATE("GLW-",B25) -> GLW-B36FD | E25: =IF('Summary Sheet'!$M$4="Plywood",VLOOKUP($B25,'Pwood & PB List'!$B$4:$V$158,10,FALSE),IF('Summary Sheet'!$M$4="PB w/ Wood Drawers",VLOOKUP($B25,'Pwood & PB List'!$B$4:$V$158,14,FALSE),IF('Summary Sheet'!$M$4="PB w/ PB Drawers",VLOOKUP($B25,'Pwood & PB List'!$B$4:$V$158,18,FALSE)))) -> 1361.83 | F25: =CONCATENATE("SLO-",B25) -> SLO-B36FD | G25: =IF('Summary Sheet'!$M$4="Plywood",VLOOKUP($B25,'Pwood & PB List'!$B$4:$V$158,11,FALSE),IF('Summary Sheet'!$M$4="PB w/ Wood Drawers",VLOOKUP($B25,'Pwood & PB List'!$B$4:$V$158,15,FALSE),IF('Summary Sheet'!$M$4="PB w/ PB Drawers",VLOOKUP($B25,'Pwood & PB List'!$B$4:$V$158,19,FALSE)))) -> 1303.18 | H25: =CONCATENATE("BLW-",B25) -> BLW-B36FD | I25: =IF('Summary Sheet'!$M$4="Plywood",VLOOKUP($B25,'Pwood & PB List'!$B$4:$V$158,10,FALSE),IF('Summary Sheet'!$M$4="PB w/ Wood Drawers",VLOOKUP($B25,'Pwood & PB List'!$B$4:$V$158,14,FALSE),IF('Summary Sheet'!$M$4="PB w/ PB Drawers",VLOOKUP($B25,'Pwood & PB List'!$B$4:$V$158,18,FALSE)))) -> 1361.83 | J25: =CONCATENATE("WEO-",B25) -> WEO-B36FD | K25: =IF('Summary Sheet'!$M$4="Plywood",VLOOKUP($B25,'Pwood & PB List'!$B$4:$V$158,9,FALSE),IF('Summary Sheet'!$M$4="PB w/ Wood Drawers",VLOOKUP($B25,'Pwood & PB List'!$B$4:$V$158,13,FALSE),IF('Summary Sheet'!$M$4="PB w/ PB Drawers",VLOOKUP($B25,'Pwood & PB List'!$B$4:$V$158,17,FALSE)))) -> 1416.685 | L25: =CONCATENATE("GLG-",B25) -> GLG-B36FD | M25: =IF('Summary Sheet'!$M$4="Plywood",VLOOKUP($B25,'Pwood & PB List'!$B$4:$V$158,12,FALSE),IF('Summary Sheet'!$M$4="PB w/ Wood Drawers",VLOOKUP($B25,'Pwood & PB List'!$B$4:$V$158,16,FALSE),IF('Summary Sheet'!$M$4="PB w/ PB Drawers",VLOOKUP($B25,'Pwood & PB List'!$B$4:$V$158,20,FALSE)))) -> 1237.4 | N25: =CONCATENATE("NAO-",B25) -> NAO-B36FD | O25: =IF('Summary Sheet'!$M$4="Plywood",VLOOKUP($B25,'Pwood & PB List'!$B$4:$V$158,12,FALSE),IF('Summary Sheet'!$M$4="PB w/ Wood Drawers",VLOOKUP($B25,'Pwood & PB List'!$B$4:$V$158,16,FALSE),IF('Summary Sheet'!$M$4="PB w/ PB Drawers",VLOOKUP($B25,'Pwood & PB List'!$B$4:$V$158,20,FALSE)))) -> 1237.4 | P25: =CONCATENATE("WHO-",B25) -> WHO-B36FD | Q25: =IF('Summary Sheet'!$M$4="Plywood",VLOOKUP($B25,'Pwood & PB List'!$B$4:$V$158,9,FALSE),IF('Summary Sheet'!$M$4="PB w/ Wood Drawers",VLOOKUP($B25,'Pwood & PB List'!$B$4:$V$158,13,FALSE),IF('Summary Sheet'!$M$4="PB w/ PB Drawers",VLOOKUP($B25,'Pwood & PB List'!$B$4:$V$158,17,FALSE)))) -> 1416.685 | R25: =CONCATENATE("MAW-",B25) -> MAW-B36FD | S25: =IF('Summary Sheet'!$M$4="Plywood",VLOOKUP($B25,'Pwood & PB List'!$B$4:$V$158,9,FALSE),IF('Summary Sheet'!$M$4="PB w/ Wood Drawers",VLOOKUP($B25,'Pwood & PB List'!$B$4:$V$158,13,FALSE),IF('Summary Sheet'!$M$4="PB w/ PB Drawers",VLOOKUP($B25,'Pwood & PB List'!$B$4:$V$158,17,FALSE)))) -> 1416.685 | T25: =CONCATENATE("MAG-",B25) -> MAG-B36FD | U25: =IF('Summary Sheet'!$M$4="Plywood",VLOOKUP($B25,'Pwood & PB List'!$B$4:$V$158,9,FALSE),IF('Summary Sheet'!$M$4="PB w/ Wood Drawers",VLOOKUP($B25,'Pwood & PB List'!$B$4:$V$158,13,FALSE),IF('Summary Sheet'!$M$4="PB w/ PB Drawers",VLOOKUP($B25,'Pwood & PB List'!$B$4:$V$158,17,FALSE)))) -> 1416.685 | V25: =CONCATENATE("MAB-",B25) -> MAB-B36FD | W25: =IF('Summary Sheet'!$M$4="Plywood",VLOOKUP($B25,'Pwood & PB List'!$B$4:$V$158,9,FALSE),IF('Summary Sheet'!$M$4="PB w/ Wood Drawers",VLOOKUP($B25,'Pwood & PB List'!$B$4:$V$158,13,FALSE),IF('Summary Sheet'!$M$4="PB w/ PB Drawers",VLOOKUP($B25,'Pwood & PB List'!$B$4:$V$158,17,FALSE)))) -> 1416.685 | X25: =CONCATENATE("GLB-",B25) -> GLB-B36FD | Y25: 2
A26: Drawer Base Cabinets with 3 Drawers, 24" Depth
A27: 12" Drawer Base Cabinet: 3 Drawers | B27: 3DB12 | C27: =IF('Summary Sheet'!$M$4="Plywood",VLOOKUP($B27,'Pwood & PB List'!$B$4:$V$158,9,FALSE),IF('Summary Sheet'!$M$4="PB w/ Wood Drawers",VLOOKUP($B27,'Pwood & PB List'!$B$4:$V$158,13,FALSE),IF('Summary Sheet'!$M$4="PB w/ PB Drawers",VLOOKUP($B27,'Pwood & PB List'!$B$4:$V$158,17,FALSE)))) -> 1113.315 | D27: =CONCATENATE("GLW-",B27) -> GLW-3DB12 | E27: =IF('Summary Sheet'!$M$4="Plywood",VLOOKUP($B27,'Pwood & PB List'!$B$4:$V$158,10,FALSE),IF('Summary Sheet'!$M$4="PB w/ Wood Drawers",VLOOKUP($B27,'Pwood & PB List'!$B$4:$V$158,14,FALSE),IF('Summary Sheet'!$M$4="PB w/ PB Drawers",VLOOKUP($B27,'Pwood & PB List'!$B$4:$V$158,18,FALSE)))) -> 1095.145 | F27: =CONCATENATE("SLO-",B27) -> SLO-3DB12 | G27: =IF('Summary Sheet'!$M$4="Plywood",VLOOKUP($B27,'Pwood & PB List'!$B$4:$V$158,11,FALSE),IF('Summary Sheet'!$M$4="PB w/ Wood Drawers",VLOOKUP($B27,'Pwood & PB List'!$B$4:$V$158,15,FALSE),IF('Summary Sheet'!$M$4="PB w/ PB Drawers",VLOOKUP($B27,'Pwood & PB List'!$B$4:$V$158,19,FALSE)))) -> 1075.94 | H27: =CONCATENATE("BLW-",B27) -> BLW-3DB12 | I27: =IF('Summary Sheet'!$M$4="Plywood",VLOOKUP($B27,'Pwood & PB List'!$B$4:$V$158,10,FALSE),IF('Summary Sheet'!$M$4="PB w/ Wood Drawers",VLOOKUP($B27,'Pwood & PB List'!$B$4:$V$158,14,FALSE),IF('Summary Sheet'!$M$4="PB w/ PB Drawers",VLOOKUP($B27,'Pwood & PB List'!$B$4:$V$158,18,FALSE)))) -> 1095.145 | J27: =CONCATENATE("WEO-",B27) -> WEO-3DB12 | K27: =IF('Summary Sheet'!$M$4="Plywood",VLOOKUP($B27,'Pwood & PB List'!$B$4:$V$158,9,FALSE),IF('Summary Sheet'!$M$4="PB w/ Wood Drawers",VLOOKUP($B27,'Pwood & PB List'!$B$4:$V$158,13,FALSE),IF('Summary Sheet'!$M$4="PB w/ PB Drawers",VLOOKUP($B27,'Pwood & PB List'!$B$4:$V$158,17,FALSE)))) -> 1113.315 | L27: =CONCATENATE("GLG-",B27) -> GLG-3DB12 | M27: =IF('Summary Sheet'!$M$4="Plywood",VLOOKUP($B27,'Pwood & PB List'!$B$4:$V$158,12,FALSE),IF('Summary Sheet'!$M$4="PB w/ Wood Drawers",VLOOKUP($B27,'Pwood & PB List'!$B$4:$V$158,16,FALSE),IF('Summary Sheet'!$M$4="PB w/ PB Drawers",VLOOKUP($B27,'Pwood & PB List'!$B$4:$V$158,20,FALSE)))) -> 1054.205 | N27: =CONCATENATE("NAO-",B27) -> NAO-3DB12 | O27: =IF('Summary Sheet'!$M$4="Plywood",VLOOKUP($B27,'Pwood & PB List'!$B$4:$V$158,12,FALSE),IF('Summary Sheet'!$M$4="PB w/ Wood Drawers",VLOOKUP($B27,'Pwood & PB List'!$B$4:$V$158,16,FALSE),IF('Summary Sheet'!$M$4="PB w/ PB Drawers",VLOOKUP($B27,'Pwood & PB List'!$B$4:$V$158,20,FALSE)))) -> 1054.205 | P27: =CONCATENATE("WHO-",B27) -> WHO-3DB12 | Q27: =IF('Summary Sheet'!$M$4="Plywood",VLOOKUP($B27,'Pwood & PB List'!$B$4:$V$158,9,FALSE),IF('Summary Sheet'!$M$4="PB w/ Wood Drawers",VLOOKUP($B27,'Pwood & PB List'!$B$4:$V$158,13,FALSE),IF('Summary Sheet'!$M$4="PB w/ PB Drawers",VLOOKUP($B27,'Pwood & PB List'!$B$4:$V$158,17,FALSE)))) -> 1113.315 | R27: =CONCATENATE("MAW-",B27) -> MAW-3DB12 | S27: =IF('Summary Sheet'!$M$4="Plywood",VLOOKUP($B27,'Pwood & PB List'!$B$4:$V$158,9,FALSE),IF('Summary Sheet'!$M$4="PB w/ Wood Drawers",VLOOKUP($B27,'Pwood & PB List'!$B$4:$V$158,13,FALSE),IF('Summary Sheet'!$M$4="PB w/ PB Drawers",VLOOKUP($B27,'Pwood & PB List'!$B$4:$V$158,17,FALSE)))) -> 1113.315 | T27: =CONCATENATE("MAG-",B27) -> MAG-3DB12 | U27: =IF('Summary Sheet'!$M$4="Plywood",VLOOKUP($B27,'Pwood & PB List'!$B$4:$V$158,9,FALSE),IF('Summary Sheet'!$M$4="PB w/ Wood Drawers",VLOOKUP($B27,'Pwood & PB List'!$B$4:$V$158,13,FALSE),IF('Summary Sheet'!$M$4="PB w/ PB Drawers",VLOOKUP($B27,'Pwood & PB List'!$B$4:$V$158,17,FALSE)))) -> 1113.315 | V27: =CONCATENATE("MAB-",B27) -> MAB-3DB12 | W27: =IF('Summary Sheet'!$M$4="Plywood",VLOOKUP($B27,'Pwood & PB List'!$B$4:$V$158,9,FALSE),IF('Summary Sheet'!$M$4="PB w/ Wood Drawers",VLOOKUP($B27,'Pwood & PB List'!$B$4:$V$158,13,FALSE),IF('Summary Sheet'!$M$4="PB w/ PB Drawers",VLOOKUP($B27,'Pwood & PB List'!$B$4:$V$158,17,FALSE)))) -> 1113.315 | X27: =CONCATENATE("GLB-",B27) -> GLB-3DB12 | Y27: 3
A28: 15" Drawer Base Cabinet: 3 Drawers | B28: 3DB15 | C28: =IF('Summary Sheet'!$M$4="Plywood",VLOOKUP($B28,'Pwood & PB List'!$B$4:$V$158,9,FALSE),IF('Summary Sheet'!$M$4="PB w/ Wood Drawers",VLOOKUP($B28,'Pwood & PB List'!$B$4:$V$158,13,FALSE),IF('Summary Sheet'!$M$4="PB w/ PB Drawers",VLOOKUP($B28,'Pwood & PB List'!$B$4:$V$158,17,FALSE)))) -> 1213.135 | D28: =CONCATENATE("GLW-",B28) -> GLW-3DB15 | E28: =IF('Summary Sheet'!$M$4="Plywood",VLOOKUP($B28,'Pwood & PB List'!$B$4:$V$158,10,FALSE),IF('Summary Sheet'!$M$4="PB w/ Wood Drawers",VLOOKUP($B28,'Pwood & PB List'!$B$4:$V$158,14,FALSE),IF('Summary Sheet'!$M$4="PB w/ PB Drawers",VLOOKUP($B28,'Pwood & PB List'!$B$4:$V$158,18,FALSE)))) -> 1190.365 | F28: =CONCATENATE("SLO-",B28) -> SLO-3DB15 | G28: =IF('Summary Sheet'!$M$4="Plywood",VLOOKUP($B28,'Pwood & PB List'!$B$4:$V$158,11,FALSE),IF('Summary Sheet'!$M$4="PB w/ Wood Drawers",VLOOKUP($B28,'Pwood & PB List'!$B$4:$V$158,15,FALSE),IF('Summary Sheet'!$M$4="PB w/ PB Drawers",VLOOKUP($B28,'Pwood & PB List'!$B$4:$V$158,19,FALSE)))) -> 1166.215 | H28: =CONCATENATE("BLW-",B28) -> BLW-3DB15 | I28: =IF('Summary Sheet'!$M$4="Plywood",VLOOKUP($B28,'Pwood & PB List'!$B$4:$V$158,10,FALSE),IF('Summary Sheet'!$M$4="PB w/ Wood Drawers",VLOOKUP($B28,'Pwood & PB List'!$B$4:$V$158,14,FALSE),IF('Summary Sheet'!$M$4="PB w/ PB Drawers",VLOOKUP($B28,'Pwood & PB List'!$B$4:$V$158,18,FALSE)))) -> 1190.365 | J28: =CONCATENATE("WEO-",B28) -> WEO-3DB15 | K28: =IF('Summary Sheet'!$M$4="Plywood",VLOOKUP($B28,'Pwood & PB List'!$B$4:$V$158,9,FALSE),IF('Summary Sheet'!$M$4="PB w/ Wood Drawers",VLOOKUP($B28,'Pwood & PB List'!$B$4:$V$158,13,FALSE),IF('Summary Sheet'!$M$4="PB w/ PB Drawers",VLOOKUP($B28,'Pwood & PB List'!$B$4:$V$158,17,FALSE)))) -> 1213.135 | L28: =CONCATENATE("GLG-",B28) -> GLG-3DB15 | M28: =IF('Summary Sheet'!$M$4="Plywood",VLOOKUP($B28,'Pwood & PB List'!$B$4:$V$158,12,FALSE),IF('Summary Sheet'!$M$4="PB w/ Wood Drawers",VLOOKUP($B28,'Pwood & PB List'!$B$4:$V$158,16,FALSE),IF('Summary Sheet'!$M$4="PB w/ PB Drawers",VLOOKUP($B28,'Pwood & PB List'!$B$4:$V$158,20,FALSE)))) -> 1139.075 | N28: =CONCATENATE("NAO-",B28) -> NAO-3DB15 | O28: =IF('Summary Sheet'!$M$4="Plywood",VLOOKUP($B28,'Pwood & PB List'!$B$4:$V$158,12,FALSE),IF('Summary Sheet'!$M$4="PB w/ Wood Drawers",VLOOKUP($B28,'Pwood & PB List'!$B$4:$V$158,16,FALSE),IF('Summary Sheet'!$M$4="PB w/ PB Drawers",VLOOKUP($B28,'Pwood & PB List'!$B$4:$V$158,20,FALSE)))) -> 1139.075 | P28: =CONCATENATE("WHO-",B28) -> WHO-3DB15 | Q28: =IF('Summary Sheet'!$M$4="Plywood",VLOOKUP($B28,'Pwood & PB List'!$B$4:$V$158,9,FALSE),IF('Summary Sheet'!$M$4="PB w/ Wood Drawers",VLOOKUP($B28,'Pwood & PB List'!$B$4:$V$158,13,FALSE),IF('Summary Sheet'!$M$4="PB w/ PB Drawers",VLOOKUP($B28,'Pwood & PB List'!$B$4:$V$158,17,FALSE)))) -> 1213.135 | R28: =CONCATENATE("MAW-",B28) -> MAW-3DB15 | S28: =IF('Summary Sheet'!$M$4="Plywood",VLOOKUP($B28,'Pwood & PB List'!$B$4:$V$158,9,FALSE),IF('Summary Sheet'!$M$4="PB w/ Wood Drawers",VLOOKUP($B28,'Pwood & PB List'!$B$4:$V$158,13,FALSE),IF('Summary Sheet'!$M$4="PB w/ PB Drawers",VLOOKUP($B28,'Pwood & PB List'!$B$4:$V$158,17,FALSE)))) -> 1213.135 | T28: =CONCATENATE("MAG-",B28) -> MAG-3DB15 | U28: =IF('Summary Sheet'!$M$4="Plywood",VLOOKUP($B28,'Pwood & PB List'!$B$4:$V$158,9,FALSE),IF('Summary Sheet'!$M$4="PB w/ Wood Drawers",VLOOKUP($B28,'Pwood & PB List'!$B$4:$V$158,13,FALSE),IF('Summary Sheet'!$M$4="PB w/ PB Drawers",VLOOKUP($B28,'Pwood & PB List'!$B$4:$V$158,17,FALSE)))) -> 1213.135 | V28: =CONCATENATE("MAB-",B28) -> MAB-3DB15 | W28: =IF('Summary Sheet'!$M$4="Plywood",VLOOKUP($B28,'Pwood & PB List'!$B$4:$V$158,9,FALSE),IF('Summary Sheet'!$M$4="PB w/ Wood Drawers",VLOOKUP($B28,'Pwood & PB List'!$B$4:$V$158,13,FALSE),IF('Summary Sheet'!$M$4="PB w/ PB Drawers",VLOOKUP($B28,'Pwood & PB List'!$B$4:$V$158,17,FALSE)))) -> 1213.135 | X28: =CONCATENATE("GLB-",B28) -> GLB-3DB15 | Y28: 3
A29: 18" Drawer Base Cabinet: 3 Drawers | B29: 3DB18 | C29: =IF('Summary Sheet'!$M$4="Plywood",VLOOKUP($B29,'Pwood & PB List'!$B$4:$V$158,9,FALSE),IF('Summary Sheet'!$M$4="PB w/ Wood Drawers",VLOOKUP($B29,'Pwood & PB List'!$B$4:$V$158,13,FALSE),IF('Summary Sheet'!$M$4="PB w/ PB Drawers",VLOOKUP($B29,'Pwood & PB List'!$B$4:$V$158,17,FALSE)))) -> 1312.725 | D29: =CONCATENATE("GLW-",B29) -> GLW-3DB18 | E29: =IF('Summary Sheet'!$M$4="Plywood",VLOOKUP($B29,'Pwood & PB List'!$B$4:$V$158,10,FALSE),IF('Summary Sheet'!$M$4="PB w/ Wood Drawers",VLOOKUP($B29,'Pwood & PB List'!$B$4:$V$158,14,FALSE),IF('Summary Sheet'!$M$4="PB w/ PB Drawers",VLOOKUP($B29,'Pwood & PB List'!$B$4:$V$158,18,FALSE)))) -> 1285.47 | F29: =CONCATENATE("SLO-",B29) -> SLO-3DB18 | G29: =IF('Summary Sheet'!$M$4="Plywood",VLOOKUP($B29,'Pwood & PB List'!$B$4:$V$158,11,FALSE),IF('Summary Sheet'!$M$4="PB w/ Wood Drawers",VLOOKUP($B29,'Pwood & PB List'!$B$4:$V$158,15,FALSE),IF('Summary Sheet'!$M$4="PB w/ PB Drawers",VLOOKUP($B29,'Pwood & PB List'!$B$4:$V$158,19,FALSE)))) -> 1256.49 | H29: =CONCATENATE("BLW-",B29) -> BLW-3DB18 | I29: =IF('Summary Sheet'!$M$4="Plywood",VLOOKUP($B29,'Pwood & PB List'!$B$4:$V$158,10,FALSE),IF('Summary Sheet'!$M$4="PB w/ Wood Drawers",VLOOKUP($B29,'Pwood & PB List'!$B$4:$V$158,14,FALSE),IF('Summary Sheet'!$M$4="PB w/ PB Drawers",VLOOKUP($B29,'Pwood & PB List'!$B$4:$V$158,18,FALSE)))) -> 1285.47 | J29: =CONCATENATE("WEO-",B29) -> WEO-3DB18 | K29: =IF('Summary Sheet'!$M$4="Plywood",VLOOKUP($B29,'Pwood & PB List'!$B$4:$V$158,9,FALSE),IF('Summary Sheet'!$M$4="PB w/ Wood Drawers",VLOOKUP($B29,'Pwood & PB List'!$B$4:$V$158,13,FALSE),IF('Summary Sheet'!$M$4="PB w/ PB Drawers",VLOOKUP($B29,'Pwood & PB List'!$B$4:$V$158,17,FALSE)))) -> 1312.725 | L29: =CONCATENATE("GLG-",B29) -> GLG-3DB18 | M29: =IF('Summary Sheet'!$M$4="Plywood",VLOOKUP($B29,'Pwood & PB List'!$B$4:$V$158,12,FALSE),IF('Summary Sheet'!$M$4="PB w/ Wood Drawers",VLOOKUP($B29,'Pwood & PB List'!$B$4:$V$158,16,FALSE),IF('Summary Sheet'!$M$4="PB w/ PB Drawers",VLOOKUP($B29,'Pwood & PB List'!$B$4:$V$158,20,FALSE)))) -> 1223.83 | N29: =CONCATENATE("NAO-",B29) -> NAO-3DB18 | O29: =IF('Summary Sheet'!$M$4="Plywood",VLOOKUP($B29,'Pwood & PB List'!$B$4:$V$158,12,FALSE),IF('Summary Sheet'!$M$4="PB w/ Wood Drawers",VLOOKUP($B29,'Pwood & PB List'!$B$4:$V$158,16,FALSE),IF('Summary Sheet'!$M$4="PB w/ PB Drawers",VLOOKUP($B29,'Pwood & PB List'!$B$4:$V$158,20,FALSE)))) -> 1223.83 | P29: =CONCATENATE("WHO-",B29) -> WHO-3DB18 | Q29: =IF('Summary Sheet'!$M$4="Plywood",VLOOKUP($B29,'Pwood & PB List'!$B$4:$V$158,9,FALSE),IF('Summary Sheet'!$M$4="PB w/ Wood Drawers",VLOOKUP($B29,'Pwood & PB List'!$B$4:$V$158,13,FALSE),IF('Summary Sheet'!$M$4="PB w/ PB Drawers",VLOOKUP($B29,'Pwood & PB List'!$B$4:$V$158,17,FALSE)))) -> 1312.725 | R29: =CONCATENATE("MAW-",B29) -> MAW-3DB18 | S29: =IF('Summary Sheet'!$M$4="Plywood",VLOOKUP($B29,'Pwood & PB List'!$B$4:$V$158,9,FALSE),IF('Summary Sheet'!$M$4="PB w/ Wood Drawers",VLOOKUP($B29,'Pwood & PB List'!$B$4:$V$158,13,FALSE),IF('Summary Sheet'!$M$4="PB w/ PB Drawers",VLOOKUP($B29,'Pwood & PB List'!$B$4:$V$158,17,FALSE)))) -> 1312.725 | T29: =CONCATENATE("MAG-",B29) -> MAG-3DB18 | U29: =IF('Summary Sheet'!$M$4="Plywood",VLOOKUP($B29,'Pwood & PB List'!$B$4:$V$158,9,FALSE),IF('Summary Sheet'!$M$4="PB w/ Wood Drawers",VLOOKUP($B29,'Pwood & PB List'!$B$4:$V$158,13,FALSE),IF('Summary Sheet'!$M$4="PB w/ PB Drawers",VLOOKUP($B29,'Pwood & PB List'!$B$4:$V$158,17,FALSE)))) -> 1312.725 | V29: =CONCATENATE("MAB-",B29) -> MAB-3DB18 | W29: =IF('Summary Sheet'!$M$4="Plywood",VLOOKUP($B29,'Pwood & PB List'!$B$4:$V$158,9,FALSE),IF('Summary Sheet'!$M$4="PB w/ Wood Drawers",VLOOKUP($B29,'Pwood & PB List'!$B$4:$V$158,13,FALSE),IF('Summary Sheet'!$M$4="PB w/ PB Drawers",VLOOKUP($B29,'Pwood & PB List'!$B$4:$V$158,17,FALSE)))) -> 1312.725 | X29: =CONCATENATE("GLB-",B29) -> GLB-3DB18 | Y29: 3
A30: 21" Drawer Base Cabinet: 3 Drawers | B30: 3DB21 | C30: =IF('Summary Sheet'!$M$4="Plywood",VLOOKUP($B30,'Pwood & PB List'!$B$4:$V$158,9,FALSE),IF('Summary Sheet'!$M$4="PB w/ Wood Drawers",VLOOKUP($B30,'Pwood & PB List'!$B$4:$V$158,13,FALSE),IF('Summary Sheet'!$M$4="PB w/ PB Drawers",VLOOKUP($B30,'Pwood & PB List'!$B$4:$V$158,17,FALSE)))) -> 1412.43 | D30: =CONCATENATE("GLW-",B30) -> GLW-3DB21 | E30: =IF('Summary Sheet'!$M$4="Plywood",VLOOKUP($B30,'Pwood & PB List'!$B$4:$V$158,10,FALSE),IF('Summary Sheet'!$M$4="PB w/ Wood Drawers",VLOOKUP($B30,'Pwood & PB List'!$B$4:$V$158,14,FALSE),IF('Summary Sheet'!$M$4="PB w/ PB Drawers",VLOOKUP($B30,'Pwood & PB List'!$B$4:$V$158,18,FALSE)))) -> 1380.575 | F30: =CONCATENATE("SLO-",B30) -> SLO-3DB21 | G30: =IF('Summary Sheet'!$M$4="Plywood",VLOOKUP($B30,'Pwood & PB List'!$B$4:$V$158,11,FALSE),IF('Summary Sheet'!$M$4="PB w/ Wood Drawers",VLOOKUP($B30,'Pwood & PB List'!$B$4:$V$158,15,FALSE),IF('Summary Sheet'!$M$4="PB w/ PB Drawers",VLOOKUP($B30,'Pwood & PB List'!$B$4:$V$158,19,FALSE)))) -> 1346.65 | H30: =CONCATENATE("BLW-",B30) -> BLW-3DB21 | I30: =IF('Summary Sheet'!$M$4="Plywood",VLOOKUP($B30,'Pwood & PB List'!$B$4:$V$158,10,FALSE),IF('Summary Sheet'!$M$4="PB w/ Wood Drawers",VLOOKUP($B30,'Pwood & PB List'!$B$4:$V$158,14,FALSE),IF('Summary Sheet'!$M$4="PB w/ PB Drawers",VLOOKUP($B30,'Pwood & PB List'!$B$4:$V$158,18,FALSE)))) -> 1380.575 | J30: =CONCATENATE("WEO-",B30) -> WEO-3DB21 | K30: =IF('Summary Sheet'!$M$4="Plywood",VLOOKUP($B30,'Pwood & PB List'!$B$4:$V$158,9,FALSE),IF('Summary Sheet'!$M$4="PB w/ Wood Drawers",VLOOKUP($B30,'Pwood & PB List'!$B$4:$V$158,13,FALSE),IF('Summary Sheet'!$M$4="PB w/ PB Drawers",VLOOKUP($B30,'Pwood & PB List'!$B$4:$V$158,17,FALSE)))) -> 1412.43 | L30: =CONCATENATE("GLG-",B30) -> GLG-3DB21 | M30: =IF('Summary Sheet'!$M$4="Plywood",VLOOKUP($B30,'Pwood & PB List'!$B$4:$V$158,12,FALSE),IF('Summary Sheet'!$M$4="PB w/ Wood Drawers",VLOOKUP($B30,'Pwood & PB List'!$B$4:$V$158,16,FALSE),IF('Summary Sheet'!$M$4="PB w/ PB Drawers",VLOOKUP($B30,'Pwood & PB List'!$B$4:$V$158,20,FALSE)))) -> 1308.47 | N30: =CONCATENATE("NAO-",B30) -> NAO-3DB21 | O30: =IF('Summary Sheet'!$M$4="Plywood",VLOOKUP($B30,'Pwood & PB List'!$B$4:$V$158,12,FALSE),IF('Summary Sheet'!$M$4="PB w/ Wood Drawers",VLOOKUP($B30,'Pwood & PB List'!$B$4:$V$158,16,FALSE),IF('Summary Sheet'!$M$4="PB w/ PB Drawers",VLOOKUP($B30,'Pwood & PB List'!$B$4:$V$158,20,FALSE)))) -> 1308.47 | P30: =CONCATENATE("WHO-",B30) -> WHO-3DB21 | Q30: =IF('Summary Sheet'!$M$4="Plywood",VLOOKUP($B30,'Pwood & PB List'!$B$4:$V$158,9,FALSE),IF('Summary Sheet'!$M$4="PB w/ Wood Drawers",VLOOKUP($B30,'Pwood & PB List'!$B$4:$V$158,13,FALSE),IF('Summary Sheet'!$M$4="PB w/ PB Drawers",VLOOKUP($B30,'Pwood & PB List'!$B$4:$V$158,17,FALSE)))) -> 1412.43 | R30: =CONCATENATE("MAW-",B30) -> MAW-3DB21 | S30: =IF('Summary Sheet'!$M$4="Plywood",VLOOKUP($B30,'Pwood & PB List'!$B$4:$V$158,9,FALSE),IF('Summary Sheet'!$M$4="PB w/ Wood Drawers",VLOOKUP($B30,'Pwood & PB List'!$B$4:$V$158,13,FALSE),IF('Summary Sheet'!$M$4="PB w/ PB Drawers",VLOOKUP($B30,'Pwood & PB List'!$B$4:$V$158,17,FALSE)))) -> 1412.43 | T30: =CONCATENATE("MAG-",B30) -> MAG-3DB21 | U30: =IF('Summary Sheet'!$M$4="Plywood",VLOOKUP($B30,'Pwood & PB List'!$B$4:$V$158,9,FALSE),IF('Summary Sheet'!$M$4="PB w/ Wood Drawers",VLOOKUP($B30,'Pwood & PB List'!$B$4:$V$158,13,FALSE),IF('Summary Sheet'!$M$4="PB w/ PB Drawers",VLOOKUP($B30,'Pwood & PB List'!$B$4:$V$158,17,FALSE)))) -> 1412.43 | V30: =CONCATENATE("MAB-",B30) -> MAB-3DB21 | W30: =IF('Summary Sheet'!$M$4="Plywood",VLOOKUP($B30,'Pwood & PB List'!$B$4:$V$158,9,FALSE),IF('Summary Sheet'!$M$4="PB w/ Wood Drawers",VLOOKUP($B30,'Pwood & PB List'!$B$4:$V$158,13,FALSE),IF('Summary Sheet'!$M$4="PB w/ PB Drawers",VLOOKUP($B30,'Pwood & PB List'!$B$4:$V$158,17,FALSE)))) -> 1412.43 | X30: =CONCATENATE("GLB-",B30) -> GLB-3DB21 | Y30: 3
A31: 24" Drawer Base Cabinet: 3 Drawers | B31: 3DB24 | C31: =IF('Summary Sheet'!$M$4="Plywood",VLOOKUP($B31,'Pwood & PB List'!$B$4:$V$158,9,FALSE),IF('Summary Sheet'!$M$4="PB w/ Wood Drawers",VLOOKUP($B31,'Pwood & PB List'!$B$4:$V$158,13,FALSE),IF('Summary Sheet'!$M$4="PB w/ PB Drawers",VLOOKUP($B31,'Pwood & PB List'!$B$4:$V$158,17,FALSE)))) -> 1512.25 | D31: =CONCATENATE("GLW-",B31) -> GLW-3DB24 | E31: =IF('Summary Sheet'!$M$4="Plywood",VLOOKUP($B31,'Pwood & PB List'!$B$4:$V$158,10,FALSE),IF('Summary Sheet'!$M$4="PB w/ Wood Drawers",VLOOKUP($B31,'Pwood & PB List'!$B$4:$V$158,14,FALSE),IF('Summary Sheet'!$M$4="PB w/ PB Drawers",VLOOKUP($B31,'Pwood & PB List'!$B$4:$V$158,18,FALSE)))) -> 1475.795 | F31: =CONCATENATE("SLO-",B31) -> SLO-3DB24 | G31: =IF('Summary Sheet'!$M$4="Plywood",VLOOKUP($B31,'Pwood & PB List'!$B$4:$V$158,11,FALSE),IF('Summary Sheet'!$M$4="PB w/ Wood Drawers",VLOOKUP($B31,'Pwood & PB List'!$B$4:$V$158,15,FALSE),IF('Summary Sheet'!$M$4="PB w/ PB Drawers",VLOOKUP($B31,'Pwood & PB List'!$B$4:$V$158,19,FALSE)))) -> 1437.04 | H31: =CONCATENATE("BLW-",B31) -> BLW-3DB24 | I31: =IF('Summary Sheet'!$M$4="Plywood",VLOOKUP($B31,'Pwood & PB List'!$B$4:$V$158,10,FALSE),IF('Summary Sheet'!$M$4="PB w/ Wood Drawers",VLOOKUP($B31,'Pwood & PB List'!$B$4:$V$158,14,FALSE),IF('Summary Sheet'!$M$4="PB w/ PB Drawers",VLOOKUP($B31,'Pwood & PB List'!$B$4:$V$158,18,FALSE)))) -> 1475.795 | J31: =CONCATENATE("WEO-",B31) -> WEO-3DB24 | K31: =IF('Summary Sheet'!$M$4="Plywood",VLOOKUP($B31,'Pwood & PB List'!$B$4:$V$158,9,FALSE),IF('Summary Sheet'!$M$4="PB w/ Wood Drawers",VLOOKUP($B31,'Pwood & PB List'!$B$4:$V$158,13,FALSE),IF('Summary Sheet'!$M$4="PB w/ PB Drawers",VLOOKUP($B31,'Pwood & PB List'!$B$4:$V$158,17,FALSE)))) -> 1512.25 | L31: =CONCATENATE("GLG-",B31) -> GLG-3DB24 | M31: =IF('Summary Sheet'!$M$4="Plywood",VLOOKUP($B31,'Pwood & PB List'!$B$4:$V$158,12,FALSE),IF('Summary Sheet'!$M$4="PB w/ Wood Drawers",VLOOKUP($B31,'Pwood & PB List'!$B$4:$V$158,16,FALSE),IF('Summary Sheet'!$M$4="PB w/ PB Drawers",VLOOKUP($B31,'Pwood & PB List'!$B$4:$V$158,20,FALSE)))) -> 1393.34 | N31: =CONCATENATE("NAO-",B31) -> NAO-3DB24 | O31: =IF('Summary Sheet'!$M$4="Plywood",VLOOKUP($B31,'Pwood & PB List'!$B$4:$V$158,12,FALSE),IF('Summary Sheet'!$M$4="PB w/ Wood Drawers",VLOOKUP($B31,'Pwood & PB List'!$B$4:$V$158,16,FALSE),IF('Summary Sheet'!$M$4="PB w/ PB Drawers",VLOOKUP($B31,'Pwood & PB List'!$B$4:$V$158,20,FALSE)))) -> 1393.34 | P31: =CONCATENATE("WHO-",B31) -> WHO-3DB24 | Q31: =IF('Summary Sheet'!$M$4="Plywood",VLOOKUP($B31,'Pwood & PB List'!$B$4:$V$158,9,FALSE),IF('Summary Sheet'!$M$4="PB w/ Wood Drawers",VLOOKUP($B31,'Pwood & PB List'!$B$4:$V$158,13,FALSE),IF('Summary Sheet'!$M$4="PB w/ PB Drawers",VLOOKUP($B31,'Pwood & PB List'!$B$4:$V$158,17,FALSE)))) -> 1512.25 | R31: =CONCATENATE("MAW-",B31) -> MAW-3DB24 | S31: =IF('Summary Sheet'!$M$4="Plywood",VLOOKUP($B31,'Pwood & PB List'!$B$4:$V$158,9,FALSE),IF('Summary Sheet'!$M$4="PB w/ Wood Drawers",VLOOKUP($B31,'Pwood & PB List'!$B$4:$V$158,13,FALSE),IF('Summary Sheet'!$M$4="PB w/ PB Drawers",VLOOKUP($B31,'Pwood & PB List'!$B$4:$V$158,17,FALSE)))) -> 1512.25 | T31: =CONCATENATE("MAG-",B31) -> MAG-3DB24 | U31: =IF('Summary Sheet'!$M$4="Plywood",VLOOKUP($B31,'Pwood & PB List'!$B$4:$V$158,9,FALSE),IF('Summary Sheet'!$M$4="PB w/ Wood Drawers",VLOOKUP($B31,'Pwood & PB List'!$B$4:$V$158,13,FALSE),IF('Summary Sheet'!$M$4="PB w/ PB Drawers",VLOOKUP($B31,'Pwood & PB List'!$B$4:$V$158,17,FALSE)))) -> 1512.25 | V31: =CONCATENATE("MAB-",B31) -> MAB-3DB24 | W31: =IF('Summary Sheet'!$M$4="Plywood",VLOOKUP($B31,'Pwood & PB List'!$B$4:$V$158,9,FALSE),IF('Summary Sheet'!$M$4="PB w/ Wood Drawers",VLOOKUP($B31,'Pwood & PB List'!$B$4:$V$158,13,FALSE),IF('Summary Sheet'!$M$4="PB w/ PB Drawers",VLOOKUP($B31,'Pwood & PB List'!$B$4:$V$158,17,FALSE)))) -> 1512.25 | X31: =CONCATENATE("GLB-",B31) -> GLB-3DB24 | Y31: 3
A32: 27" Drawer Base Cabinet: 3 Drawers | B32: 3DB27 | C32: =IF('Summary Sheet'!$M$4="Plywood",VLOOKUP($B32,'Pwood & PB List'!$B$4:$V$158,9,FALSE),IF('Summary Sheet'!$M$4="PB w/ Wood Drawers",VLOOKUP($B32,'Pwood & PB List'!$B$4:$V$158,13,FALSE),IF('Summary Sheet'!$M$4="PB w/ PB Drawers",VLOOKUP($B32,'Pwood & PB List'!$B$4:$V$158,17,FALSE)))) -> 1611.84 | D32: =CONCATENATE("GLW-",B32) -> GLW-3DB27 | E32: =IF('Summary Sheet'!$M$4="Plywood",VLOOKUP($B32,'Pwood & PB List'!$B$4:$V$158,10,FALSE),IF('Summary Sheet'!$M$4="PB w/ Wood Drawers",VLOOKUP($B32,'Pwood & PB List'!$B$4:$V$158,14,FALSE),IF('Summary Sheet'!$M$4="PB w/ PB Drawers",VLOOKUP($B32,'Pwood & PB List'!$B$4:$V$158,18,FALSE)))) -> 1570.785 | F32: =CONCATENATE("SLO-",B32) -> SLO-3DB27 | G32: =IF('Summary Sheet'!$M$4="Plywood",VLOOKUP($B32,'Pwood & PB List'!$B$4:$V$158,11,FALSE),IF('Summary Sheet'!$M$4="PB w/ Wood Drawers",VLOOKUP($B32,'Pwood & PB List'!$B$4:$V$158,15,FALSE),IF('Summary Sheet'!$M$4="PB w/ PB Drawers",VLOOKUP($B32,'Pwood & PB List'!$B$4:$V$158,19,FALSE)))) -> 1527.2 | H32: =CONCATENATE("BLW-",B32) -> BLW-3DB27 | I32: =IF('Summary Sheet'!$M$4="Plywood",VLOOKUP($B32,'Pwood & PB List'!$B$4:$V$158,10,FALSE),IF('Summary Sheet'!$M$4="PB w/ Wood Drawers",VLOOKUP($B32,'Pwood & PB List'!$B$4:$V$158,14,FALSE),IF('Summary Sheet'!$M$4="PB w/ PB Drawers",VLOOKUP($B32,'Pwood & PB List'!$B$4:$V$158,18,FALSE)))) -> 1570.785 | J32: =CONCATENATE("WEO-",B32) -> WEO-3DB27 | K32: =IF('Summary Sheet'!$M$4="Plywood",VLOOKUP($B32,'Pwood & PB List'!$B$4:$V$158,9,FALSE),IF('Summary Sheet'!$M$4="PB w/ Wood Drawers",VLOOKUP($B32,'Pwood & PB List'!$B$4:$V$158,13,FALSE),IF('Summary Sheet'!$M$4="PB w/ PB Drawers",VLOOKUP($B32,'Pwood & PB List'!$B$4:$V$158,17,FALSE)))) -> 1611.84 | L32: =CONCATENATE("GLG-",B32) -> GLG-3DB27 | M32: =IF('Summary Sheet'!$M$4="Plywood",VLOOKUP($B32,'Pwood & PB List'!$B$4:$V$158,12,FALSE),IF('Summary Sheet'!$M$4="PB w/ Wood Drawers",VLOOKUP($B32,'Pwood & PB List'!$B$4:$V$158,16,FALSE),IF('Summary Sheet'!$M$4="PB w/ PB Drawers",VLOOKUP($B32,'Pwood & PB List'!$B$4:$V$158,20,FALSE)))) -> 1477.98 | N32: =CONCATENATE("NAO-",B32) -> NAO-3DB27 | O32: =IF('Summary Sheet'!$M$4="Plywood",VLOOKUP($B32,'Pwood & PB List'!$B$4:$V$158,12,FALSE),IF('Summary Sheet'!$M$4="PB w/ Wood Drawers",VLOOKUP($B32,'Pwood & PB List'!$B$4:$V$158,16,FALSE),IF('Summary Sheet'!$M$4="PB w/ PB Drawers",VLOOKUP($B32,'Pwood & PB List'!$B$4:$V$158,20,FALSE)))) -> 1477.98 | P32: =CONCATENATE("WHO-",B32) -> WHO-3DB27 | Q32: =IF('Summary Sheet'!$M$4="Plywood",VLOOKUP($B32,'Pwood & PB List'!$B$4:$V$158,9,FALSE),IF('Summary Sheet'!$M$4="PB w/ Wood Drawers",VLOOKUP($B32,'Pwood & PB List'!$B$4:$V$158,13,FALSE),IF('Summary Sheet'!$M$4="PB w/ PB Drawers",VLOOKUP($B32,'Pwood & PB List'!$B$4:$V$158,17,FALSE)))) -> 1611.84 | R32: =CONCATENATE("MAW-",B32) -> MAW-3DB27 | S32: =IF('Summary Sheet'!$M$4="Plywood",VLOOKUP($B32,'Pwood & PB List'!$B$4:$V$158,9,FALSE),IF('Summary Sheet'!$M$4="PB w/ Wood Drawers",VLOOKUP($B32,'Pwood & PB List'!$B$4:$V$158,13,FALSE),IF('Summary Sheet'!$M$4="PB w/ PB Drawers",VLOOKUP($B32,'Pwood & PB List'!$B$4:$V$158,17,FALSE)))) -> 1611.84 | T32: =CONCATENATE("MAG-",B32) -> MAG-3DB27 | U32: =IF('Summary Sheet'!$M$4="Plywood",VLOOKUP($B32,'Pwood & PB List'!$B$4:$V$158,9,FALSE),IF('Summary Sheet'!$M$4="PB w/ Wood Drawers",VLOOKUP($B32,'Pwood & PB List'!$B$4:$V$158,13,FALSE),IF('Summary Sheet'!$M$4="PB w/ PB Drawers",VLOOKUP($B32,'Pwood & PB List'!$B$4:$V$158,17,FALSE)))) -> 1611.84 | V32: =CONCATENATE("MAB-",B32) -> MAB-3DB27 | W32: =IF('Summary Sheet'!$M$4="Plywood",VLOOKUP($B32,'Pwood & PB List'!$B$4:$V$158,9,FALSE),IF('Summary Sheet'!$M$4="PB w/ Wood Drawers",VLOOKUP($B32,'Pwood & PB List'!$B$4:$V$158,13,FALSE),IF('Summary Sheet'!$M$4="PB w/ PB Drawers",VLOOKUP($B32,'Pwood & PB List'!$B$4:$V$158,17,FALSE)))) -> 1611.84 | X32: =CONCATENATE("GLB-",B32) -> GLB-3DB27 | Y32: 3
A33: 30" Drawer Base Cabinet: 3 Drawers | B33: 3DB30 | C33: =IF('Summary Sheet'!$M$4="Plywood",VLOOKUP($B33,'Pwood & PB List'!$B$4:$V$158,9,FALSE),IF('Summary Sheet'!$M$4="PB w/ Wood Drawers",VLOOKUP($B33,'Pwood & PB List'!$B$4:$V$158,13,FALSE),IF('Summary Sheet'!$M$4="PB w/ PB Drawers",VLOOKUP($B33,'Pwood & PB List'!$B$4:$V$158,17,FALSE)))) -> 1728.105 | D33: =CONCATENATE("GLW-",B33) -> GLW-3DB30 | E33: =IF('Summary Sheet'!$M$4="Plywood",VLOOKUP($B33,'Pwood & PB List'!$B$4:$V$158,10,FALSE),IF('Summary Sheet'!$M$4="PB w/ Wood Drawers",VLOOKUP($B33,'Pwood & PB List'!$B$4:$V$158,14,FALSE),IF('Summary Sheet'!$M$4="PB w/ PB Drawers",VLOOKUP($B33,'Pwood & PB List'!$B$4:$V$158,18,FALSE)))) -> 1682.565 | F33: =CONCATENATE("SLO-",B33) -> SLO-3DB30 | G33: =IF('Summary Sheet'!$M$4="Plywood",VLOOKUP($B33,'Pwood & PB List'!$B$4:$V$158,11,FALSE),IF('Summary Sheet'!$M$4="PB w/ Wood Drawers",VLOOKUP($B33,'Pwood & PB List'!$B$4:$V$158,15,FALSE),IF('Summary Sheet'!$M$4="PB w/ PB Drawers",VLOOKUP($B33,'Pwood & PB List'!$B$4:$V$158,19,FALSE)))) -> 1634.035 | H33: =CONCATENATE("BLW-",B33) -> BLW-3DB30 | I33: =IF('Summary Sheet'!$M$4="Plywood",VLOOKUP($B33,'Pwood & PB List'!$B$4:$V$158,10,FALSE),IF('Summary Sheet'!$M$4="PB w/ Wood Drawers",VLOOKUP($B33,'Pwood & PB List'!$B$4:$V$158,14,FALSE),IF('Summary Sheet'!$M$4="PB w/ PB Drawers",VLOOKUP($B33,'Pwood & PB List'!$B$4:$V$158,18,FALSE)))) -> 1682.565 | J33: =CONCATENATE("WEO-",B33) -> WEO-3DB30 | K33: =IF('Summary Sheet'!$M$4="Plywood",VLOOKUP($B33,'Pwood & PB List'!$B$4:$V$158,9,FALSE),IF('Summary Sheet'!$M$4="PB w/ Wood Drawers",VLOOKUP($B33,'Pwood & PB List'!$B$4:$V$158,13,FALSE),IF('Summary Sheet'!$M$4="PB w/ PB Drawers",VLOOKUP($B33,'Pwood & PB List'!$B$4:$V$158,17,FALSE)))) -> 1728.105 | L33: =CONCATENATE("GLG-",B33) -> GLG-3DB30 | M33: =IF('Summary Sheet'!$M$4="Plywood",VLOOKUP($B33,'Pwood & PB List'!$B$4:$V$158,12,FALSE),IF('Summary Sheet'!$M$4="PB w/ Wood Drawers",VLOOKUP($B33,'Pwood & PB List'!$B$4:$V$158,16,FALSE),IF('Summary Sheet'!$M$4="PB w/ PB Drawers",VLOOKUP($B33,'Pwood & PB List'!$B$4:$V$158,20,FALSE)))) -> 1579.41 | N33: =CONCATENATE("NAO-",B33) -> NAO-3DB30 | O33: =IF('Summary Sheet'!$M$4="Plywood",VLOOKUP($B33,'Pwood & PB List'!$B$4:$V$158,12,FALSE),IF('Summary Sheet'!$M$4="PB w/ Wood Drawers",VLOOKUP($B33,'Pwood & PB List'!$B$4:$V$158,16,FALSE),IF('Summary Sheet'!$M$4="PB w/ PB Drawers",VLOOKUP($B33,'Pwood & PB List'!$B$4:$V$158,20,FALSE)))) -> 1579.41 | P33: =CONCATENATE("WHO-",B33) -> WHO-3DB30 | Q33: =IF('Summary Sheet'!$M$4="Plywood",VLOOKUP($B33,'Pwood & PB List'!$B$4:$V$158,9,FALSE),IF('Summary Sheet'!$M$4="PB w/ Wood Drawers",VLOOKUP($B33,'Pwood & PB List'!$B$4:$V$158,13,FALSE),IF('Summary Sheet'!$M$4="PB w/ PB Drawers",VLOOKUP($B33,'Pwood & PB List'!$B$4:$V$158,17,FALSE)))) -> 1728.105 | R33: =CONCATENATE("MAW-",B33) -> MAW-3DB30 | S33: =IF('Summary Sheet'!$M$4="Plywood",VLOOKUP($B33,'Pwood & PB List'!$B$4:$V$158,9,FALSE),IF('Summary Sheet'!$M$4="PB w/ Wood Drawers",VLOOKUP($B33,'Pwood & PB List'!$B$4:$V$158,13,FALSE),IF('Summary Sheet'!$M$4="PB w/ PB Drawers",VLOOKUP($B33,'Pwood & PB List'!$B$4:$V$158,17,FALSE)))) -> 1728.105 | T33: =CONCATENATE("MAG-",B33) -> MAG-3DB30 | U33: =IF('Summary Sheet'!$M$4="Plywood",VLOOKUP($B33,'Pwood & PB List'!$B$4:$V$158,9,FALSE),IF('Summary Sheet'!$M$4="PB w/ Wood Drawers",VLOOKUP($B33,'Pwood & PB List'!$B$4:$V$158,13,FALSE),IF('Summary Sheet'!$M$4="PB w/ PB Drawers",VLOOKUP($B33,'Pwood & PB List'!$B$4:$V$158,17,FALSE)))) -> 1728.105 | V33: =CONCATENATE("MAB-",B33) -> MAB-3DB30 | W33: =IF('Summary Sheet'!$M$4="Plywood",VLOOKUP($B33,'Pwood & PB List'!$B$4:$V$158,9,FALSE),IF('Summary Sheet'!$M$4="PB w/ Wood Drawers",VLOOKUP($B33,'Pwood & PB List'!$B$4:$V$158,13,FALSE),IF('Summary Sheet'!$M$4="PB w/ PB Drawers",VLOOKUP($B33,'Pwood & PB List'!$B$4:$V$158,17,FALSE)))) -> 1728.105 | X33: =CONCATENATE("GLB-",B33) -> GLB-3DB30 | Y33: 3
A34: 36" Drawer Base Cabinet: 3 Drawers | B34: 3DB36 | C34: =IF('Summary Sheet'!$M$4="Plywood",VLOOKUP($B34,'Pwood & PB List'!$B$4:$V$158,9,FALSE),IF('Summary Sheet'!$M$4="PB w/ Wood Drawers",VLOOKUP($B34,'Pwood & PB List'!$B$4:$V$158,13,FALSE),IF('Summary Sheet'!$M$4="PB w/ PB Drawers",VLOOKUP($B34,'Pwood & PB List'!$B$4:$V$158,17,FALSE)))) -> 1927.515 | D34: =CONCATENATE("GLW-",B34) -> GLW-3DB36 | E34: =IF('Summary Sheet'!$M$4="Plywood",VLOOKUP($B34,'Pwood & PB List'!$B$4:$V$158,10,FALSE),IF('Summary Sheet'!$M$4="PB w/ Wood Drawers",VLOOKUP($B34,'Pwood & PB List'!$B$4:$V$158,14,FALSE),IF('Summary Sheet'!$M$4="PB w/ PB Drawers",VLOOKUP($B34,'Pwood & PB List'!$B$4:$V$158,18,FALSE)))) -> 1872.775 | F34: =CONCATENATE("SLO-",B34) -> SLO-3DB36 | G34: =IF('Summary Sheet'!$M$4="Plywood",VLOOKUP($B34,'Pwood & PB List'!$B$4:$V$158,11,FALSE),IF('Summary Sheet'!$M$4="PB w/ Wood Drawers",VLOOKUP($B34,'Pwood & PB List'!$B$4:$V$158,15,FALSE),IF('Summary Sheet'!$M$4="PB w/ PB Drawers",VLOOKUP($B34,'Pwood & PB List'!$B$4:$V$158,19,FALSE)))) -> 1814.47 | H34: =CONCATENATE("BLW-",B34) -> BLW-3DB36 | I34: =IF('Summary Sheet'!$M$4="Plywood",VLOOKUP($B34,'Pwood & PB List'!$B$4:$V$158,10,FALSE),IF('Summary Sheet'!$M$4="PB w/ Wood Drawers",VLOOKUP($B34,'Pwood & PB List'!$B$4:$V$158,14,FALSE),IF('Summary Sheet'!$M$4="PB w/ PB Drawers",VLOOKUP($B34,'Pwood & PB List'!$B$4:$V$158,18,FALSE)))) -> 1872.775 | J34: =CONCATENATE("WEO-",B34) -> WEO-3DB36 | K34: =IF('Summary Sheet'!$M$4="Plywood",VLOOKUP($B34,'Pwood & PB List'!$B$4:$V$158,9,FALSE),IF('Summary Sheet'!$M$4="PB w/ Wood Drawers",VLOOKUP($B34,'Pwood & PB List'!$B$4:$V$158,13,FALSE),IF('Summary Sheet'!$M$4="PB w/ PB Drawers",VLOOKUP($B34,'Pwood & PB List'!$B$4:$V$158,17,FALSE)))) -> 1927.515 | L34: =CONCATENATE("GLG-",B34) -> GLG-3DB36 | M34: =IF('Summary Sheet'!$M$4="Plywood",VLOOKUP($B34,'Pwood & PB List'!$B$4:$V$158,12,FALSE),IF('Summary Sheet'!$M$4="PB w/ Wood Drawers",VLOOKUP($B34,'Pwood & PB List'!$B$4:$V$158,16,FALSE),IF('Summary Sheet'!$M$4="PB w/ PB Drawers",VLOOKUP($B34,'Pwood & PB List'!$B$4:$V$158,20,FALSE)))) -> 1748.92 | N34: =CONCATENATE("NAO-",B34) -> NAO-3DB36 | O34: =IF('Summary Sheet'!$M$4="Plywood",VLOOKUP($B34,'Pwood & PB List'!$B$4:$V$158,12,FALSE),IF('Summary Sheet'!$M$4="PB w/ Wood Drawers",VLOOKUP($B34,'Pwood & PB List'!$B$4:$V$158,16,FALSE),IF('Summary Sheet'!$M$4="PB w/ PB Drawers",VLOOKUP($B34,'Pwood & PB List'!$B$4:$V$158,20,FALSE)))) -> 1748.92 | P34: =CONCATENATE("WHO-",B34) -> WHO-3DB36 | Q34: =IF('Summary Sheet'!$M$4="Plywood",VLOOKUP($B34,'Pwood & PB List'!$B$4:$V$158,9,FALSE),IF('Summary Sheet'!$M$4="PB w/ Wood Drawers",VLOOKUP($B34,'Pwood & PB List'!$B$4:$V$158,13,FALSE),IF('Summary Sheet'!$M$4="PB w/ PB Drawers",VLOOKUP($B34,'Pwood & PB List'!$B$4:$V$158,17,FALSE)))) -> 1927.515 | R34: =CONCATENATE("MAW-",B34) -> MAW-3DB36 | S34: =IF('Summary Sheet'!$M$4="Plywood",VLOOKUP($B34,'Pwood & PB List'!$B$4:$V$158,9,FALSE),IF('Summary Sheet'!$M$4="PB w/ Wood Drawers",VLOOKUP($B34,'Pwood & PB List'!$B$4:$V$158,13,FALSE),IF('Summary Sheet'!$M$4="PB w/ PB Drawers",VLOOKUP($B34,'Pwood & PB List'!$B$4:$V$158,17,FALSE)))) -> 1927.515 | T34: =CONCATENATE("MAG-",B34) -> MAG-3DB36 | U34: =IF('Summary Sheet'!$M$4="Plywood",VLOOKUP($B34,'Pwood & PB List'!$B$4:$V$158,9,FALSE),IF('Summary Sheet'!$M$4="PB w/ Wood Drawers",VLOOKUP($B34,'Pwood & PB List'!$B$4:$V$158,13,FALSE),IF('Summary Sheet'!$M$4="PB w/ PB Drawers",VLOOKUP($B34,'Pwood & PB List'!$B$4:$V$158,17,FALSE)))) -> 1927.515 | V34: =CONCATENATE("MAB-",B34) -> MAB-3DB36 | W34: =IF('Summary Sheet'!$M$4="Plywood",VLOOKUP($B34,'Pwood & PB List'!$B$4:$V$158,9,FALSE),IF('Summary Sheet'!$M$4="PB w/ Wood Drawers",VLOOKUP($B34,'Pwood & PB List'!$B$4:$V$158,13,FALSE),IF('Summary Sheet'!$M$4="PB w/ PB Drawers",VLOOKUP($B34,'Pwood & PB List'!$B$4:$V$158,17,FALSE)))) -> 1927.515 | X34: =CONCATENATE("GLB-",B34) -> GLB-3DB36 | Y34: 3
A35: Drawer Base Cabinets with 2 Drawers, 24" Depth
A36: 24" Drawer Base Cabinet: 2 Drawers | B36: 2DB24 | C36: =IF('Summary Sheet'!$M$4="Plywood",VLOOKUP($B36,'Pwood & PB List'!$B$4:$V$158,9,FALSE),IF('Summary Sheet'!$M$4="PB w/ Wood Drawers",VLOOKUP($B36,'Pwood & PB List'!$B$4:$V$158,13,FALSE),IF('Summary Sheet'!$M$4="PB w/ PB Drawers",VLOOKUP($B36,'Pwood & PB List'!$B$4:$V$158,17,FALSE)))) -> 1305.94 | D36: =CONCATENATE("GLW-",B36) -> GLW-2DB24 | E36: =IF('Summary Sheet'!$M$4="Plywood",VLOOKUP($B36,'Pwood & PB List'!$B$4:$V$158,10,FALSE),IF('Summary Sheet'!$M$4="PB w/ Wood Drawers",VLOOKUP($B36,'Pwood & PB List'!$B$4:$V$158,14,FALSE),IF('Summary Sheet'!$M$4="PB w/ PB Drawers",VLOOKUP($B36,'Pwood & PB List'!$B$4:$V$158,18,FALSE)))) -> 1269.37 | F36: =CONCATENATE("SLO-",B36) -> SLO-2DB24 | G36: =IF('Summary Sheet'!$M$4="Plywood",VLOOKUP($B36,'Pwood & PB List'!$B$4:$V$158,11,FALSE),IF('Summary Sheet'!$M$4="PB w/ Wood Drawers",VLOOKUP($B36,'Pwood & PB List'!$B$4:$V$158,15,FALSE),IF('Summary Sheet'!$M$4="PB w/ PB Drawers",VLOOKUP($B36,'Pwood & PB List'!$B$4:$V$158,19,FALSE)))) -> 1230.5 | H36: =CONCATENATE("BLW-",B36) -> BLW-2DB24 | I36: =IF('Summary Sheet'!$M$4="Plywood",VLOOKUP($B36,'Pwood & PB List'!$B$4:$V$158,10,FALSE),IF('Summary Sheet'!$M$4="PB w/ Wood Drawers",VLOOKUP($B36,'Pwood & PB List'!$B$4:$V$158,14,FALSE),IF('Summary Sheet'!$M$4="PB w/ PB Drawers",VLOOKUP($B36,'Pwood & PB List'!$B$4:$V$158,18,FALSE)))) -> 1269.37 | J36: =CONCATENATE("WEO-",B36) -> WEO-2DB24 | K36: =IF('Summary Sheet'!$M$4="Plywood",VLOOKUP($B36,'Pwood & PB List'!$B$4:$V$158,9,FALSE),IF('Summary Sheet'!$M$4="PB w/ Wood Drawers",VLOOKUP($B36,'Pwood & PB List'!$B$4:$V$158,13,FALSE),IF('Summary Sheet'!$M$4="PB w/ PB Drawers",VLOOKUP($B36,'Pwood & PB List'!$B$4:$V$158,17,FALSE)))) -> 1305.94 | L36: =CONCATENATE("GLG-",B36) -> GLG-2DB24 | M36: =IF('Summary Sheet'!$M$4="Plywood",VLOOKUP($B36,'Pwood & PB List'!$B$4:$V$158,12,FALSE),IF('Summary Sheet'!$M$4="PB w/ Wood Drawers",VLOOKUP($B36,'Pwood & PB List'!$B$4:$V$158,16,FALSE),IF('Summary Sheet'!$M$4="PB w/ PB Drawers",VLOOKUP($B36,'Pwood & PB List'!$B$4:$V$158,20,FALSE)))) -> 1186.57 | N36: =CONCATENATE("NAO-",B36) -> NAO-2DB24 | O36: =IF('Summary Sheet'!$M$4="Plywood",VLOOKUP($B36,'Pwood & PB List'!$B$4:$V$158,12,FALSE),IF('Summary Sheet'!$M$4="PB w/ Wood Drawers",VLOOKUP($B36,'Pwood & PB List'!$B$4:$V$158,16,FALSE),IF('Summary Sheet'!$M$4="PB w/ PB Drawers",VLOOKUP($B36,'Pwood & PB List'!$B$4:$V$158,20,FALSE)))) -> 1186.57 | P36: =CONCATENATE("WHO-",B36) -> WHO-2DB24 | Q36: =IF('Summary Sheet'!$M$4="Plywood",VLOOKUP($B36,'Pwood & PB List'!$B$4:$V$158,9,FALSE),IF('Summary Sheet'!$M$4="PB w/ Wood Drawers",VLOOKUP($B36,'Pwood & PB List'!$B$4:$V$158,13,FALSE),IF('Summary Sheet'!$M$4="PB w/ PB Drawers",VLOOKUP($B36,'Pwood & PB List'!$B$4:$V$158,17,FALSE)))) -> 1305.94 | R36: =CONCATENATE("MAW-",B36) -> MAW-2DB24 | S36: =IF('Summary Sheet'!$M$4="Plywood",VLOOKUP($B36,'Pwood & PB List'!$B$4:$V$158,9,FALSE),IF('Summary Sheet'!$M$4="PB w/ Wood Drawers",VLOOKUP($B36,'Pwood & PB List'!$B$4:$V$158,13,FALSE),IF('Summary Sheet'!$M$4="PB w/ PB Drawers",VLOOKUP($B36,'Pwood & PB List'!$B$4:$V$158,17,FALSE)))) -> 1305.94 | T36: =CONCATENATE("MAG-",B36) -> MAG-2DB24 | U36: =IF('Summary Sheet'!$M$4="Plywood",VLOOKUP($B36,'Pwood & PB List'!$B$4:$V$158,9,FALSE),IF('Summary Sheet'!$M$4="PB w/ Wood Drawers",VLOOKUP($B36,'Pwood & PB List'!$B$4:$V$158,13,FALSE),IF('Summary Sheet'!$M$4="PB w/ PB Drawers",VLOOKUP($B36,'Pwood & PB List'!$B$4:$V$158,17,FALSE)))) -> 1305.94 | V36: =CONCATENATE("MAB-",B36) -> MAB-2DB24 | W36: =IF('Summary Sheet'!$M$4="Plywood",VLOOKUP($B36,'Pwood & PB List'!$B$4:$V$158,9,FALSE),IF('Summary Sheet'!$M$4="PB w/ Wood Drawers",VLOOKUP($B36,'Pwood & PB List'!$B$4:$V$158,13,FALSE),IF('Summary Sheet'!$M$4="PB w/ PB Drawers",VLOOKUP($B36,'Pwood & PB List'!$B$4:$V$158,17,FALSE)))) -> 1305.94 | X36: =CONCATENATE("GLB-",B36) -> GLB-2DB24 | Y36: 2
